Workbook
Name _2012.06.11___GFM_Indicator_List: 'Indicator Metadata'!$D$18:$J$36
Name _2012.06.11___GFM_Indicator_List_1: 'Indicator Metadata'!$D$18:$J$36
Name _2012.06.11___GFM_Indicator_List_2: 'Indicator Metadata'!$D$16:$J$36
Name CrisisList: 'Crisis Indicator Data'!$A$13:$A$28
Name CrisisType: VLOOKUP(#REF!,#REF!,2,FALSE)
Name iCrisisType: INDIRECT(CrisisType)
Name iCrisisType: INDIRECT(CrisisType)
Name iCrisisType: INDIRECT(CrisisType)
Name iIcons_a5: INDIRECT(#REF!)
Name iIcons_a8: INDIRECT(#REF!)

Sheet About
A2: release:
A3: 31/01/2022
A4: INFORM SEVERITY INDEX
A5: January 2022
A6: OBJECTIVES AND PROCESS
A7: The INFORM Severity Index summarises a wide range of already existing, quantitative information about crisis severity and presents it in a format that can be used more easily in decision-making. It aggregates information from a range of credible, publicly available sources. Human analysts collect the data and enter it into the Index. It is intended to contribute to: - A shared and objective understanding of crisis severity; - Decisions on the allocation of resources in a way that is proportionate with crisis severity; - Justify and advocate for action, especially in the case of forgotten or unrecognised crises; - Monitor trends in crisis severity over time
A8: ANALYTICAL FRAMEWORK AND METHODOLOGY
A9: The INFORM Severity Index is a composite indicator that measures the severity of humanitarian crises against a common scale: It is a composite indicator that aggregates data from various sources to categorise all crises into five levels of severity: - Very high (5); High (4); Medium (3); Low (2); Very low (1) The Index covers: - The impact of the crisis itself, in terms of the scope of its geographical, human and physical effects; - The conditions and status of the people affected, including information about the distribution of severity (i.e. the number of people in each category of severity within a crisis); - The complexity of the crisis, in terms of factors that affect its mitigation or resolution. The results are provided by crisis and by country. A crisis is defined as an event and a location. There may be more than one crisis per country. Sometimes a crisis may be defined as a country. It is also possible to access the values for different levels of the analytical framework, to better understand the main drivers of a crisis. All the underlying data, metadata and methodology are publicly available.
A11: DATA SOURCES, USE AND LIMITATIONS
A12: The INFORM Severity aggregates information from a range of credible, publicly available sources, such as UN agencies, governments and other multilateral organisations. The country’s Humanitarian Needs Overview (HNO) is used if one is available. The INFORM Severity Index can be used to support decisions that require an understanding of the severity of crises globally or to understand changes in crisis severity over time. It should not be used for decisions about the operational response to a specific crisis. Crisis-specific information like needs assessments and appeals should be used to support these decisions. The INFORM Severity Index is only one source of information that can support decisions about humanitarian crises. It should typically be complemented by other sources. Due to the dynamic and chaotic nature of humanitarian emergencies and the lack of a globally systematic approach to data collection, imperfect information is necessarily used in the Index. Expert judgement is involved in deciding what data to include. A reliability estimate is provided for each crisis. The results spreadsheet contains metadata, showing the sources and dates of included figures, as well as key assessments or judgements made in their inclusion.
A13: FURTHER INFORMATION
A14: The development of the INFORM Severity Index was initiated and guided by the INFORM initiative - a multistakeholder partnership of humanitarian and development organisations, donors and technical partners - together with other interested organisations. The European Commission Joint Research Centre is responsible for the methodology. ACAPS is responsible for the data collection and analysis. OCHA is the overall coordinator of INFORM. We welcome all feedback and questions relating to the INFORM Severity INDEX. Please send them to contact@inform.index.org.
... A18: Citation INFORM. 2022. INFORM Seveirty Index January 2022. https://drmkc.jrc.ec.europa.eu/inform-index/INFORM-Severity. INFORM is a collaboration of the Inter-Agency Standing Committee Reference Group on Risk, Early Warning and Preparedness and the European Commission. The European Commission Joint Research Centre is responsible for the methodology. ACAPS is responsible for the data collection and analysis. OCHA is the overall coordinator of INFORM.

Sheet INFORM Severity - hidden
A2: CRISIS | B2: Website name | C2: CRISIS ID | D2: COUNTRY | E2: ISO3 | F2: TYPE OF CRISIS | G2: INFORM Severity Index | H2: INFORM Severity category | I2: INFORM Severity category | J2: Trend (last 3 months) | K2: Reliability | L2: Impact of the crisis | M2: Geographical Impact | N2: Human Impact | O2: Conditions of people affected | P2: People in need | Q2: Concentration of conditions | R2: Complexity of the crisis | S2: Society and safety | T2: Operating environment | U2: Regions | V2: Last updated
A3: Weights | R3: 0.3
A4: (a-z) | E4: (a-z) | G4: (1-5) | H4: (1-5) | I4: (Very Low-Very High) | J4: (Decreasing-Stable-Increasing) | K4: (Very Low-Very High) | L4: (1-5) | M4: (1-5) | N4: (1-5) | O4: (1-5) | P4: (1-5) | Q4: (1-5) | R4: (1-5) | S4: (1-5) | T4: (1-5)
A5: ='Crisis Indicator Data'!A3 -> Complex crisis in Afghanistan | B5: =Lists!G3 -> Complex crisis | C5: ='Crisis Indicator Data'!C3 -> AFG001 | D5: ='Crisis Indicator Data'!D3 -> Afghanistan | E5: ='Crisis Indicator Data'!E3 -> AFG | F5: ='Crisis Indicator Data'!B3 -> Complex crisis | G5: =IF(OR(O5="x",L5="x"),"x",ROUND((5-GEOMEAN(((5-L5)/5*4+1),((5-O5)/5*4+1),((5-O5)/5*4+1)))/4*3.5+R5*0.3,1)) -> 4.7 | H5: =IF(G5="x","x",ROUNDUP(G5,0)) -> 5 | I5: =IF(O5="x","x",IF(L5="x","x",(IF(H5=5,"Very High",IF(H5=4,"High",IF(H5=3,"Medium",IF(H5=2,"Low","Very Low"))))))) -> Very High | J5: =INDEX(Trends!$D$3:$D$404,MATCH(C5,Trends!$C$3:$C$404,0)) -> Stable | K5: =IF(Reliability!B3="x","x",(IF(ROUNDUP(Reliability!B3,0)=1,"Very High",IF(ROUNDUP(Reliability!B3,0)=2,"High",IF(ROUNDUP(Reliability!B3,0)=3,"Medium",IF(ROUNDUP(Reliability!B3,0)=4,"Low","Very Low")))))) -> High | L5: =IF(OR(N5="x",M5="x"),"x",ROUND((5-GEOMEAN(((5-M5)/5*4+1),((5-N5)/5*4+1),((5-N5)/5*4+1)))/4*5,1)) -> 4.8 | M5: ='Impact of the crisis'!N6 -> 4.9 | N5: ='Impact of the crisis'!AB6 -> 4.8 | O5: ='Conditions of people affected'!R6 -> 4.5 | P5: ='Conditions of people affected'!K6 -> 5 | Q5: ='Conditions of people affected'!Q6 -> 4 | R5: =IF(OR(T5="x",S5="x"),S5,ROUND((5-GEOMEAN(((5-S5)/5*4+1),((5-T5)/5*4+1)))/4*5,1)) -> 4.9 | S5: ='Complexity of the crisis'!X6 -> 4.8 | T5: ='Complexity of the crisis'!AN6 -> 5 | U5: =VLOOKUP(C5,Lists!$C$3:$E$160,3,FALSE) -> Asia | V5: 44571
A6: ='Crisis Indicator Data'!A4 -> Drought in South-West Angola | B6: =Lists!G4 -> Drought in South-West | C6: ='Crisis Indicator Data'!C4 -> AGO002 | D6: ='Crisis Indicator Data'!D4 -> Angola | E6: ='Crisis Indicator Data'!E4 -> AGO | F6: ='Crisis Indicator Data'!B4 -> Food Security | G6: =IF(OR(O6="x",L6="x"),"x",ROUND((5-GEOMEAN(((5-L6)/5*4+1),((5-O6)/5*4+1),((5-O6)/5*4+1)))/4*3.5+R6*0.3,1)) -> 3.2 | H6: =IF(G6="x","x",ROUNDUP(G6,0)) -> 4 | I6: =IF(O6="x","x",IF(L6="x","x",(IF(H6=5,"Very High",IF(H6=4,"High",IF(H6=3,"Medium",IF(H6=2,"Low","Very Low"))))))) -> High | J6: =INDEX(Trends!$D$3:$D$404,MATCH(C6,Trends!$C$3:$C$404,0)) -> - | K6: =IF(Reliability!B4="x","x",(IF(ROUNDUP(Reliability!B4,0)=1,"Very High",IF(ROUNDUP(Reliability!B4,0)=2,"High",IF(ROUNDUP(Reliability!B4,0)=3,"Medium",IF(ROUNDUP(Reliability!B4,0)=4,"Low","Very Low")))))) -> Very High | L6: =IF(OR(N6="x",M6="x"),"x",ROUND((5-GEOMEAN(((5-M6)/5*4+1),((5-N6)/5*4+1),((5-N6)/5*4+1)))/4*5,1)) -> 2 | M6: ='Impact of the crisis'!N7 -> 1.7 | N6: ='Impact of the crisis'!AB7 -> 2.2 | O6: ='Conditions of people affected'!R7 -> 3.8 | P6: ='Conditions of people affected'!K7 -> 3.6 | Q6: ='Conditions of people affected'!Q7 -> 4 | R6: =IF(OR(T6="x",S6="x"),S6,ROUND((5-GEOMEAN(((5-S6)/5*4+1),((5-T6)/5*4+1)))/4*5,1)) -> 2.9 | S6: ='Complexity of the crisis'!X7 -> 3.6 | T6: ='Complexity of the crisis'!AN7 -> 2 | U6: =VLOOKUP(C6,Lists!$C$3:$E$160,3,FALSE) -> Africa | V6: 44550
A7: ='Crisis Indicator Data'!A5 -> Nagorno-Karabakh Conflict in Armenia | B7: =Lists!G5 -> Nagorno-Karabakh Conflict in Armenia | C7: ='Crisis Indicator Data'!C5 -> ARM002 | D7: ='Crisis Indicator Data'!D5 -> Armenia | E7: ='Crisis Indicator Data'!E5 -> ARM | F7: ='Crisis Indicator Data'!B5 -> Conflict | G7: =IF(OR(O7="x",L7="x"),"x",ROUND((5-GEOMEAN(((5-L7)/5*4+1),((5-O7)/5*4+1),((5-O7)/5*4+1)))/4*3.5+R7*0.3,1)) -> 1.6 | H7: =IF(G7="x","x",ROUNDUP(G7,0)) -> 2 | I7: =IF(O7="x","x",IF(L7="x","x",(IF(H7=5,"Very High",IF(H7=4,"High",IF(H7=3,"Medium",IF(H7=2,"Low","Very Low"))))))) -> Low | J7: =INDEX(Trends!$D$3:$D$404,MATCH(C7,Trends!$C$3:$C$404,0)) -> Decreasing | K7: =IF(Reliability!B5="x","x",(IF(ROUNDUP(Reliability!B5,0)=1,"Very High",IF(ROUNDUP(Reliability!B5,0)=2,"High",IF(ROUNDUP(Reliability!B5,0)=3,"Medium",IF(ROUNDUP(Reliability!B5,0)=4,"Low","Very Low")))))) -> High | L7: =IF(OR(N7="x",M7="x"),"x",ROUND((5-GEOMEAN(((5-M7)/5*4+1),((5-N7)/5*4+1),((5-N7)/5*4+1)))/4*5,1)) -> 2.3 | M7: ='Impact of the crisis'!N8 -> 3.5 | N7: ='Impact of the crisis'!AB8 -> 1.5 | O7: ='Conditions of people affected'!R8 -> 1.2 | P7: ='Conditions of people affected'!K8 -> 1.4 | Q7: ='Conditions of people affected'!Q8 -> 1 | R7: =IF(OR(T7="x",S7="x"),S7,ROUND((5-GEOMEAN(((5-S7)/5*4+1),((5-T7)/5*4+1)))/4*5,1)) -> 1.6 | S7: ='Complexity of the crisis'!X8 -> 2.2 | T7: ='Complexity of the crisis'!AN8 -> 1 | U7: =VLOOKUP(C7,Lists!$C$3:$E$160,3,FALSE) -> Middle east | V7: 44496
A8: ='Crisis Indicator Data'!A6 -> Nagorno-Karabakh conflict in Azerbaijan | B8: =Lists!G6 -> Nagorno-Karabakh conflict in Azerbaijan | C8: ='Crisis Indicator Data'!C6 -> AZE002 | D8: ='Crisis Indicator Data'!D6 -> Azerbaijan | E8: ='Crisis Indicator Data'!E6 -> AZE | F8: ='Crisis Indicator Data'!B6 -> Conflict | G8: =IF(OR(O8="x",L8="x"),"x",ROUND((5-GEOMEAN(((5-L8)/5*4+1),((5-O8)/5*4+1),((5-O8)/5*4+1)))/4*3.5+R8*0.3,1)) -> x | H8: =IF(G8="x","x",ROUNDUP(G8,0)) -> x | I8: =IF(O8="x","x",IF(L8="x","x",(IF(H8=5,"Very High",IF(H8=4,"High",IF(H8=3,"Medium",IF(H8=2,"Low","Very Low"))))))) -> x | J8: =INDEX(Trends!$D$3:$D$404,MATCH(C8,Trends!$C$3:$C$404,0)) -> - | K8: =IF(Reliability!B6="x","x",(IF(ROUNDUP(Reliability!B6,0)=1,"Very High",IF(ROUNDUP(Reliability!B6,0)=2,"High",IF(ROUNDUP(Reliability!B6,0)=3,"Medium",IF(ROUNDUP(Reliability!B6,0)=4,"Low","Very Low")))))) -> Very Low | L8: =IF(OR(N8="x",M8="x"),"x",ROUND((5-GEOMEAN(((5-M8)/5*4+1),((5-N8)/5*4+1),((5-N8)/5*4+1)))/4*5,1)) -> 3.1 | M8: ='Impact of the crisis'!N9 -> 2.5 | N8: ='Impact of the crisis'!AB9 -> 3.4 | O8: ='Conditions of people affected'!R9 -> x | P8: ='Conditions of people affected'!K9 -> x | Q8: ='Conditions of people affected'!Q9 -> x | R8: =IF(OR(T8="x",S8="x"),S8,ROUND((5-GEOMEAN(((5-S8)/5*4+1),((5-T8)/5*4+1)))/4*5,1)) -> 3.3 | S8: ='Complexity of the crisis'!X9 -> 4 | T8: ='Complexity of the crisis'!AN9 -> 2.5 | U8: =VLOOKUP(C8,Lists!$C$3:$E$160,3,FALSE) -> Middle east | V8: 44496
A9: ='Crisis Indicator Data'!A7 -> Complex in Burundi | B9: =Lists!G7 -> Complex crisis | C9: ='Crisis Indicator Data'!C7 -> BDI001 | D9: ='Crisis Indicator Data'!D7 -> Burundi | E9: ='Crisis Indicator Data'!E7 -> BDI | F9: ='Crisis Indicator Data'!B7 -> Complex crisis | G9: =IF(OR(O9="x",L9="x"),"x",ROUND((5-GEOMEAN(((5-L9)/5*4+1),((5-O9)/5*4+1),((5-O9)/5*4+1)))/4*3.5+R9*0.3,1)) -> 3.9 | H9: =IF(G9="x","x",ROUNDUP(G9,0)) -> 4 | I9: =IF(O9="x","x",IF(L9="x","x",(IF(H9=5,"Very High",IF(H9=4,"High",IF(H9=3,"Medium",IF(H9=2,"Low","Very Low"))))))) -> High | J9: =INDEX(Trends!$D$3:$D$404,MATCH(C9,Trends!$C$3:$C$404,0)) -> Stable | K9: =IF(Reliability!B7="x","x",(IF(ROUNDUP(Reliability!B7,0)=1,"Very High",IF(ROUNDUP(Reliability!B7,0)=2,"High",IF(ROUNDUP(Reliability!B7,0)=3,"Medium",IF(ROUNDUP(Reliability!B7,0)=4,"Low","Very Low")))))) -> Medium | L9: =IF(OR(N9="x",M9="x"),"x",ROUND((5-GEOMEAN(((5-M9)/5*4+1),((5-N9)/5*4+1),((5-N9)/5*4+1)))/4*5,1)) -> 3.9 | M9: ='Impact of the crisis'!N10 -> 4 | N9: ='Impact of the crisis'!AB10 -> 3.8 | O9: ='Conditions of people affected'!R10 -> 4 | P9: ='Conditions of people affected'!K10 -> 4 | Q9: ='Conditions of people affected'!Q10 -> 4 | R9: =IF(OR(T9="x",S9="x"),S9,ROUND((5-GEOMEAN(((5-S9)/5*4+1),((5-T9)/5*4+1)))/4*5,1)) -> 3.6 | S9: ='Complexity of the crisis'!X10 -> 3.6 | T9: ='Complexity of the crisis'!AN10 -> 3.5 | U9: =VLOOKUP(C9,Lists!$C$3:$E$160,3,FALSE) -> Africa | V9: 44498
A10: ='Crisis Indicator Data'!A8 -> Conflict in Burkina Faso | B10: =Lists!G8 -> Conflict | C10: ='Crisis Indicator Data'!C8 -> BFA002 | D10: ='Crisis Indicator Data'!D8 -> Burkina Faso | E10: ='Crisis Indicator Data'!E8 -> BFA | F10: ='Crisis Indicator Data'!B8 -> Conflict | G10: =IF(OR(O10="x",L10="x"),"x",ROUND((5-GEOMEAN(((5-L10)/5*4+1),((5-O10)/5*4+1),((5-O10)/5*4+1)))/4*3.5+R10*0.3,1)) -> 4.1 | H10: =IF(G10="x","x",ROUNDUP(G10,0)) -> 5 | I10: =IF(O10="x","x",IF(L10="x","x",(IF(H10=5,"Very High",IF(H10=4,"High",IF(H10=3,"Medium",IF(H10=2,"Low","Very Low"))))))) -> Very High | J10: =INDEX(Trends!$D$3:$D$404,MATCH(C10,Trends!$C$3:$C$404,0)) -> Stable | K10: =IF(Reliability!B8="x","x",(IF(ROUNDUP(Reliability!B8,0)=1,"Very High",IF(ROUNDUP(Reliability!B8,0)=2,"High",IF(ROUNDUP(Reliability!B8,0)=3,"Medium",IF(ROUNDUP(Reliability!B8,0)=4,"Low","Very Low")))))) -> High | L10: =IF(OR(N10="x",M10="x"),"x",ROUND((5-GEOMEAN(((5-M10)/5*4+1),((5-N10)/5*4+1),((5-N10)/5*4+1)))/4*5,1)) -> 4 | M10: ='Impact of the crisis'!N11 -> 2.5 | N10: ='Impact of the crisis'!AB11 -> 4.5 | O10: ='Conditions of people affected'!R11 -> 4.3 | P10: ='Conditions of people affected'!K11 -> 3.6 | Q10: ='Conditions of people affected'!Q11 -> 5 | R10: =IF(OR(T10="x",S10="x"),S10,ROUND((5-GEOMEAN(((5-S10)/5*4+1),((5-T10)/5*4+1)))/4*5,1)) -> 3.7 | S10: ='Complexity of the crisis'!X11 -> 3.9 | T10: ='Complexity of the crisis'!AN11 -> 3.5 | U10: =VLOOKUP(C10,Lists!$C$3:$E$160,3,FALSE) -> Africa | V10: 44567
A11: ='Crisis Indicator Data'!A9 -> Rohingya refugee crisis | B11: =Lists!G9 -> Rohingya Refugees | C11: ='Crisis Indicator Data'!C9 -> BGD002 | D11: ='Crisis Indicator Data'!D9 -> Bangladesh | E11: ='Crisis Indicator Data'!E9 -> BGD | F11: ='Crisis Indicator Data'!B9 -> International displacement | G11: =IF(OR(O11="x",L11="x"),"x",ROUND((5-GEOMEAN(((5-L11)/5*4+1),((5-O11)/5*4+1),((5-O11)/5*4+1)))/4*3.5+R11*0.3,1)) -> 3.3 | H11: =IF(G11="x","x",ROUNDUP(G11,0)) -> 4 | I11: =IF(O11="x","x",IF(L11="x","x",(IF(H11=5,"Very High",IF(H11=4,"High",IF(H11=3,"Medium",IF(H11=2,"Low","Very Low"))))))) -> High | J11: =INDEX(Trends!$D$3:$D$404,MATCH(C11,Trends!$C$3:$C$404,0)) -> Increasing | K11: =IF(Reliability!B9="x","x",(IF(ROUNDUP(Reliability!B9,0)=1,"Very High",IF(ROUNDUP(Reliability!B9,0)=2,"High",IF(ROUNDUP(Reliability!B9,0)=3,"Medium",IF(ROUNDUP(Reliability!B9,0)=4,"Low","Very Low")))))) -> High | L11: =IF(OR(N11="x",M11="x"),"x",ROUND((5-GEOMEAN(((5-M11)/5*4+1),((5-N11)/5*4+1),((5-N11)/5*4+1)))/4*5,1)) -> 3.4 | M11: ='Impact of the crisis'!N12 -> 0.1 | N11: ='Impact of the crisis'!AB12 -> 4.3 | O11: ='Conditions of people affected'!R12 -> 3.3 | P11: ='Conditions of people affected'!K12 -> 3.6 | Q11: ='Conditions of people affected'!Q12 -> 3 | R11: =IF(OR(T11="x",S11="x"),S11,ROUND((5-GEOMEAN(((5-S11)/5*4+1),((5-T11)/5*4+1)))/4*5,1)) -> 3.2 | S11: ='Complexity of the crisis'!X12 -> 3.3 | T11: ='Complexity of the crisis'!AN12 -> 3 | U11: =VLOOKUP(C11,Lists!$C$3:$E$160,3,FALSE) -> Asia | V11: 44585
A12: ='Crisis Indicator Data'!A10 -> Country level Brazil | B12: =Lists!G10 -> Country level | C12: ='Crisis Indicator Data'!C10 -> BRA001 | D12: ='Crisis Indicator Data'!D10 -> Brazil | E12: ='Crisis Indicator Data'!E10 -> BRA | F12: ='Crisis Indicator Data'!B10 -> Multiple crises country | G12: =IF(OR(O12="x",L12="x"),"x",ROUND((5-GEOMEAN(((5-L12)/5*4+1),((5-O12)/5*4+1),((5-O12)/5*4+1)))/4*3.5+R12*0.3,1)) -> 2.3 | H12: =IF(G12="x","x",ROUNDUP(G12,0)) -> 3 | I12: =IF(O12="x","x",IF(L12="x","x",(IF(H12=5,"Very High",IF(H12=4,"High",IF(H12=3,"Medium",IF(H12=2,"Low","Very Low"))))))) -> Medium | J12: =INDEX(Trends!$D$3:$D$404,MATCH(C12,Trends!$C$3:$C$404,0)) -> - | K12: =IF(Reliability!B10="x","x",(IF(ROUNDUP(Reliability!B10,0)=1,"Very High",IF(ROUNDUP(Reliability!B10,0)=2,"High",IF(ROUNDUP(Reliability!B10,0)=3,"Medium",IF(ROUNDUP(Reliability!B10,0)=4,"Low","Very Low")))))) -> High | L12: =IF(OR(N12="x",M12="x"),"x",ROUND((5-GEOMEAN(((5-M12)/5*4+1),((5-N12)/5*4+1),((5-N12)/5*4+1)))/4*5,1)) -> 2.6 | M12: ='Impact of the crisis'!N13 -> 2.9 | N12: ='Impact of the crisis'!AB13 -> 2.5 | O12: ='Conditions of people affected'!R13 -> 1.9 | P12: ='Conditions of people affected'!K13 -> 2.8 | Q12: ='Conditions of people affected'!Q13 -> 1 | R12: =IF(OR(T12="x",S12="x"),S12,ROUND((5-GEOMEAN(((5-S12)/5*4+1),((5-T12)/5*4+1)))/4*5,1)) -> 2.8 | S12: ='Complexity of the crisis'!X13 -> 3.4 | T12: ='Complexity of the crisis'!AN13 -> 2 | U12: =VLOOKUP(C12,Lists!$C$3:$E$160,3,FALSE) -> Americas | V12: 44572
A13: ='Crisis Indicator Data'!A11 -> Venezuela displacement in Brazil | B13: =Lists!G11 -> Venezuelan refugees | C13: ='Crisis Indicator Data'!C11 -> BRA002 | D13: ='Crisis Indicator Data'!D11 -> Brazil | E13: ='Crisis Indicator Data'!E11 -> BRA | F13: ='Crisis Indicator Data'!B11 -> International displacement | G13: =IF(OR(O13="x",L13="x"),"x",ROUND((5-GEOMEAN(((5-L13)/5*4+1),((5-O13)/5*4+1),((5-O13)/5*4+1)))/4*3.5+R13*0.3,1)) -> 2.6 | H13: =IF(G13="x","x",ROUNDUP(G13,0)) -> 3 | I13: =IF(O13="x","x",IF(L13="x","x",(IF(H13=5,"Very High",IF(H13=4,"High",IF(H13=3,"Medium",IF(H13=2,"Low","Very Low"))))))) -> Medium | J13: =INDEX(Trends!$D$3:$D$404,MATCH(C13,Trends!$C$3:$C$404,0)) -> Decreasing | K13: =IF(Reliability!B11="x","x",(IF(ROUNDUP(Reliability!B11,0)=1,"Very High",IF(ROUNDUP(Reliability!B11,0)=2,"High",IF(ROUNDUP(Reliability!B11,0)=3,"Medium",IF(ROUNDUP(Reliability!B11,0)=4,"Low","Very Low")))))) -> Medium | L13: =IF(OR(N13="x",M13="x"),"x",ROUND((5-GEOMEAN(((5-M13)/5*4+1),((5-N13)/5*4+1),((5-N13)/5*4+1)))/4*5,1)) -> 2.2 | M13: ='Impact of the crisis'!N14 -> 1.1 | N13: ='Impact of the crisis'!AB14 -> 2.6 | O13: ='Conditions of people affected'!R14 -> 2.8 | P13: ='Conditions of people affected'!K14 -> 2.6 | Q13: ='Conditions of people affected'!Q14 -> 3 | R13: =IF(OR(T13="x",S13="x"),S13,ROUND((5-GEOMEAN(((5-S13)/5*4+1),((5-T13)/5*4+1)))/4*5,1)) -> 2.6 | S13: ='Complexity of the crisis'!X14 -> 3.4 | T13: ='Complexity of the crisis'!AN14 -> 1.5 | U13: =VLOOKUP(C13,Lists!$C$3:$E$160,3,FALSE) -> Americas | V13: 44525
A14: ='Crisis Indicator Data'!A12 -> Floods in Bahia and Minas Gerais | B14: =Lists!G12 -> Floods | C14: ='Crisis Indicator Data'!C12 -> BRA003 | D14: ='Crisis Indicator Data'!D12 -> Brazil | E14: ='Crisis Indicator Data'!E12 -> BRA | F14: ='Crisis Indicator Data'!B12 -> Flood | G14: =IF(OR(O14="x",L14="x"),"x",ROUND((5-GEOMEAN(((5-L14)/5*4+1),((5-O14)/5*4+1),((5-O14)/5*4+1)))/4*3.5+R14*0.3,1)) -> 2.1 | H14: =IF(G14="x","x",ROUNDUP(G14,0)) -> 3 | I14: =IF(O14="x","x",IF(L14="x","x",(IF(H14=5,"Very High",IF(H14=4,"High",IF(H14=3,"Medium",IF(H14=2,"Low","Very Low"))))))) -> Medium | J14: =INDEX(Trends!$D$3:$D$404,MATCH(C14,Trends!$C$3:$C$404,0)) -> - | K14: =IF(Reliability!B12="x","x",(IF(ROUNDUP(Reliability!B12,0)=1,"Very High",IF(ROUNDUP(Reliability!B12,0)=2,"High",IF(ROUNDUP(Reliability!B12,0)=3,"Medium",IF(ROUNDUP(Reliability!B12,0)=4,"Low","Very Low")))))) -> High | L14: =IF(OR(N14="x",M14="x"),"x",ROUND((5-GEOMEAN(((5-M14)/5*4+1),((5-N14)/5*4+1),((5-N14)/5*4+1)))/4*5,1)) -> 2.5 | M14: ='Impact of the crisis'!N15 -> 2.9 | N14: ='Impact of the crisis'!AB15 -> 2.3 | O14: ='Conditions of people affected'!R15 -> 1.3 | P14: ='Conditions of people affected'!K15 -> 1.6 | Q14: ='Conditions of people affected'!Q15 -> 1 | R14: =IF(OR(T14="x",S14="x"),S14,ROUND((5-GEOMEAN(((5-S14)/5*4+1),((5-T14)/5*4+1)))/4*5,1)) -> 2.8 | S14: ='Complexity of the crisis'!X15 -> 3.4 | T14: ='Complexity of the crisis'!AN15 -> 2 | U14: =VLOOKUP(C14,Lists!$C$3:$E$160,3,FALSE) -> Americas | V14: 44572
A15: ='Crisis Indicator Data'!A13 -> Complex crisis in CAR | B15: =Lists!G13 -> Complex crisis | C15: ='Crisis Indicator Data'!C13 -> CAF001 | D15: ='Crisis Indicator Data'!D13 -> CAR | E15: ='Crisis Indicator Data'!E13 -> CAF | F15: ='Crisis Indicator Data'!B13 -> Complex crisis | G15: =IF(OR(O15="x",L15="x"),"x",ROUND((5-GEOMEAN(((5-L15)/5*4+1),((5-O15)/5*4+1),((5-O15)/5*4+1)))/4*3.5+R15*0.3,1)) -> 4.3 | H15: =IF(G15="x","x",ROUNDUP(G15,0)) -> 5 | I15: =IF(O15="x","x",IF(L15="x","x",(IF(H15=5,"Very High",IF(H15=4,"High",IF(H15=3,"Medium",IF(H15=2,"Low","Very Low"))))))) -> Very High | J15: =INDEX(Trends!$D$3:$D$404,MATCH(C15,Trends!$C$3:$C$404,0)) -> Stable | K15: =IF(Reliability!B13="x","x",(IF(ROUNDUP(Reliability!B13,0)=1,"Very High",IF(ROUNDUP(Reliability!B13,0)=2,"High",IF(ROUNDUP(Reliability!B13,0)=3,"Medium",IF(ROUNDUP(Reliability!B13,0)=4,"Low","Very Low")))))) -> Medium | L15: =IF(OR(N15="x",M15="x"),"x",ROUND((5-GEOMEAN(((5-M15)/5*4+1),((5-N15)/5*4+1),((5-N15)/5*4+1)))/4*5,1)) -> 4.4 | M15: ='Impact of the crisis'!N16 -> 4.3 | N15: ='Impact of the crisis'!AB16 -> 4.5 | O15: ='Conditions of people affected'!R16 -> 4.05 | P15: ='Conditions of people affected'!K16 -> 4.1 | Q15: ='Conditions of people affected'!Q16 -> 4 | R15: =IF(OR(T15="x",S15="x"),S15,ROUND((5-GEOMEAN(((5-S15)/5*4+1),((5-T15)/5*4+1)))/4*5,1)) -> 4.5 | S15: ='Complexity of the crisis'!X16 -> 4.5 | T15: ='Complexity of the crisis'!AN16 -> 4.5 | U15: =VLOOKUP(C15,Lists!$C$3:$E$160,3,FALSE) -> Africa | V15: 44496
A16: ='Crisis Indicator Data'!A14 -> Multiple crises in Cameroon | B16: =Lists!G14 -> Country level | C16: ='Crisis Indicator Data'!C14 -> CMR001 | D16: ='Crisis Indicator Data'!D14 -> Cameroon | E16: ='Crisis Indicator Data'!E14 -> CMR | F16: ='Crisis Indicator Data'!B14 -> Multiple crises country | G16: =IF(OR(O16="x",L16="x"),"x",ROUND((5-GEOMEAN(((5-L16)/5*4+1),((5-O16)/5*4+1),((5-O16)/5*4+1)))/4*3.5+R16*0.3,1)) -> 4.3 | H16: =IF(G16="x","x",ROUNDUP(G16,0)) -> 5 | I16: =IF(O16="x","x",IF(L16="x","x",(IF(H16=5,"Very High",IF(H16=4,"High",IF(H16=3,"Medium",IF(H16=2,"Low","Very Low"))))))) -> Very High | J16: =INDEX(Trends!$D$3:$D$404,MATCH(C16,Trends!$C$3:$C$404,0)) -> Increasing | K16: =IF(Reliability!B14="x","x",(IF(ROUNDUP(Reliability!B14,0)=1,"Very High",IF(ROUNDUP(Reliability!B14,0)=2,"High",IF(ROUNDUP(Reliability!B14,0)=3,"Medium",IF(ROUNDUP(Reliability!B14,0)=4,"Low","Very Low")))))) -> High | L16: =IF(OR(N16="x",M16="x"),"x",ROUND((5-GEOMEAN(((5-M16)/5*4+1),((5-N16)/5*4+1),((5-N16)/5*4+1)))/4*5,1)) -> 4.1 | M16: ='Impact of the crisis'!N17 -> 4.7 | N16: ='Impact of the crisis'!AB17 -> 3.7 | O16: ='Conditions of people affected'!R17 -> 4.15 | P16: ='Conditions of people affected'!K17 -> 4.3 | Q16: ='Conditions of people affected'!Q17 -> 4 | R16: =IF(OR(T16="x",S16="x"),S16,ROUND((5-GEOMEAN(((5-S16)/5*4+1),((5-T16)/5*4+1)))/4*5,1)) -> 4.6 | S16: ='Complexity of the crisis'!X17 -> 4.2 | T16: ='Complexity of the crisis'!AN17 -> 5 | U16: =VLOOKUP(C16,Lists!$C$3:$E$160,3,FALSE) -> Africa | V16: 44522
... A143: ='Crisis Indicator Data'!A141 -> Complex crisis in Zimbabwe | B143: =Lists!G141 -> Complex crisis | C143: ='Crisis Indicator Data'!C141 -> ZWE001 | D143: ='Crisis Indicator Data'!D141 -> Zimbabwe | E143: ='Crisis Indicator Data'!E141 -> ZWE | F143: ='Crisis Indicator Data'!B141 -> Complex crisis | G143: =IF(OR(O143="x",L143="x"),"x",ROUND((5-GEOMEAN(((5-L143)/5*4+1),((5-O143)/5*4+1),((5-O143)/5*4+1)))/4*3.5+R143*0.3,1)) -> 3.8 | H143: =IF(G143="x","x",ROUNDUP(G143,0)) -> 4 | I143: =IF(O143="x","x",IF(L143="x","x",(IF(H143=5,"Very High",IF(H143=4,"High",IF(H143=3,"Medium",IF(H143=2,"Low","Very Low"))))))) -> High | J143: =INDEX(Trends!$D$3:$D$404,MATCH(C143,Trends!$C$3:$C$404,0)) -> Increasing | K143: =IF(Reliability!B141="x","x",(IF(ROUNDUP(Reliability!B141,0)=1,"Very High",IF(ROUNDUP(Reliability!B141,0)=2,"High",IF(ROUNDUP(Reliability!B141,0)=3,"Medium",IF(ROUNDUP(Reliability!B141,0)=4,"Low","Very Low")))))) -> Very High | L143: =IF(OR(N143="x",M143="x"),"x",ROUND((5-GEOMEAN(((5-M143)/5*4+1),((5-N143)/5*4+1),((5-N143)/5*4+1)))/4*5,1)) -> 3.8 | M143: ='Impact of the crisis'!N144 -> 4.6 | N143: ='Impact of the crisis'!AB144 -> 3.2 | O143: ='Conditions of people affected'!R144 -> 4.35 | P143: ='Conditions of people affected'!K144 -> 4.7 | Q143: ='Conditions of people affected'!Q144 -> 4 | R143: =IF(OR(T143="x",S143="x"),S143,ROUND((5-GEOMEAN(((5-S143)/5*4+1),((5-T143)/5*4+1)))/4*5,1)) -> 3 | S143: ='Complexity of the crisis'!X144 -> 3.5 | T143: ='Complexity of the crisis'!AN144 -> 2.5 | U143: =VLOOKUP(C143,Lists!$C$3:$E$160,3,FALSE) -> Africa | V143: 44591

Sheet INFORM Severity - all crises
A1: ="INFORM Severity Index - all crises. Release: "&About!$A$5&"" -> INFORM Severity Index - all crises. Release: January 2022
A2: CRISIS | B2: CRISIS ID | C2: COUNTRY | D2: ISO3 | E2: TYPE OF CRISIS | F2: INFORM Severity Index | G2: INFORM Severity category | H2: INFORM Severity category | I2: Trend (last 3 months) | J2: Reliability | K2: Impact of the crisis | L2: Geographical | M2: Human | N2: Conditions of people affected | O2: People in need | P2: Concentration of conditions | Q2: Complexity of the crisis | R2: Society and safety | S2: Operating environment | T2: Regions | U2: Last updated
A3: Weights
A4: (a-z) | D4: (a-z) | F4: (1-5) | G4: (1-5) | H4: (Very Low-Very High) | I4: (Decreasing-Stable-Increasing) | J4: (Very Low-Very High) | K4: (1-5) | L4: (1-5) | M4: (1-5) | N4: (1-5) | O4: (1-5) | P4: (1-5) | Q4: (1-5) | R4: (1-5) | S4: (1-5)
A5: {=IFERROR(INDEX(Lists!$B$2:$B$153,SMALL(IF(Lists!$I$2:$I$153="Individual",ROW(Lists!$B$2:$B$153)),ROW(1:1))-1,1),"")} -> Complex crisis in Afghanistan | B5: =VLOOKUP(A5,Lists!$B$2:$G$153,2,FALSE) -> AFG001 | C5: =VLOOKUP(B5,'INFORM Severity - hidden'!$C$5:$D$160,2,FALSE) -> Afghanistan | D5: =VLOOKUP(A5,Lists!$B$2:$G$153,3,FALSE) -> AFG | E5: =VLOOKUP(A5,Lists!$B$2:$G$153,5,FALSE) -> Complex crisis | F5: =IF(OR(N5="x",K5="x"),"x",ROUND((5-GEOMEAN(((5-K5)/5*4+1),((5-N5)/5*4+1),((5-N5)/5*4+1)))/4*3.5+Q5*0.3,1)) -> 4.7 | G5: =IF(F5="x","x",ROUNDUP(F5,0)) -> 5 | H5: =IF(N5="x","x",IF(K5="x","x",(IF(G5=5,"Very High",IF(G5=4,"High",IF(G5=3,"Medium",IF(G5=2,"Low","Very Low"))))))) -> Very High | I5: =INDEX(Trends!$D$3:$D$404,MATCH(B5,Trends!$C$3:$C$404,0)) -> Stable | J5: =VLOOKUP($B5,Reliability!$A$3:$I$170,9,FALSE) -> High | K5: =IF(OR(M5="x",L5="x"),"x",ROUND((5-GEOMEAN(((5-L5)/5*4+1),((5-M5)/5*4+1),((5-M5)/5*4+1)))/4*5,1)) -> 4.8 | L5: =VLOOKUP($B5,'Impact of the crisis'!$C$6:$N$170,12,FALSE) -> 4.9 | M5: =VLOOKUP($B5,'Impact of the crisis'!$C$6:$AB$170,26,FALSE) -> 4.8 | N5: =VLOOKUP($B5,'Conditions of people affected'!$C$6:$R$170,16,FALSE) -> 4.5 | O5: =VLOOKUP($B5,'Conditions of people affected'!$C$6:$R$170,9,FALSE) -> 5 | P5: =VLOOKUP($B5,'Conditions of people affected'!$C$6:$R$170,15,FALSE) -> 4 | Q5: =IF(OR(S5="x",R5="x"),R5,ROUND((5-GEOMEAN(((5-R5)/5*4+1),((5-S5)/5*4+1)))/4*5,1)) -> 4.9 | R5: =VLOOKUP($B5,'Complexity of the crisis'!$C$6:$AN$170,22,FALSE) -> 4.8 | S5: =VLOOKUP($B5,'Complexity of the crisis'!$C$6:$AN$170,38,FALSE) -> 5 | T5: =VLOOKUP(B5,Lists!$C$3:$E$163,3,FALSE) -> Asia | U5: =VLOOKUP(B5,'INFORM Severity - hidden'!$C$5:$V$170,20,FALSE) -> 44571
A6: {=IFERROR(INDEX(Lists!$B$2:$B$153,SMALL(IF(Lists!$I$2:$I$153="Individual",ROW(Lists!$B$2:$B$153)),ROW(2:2))-1,1),"")} -> Drought in South-West Angola | B6: =VLOOKUP(A6,Lists!$B$2:$G$153,2,FALSE) -> AGO002 | C6: =VLOOKUP(B6,'INFORM Severity - hidden'!$C$5:$D$160,2,FALSE) -> Angola | D6: =VLOOKUP(A6,Lists!$B$2:$G$153,3,FALSE) -> AGO | E6: =VLOOKUP(A6,Lists!$B$2:$G$153,5,FALSE) -> Food Security | F6: =IF(OR(N6="x",K6="x"),"x",ROUND((5-GEOMEAN(((5-K6)/5*4+1),((5-N6)/5*4+1),((5-N6)/5*4+1)))/4*3.5+Q6*0.3,1)) -> 3.2 | G6: =IF(F6="x","x",ROUNDUP(F6,0)) -> 4 | H6: =IF(N6="x","x",IF(K6="x","x",(IF(G6=5,"Very High",IF(G6=4,"High",IF(G6=3,"Medium",IF(G6=2,"Low","Very Low"))))))) -> High | I6: =INDEX(Trends!$D$3:$D$404,MATCH(B6,Trends!$C$3:$C$404,0)) -> - | J6: =VLOOKUP($B6,Reliability!$A$3:$I$170,9,FALSE) -> Very High | K6: =IF(OR(M6="x",L6="x"),"x",ROUND((5-GEOMEAN(((5-L6)/5*4+1),((5-M6)/5*4+1),((5-M6)/5*4+1)))/4*5,1)) -> 2 | L6: =VLOOKUP($B6,'Impact of the crisis'!$C$6:$N$170,12,FALSE) -> 1.7 | M6: =VLOOKUP($B6,'Impact of the crisis'!$C$6:$AB$170,26,FALSE) -> 2.2 | N6: =VLOOKUP($B6,'Conditions of people affected'!$C$6:$R$170,16,FALSE) -> 3.8 | O6: =VLOOKUP($B6,'Conditions of people affected'!$C$6:$R$170,9,FALSE) -> 3.6 | P6: =VLOOKUP($B6,'Conditions of people affected'!$C$6:$R$170,15,FALSE) -> 4 | Q6: =IF(OR(S6="x",R6="x"),R6,ROUND((5-GEOMEAN(((5-R6)/5*4+1),((5-S6)/5*4+1)))/4*5,1)) -> 2.9 | R6: =VLOOKUP($B6,'Complexity of the crisis'!$C$6:$AN$170,22,FALSE) -> 3.6 | S6: =VLOOKUP($B6,'Complexity of the crisis'!$C$6:$AN$170,38,FALSE) -> 2 | T6: =VLOOKUP(B6,Lists!$C$3:$E$163,3,FALSE) -> Africa | U6: =VLOOKUP(B6,'INFORM Severity - hidden'!$C$5:$V$170,20,FALSE) -> 44550
A7: {=IFERROR(INDEX(Lists!$B$2:$B$153,SMALL(IF(Lists!$I$2:$I$153="Individual",ROW(Lists!$B$2:$B$153)),ROW(3:3))-1,1),"")} -> Nagorno-Karabakh Conflict in Armenia | B7: =VLOOKUP(A7,Lists!$B$2:$G$153,2,FALSE) -> ARM002 | C7: =VLOOKUP(B7,'INFORM Severity - hidden'!$C$5:$D$160,2,FALSE) -> Armenia | D7: =VLOOKUP(A7,Lists!$B$2:$G$153,3,FALSE) -> ARM | E7: =VLOOKUP(A7,Lists!$B$2:$G$153,5,FALSE) -> Conflict | F7: =IF(OR(N7="x",K7="x"),"x",ROUND((5-GEOMEAN(((5-K7)/5*4+1),((5-N7)/5*4+1),((5-N7)/5*4+1)))/4*3.5+Q7*0.3,1)) -> 1.6 | G7: =IF(F7="x","x",ROUNDUP(F7,0)) -> 2 | H7: =IF(N7="x","x",IF(K7="x","x",(IF(G7=5,"Very High",IF(G7=4,"High",IF(G7=3,"Medium",IF(G7=2,"Low","Very Low"))))))) -> Low | I7: =INDEX(Trends!$D$3:$D$404,MATCH(B7,Trends!$C$3:$C$404,0)) -> Decreasing | J7: =VLOOKUP($B7,Reliability!$A$3:$I$170,9,FALSE) -> High | K7: =IF(OR(M7="x",L7="x"),"x",ROUND((5-GEOMEAN(((5-L7)/5*4+1),((5-M7)/5*4+1),((5-M7)/5*4+1)))/4*5,1)) -> 2.3 | L7: =VLOOKUP($B7,'Impact of the crisis'!$C$6:$N$170,12,FALSE) -> 3.5 | M7: =VLOOKUP($B7,'Impact of the crisis'!$C$6:$AB$170,26,FALSE) -> 1.5 | N7: =VLOOKUP($B7,'Conditions of people affected'!$C$6:$R$170,16,FALSE) -> 1.2 | O7: =VLOOKUP($B7,'Conditions of people affected'!$C$6:$R$170,9,FALSE) -> 1.4 | P7: =VLOOKUP($B7,'Conditions of people affected'!$C$6:$R$170,15,FALSE) -> 1 | Q7: =IF(OR(S7="x",R7="x"),R7,ROUND((5-GEOMEAN(((5-R7)/5*4+1),((5-S7)/5*4+1)))/4*5,1)) -> 1.6 | R7: =VLOOKUP($B7,'Complexity of the crisis'!$C$6:$AN$170,22,FALSE) -> 2.2 | S7: =VLOOKUP($B7,'Complexity of the crisis'!$C$6:$AN$170,38,FALSE) -> 1 | T7: =VLOOKUP(B7,Lists!$C$3:$E$163,3,FALSE) -> Middle east | U7: =VLOOKUP(B7,'INFORM Severity - hidden'!$C$5:$V$170,20,FALSE) -> 44496
A8: {=IFERROR(INDEX(Lists!$B$2:$B$153,SMALL(IF(Lists!$I$2:$I$153="Individual",ROW(Lists!$B$2:$B$153)),ROW(4:4))-1,1),"")} -> Nagorno-Karabakh conflict in Azerbaijan | B8: =VLOOKUP(A8,Lists!$B$2:$G$153,2,FALSE) -> AZE002 | C8: =VLOOKUP(B8,'INFORM Severity - hidden'!$C$5:$D$160,2,FALSE) -> Azerbaijan | D8: =VLOOKUP(A8,Lists!$B$2:$G$153,3,FALSE) -> AZE | E8: =VLOOKUP(A8,Lists!$B$2:$G$153,5,FALSE) -> Conflict | F8: =IF(OR(N8="x",K8="x"),"x",ROUND((5-GEOMEAN(((5-K8)/5*4+1),((5-N8)/5*4+1),((5-N8)/5*4+1)))/4*3.5+Q8*0.3,1)) -> x | G8: =IF(F8="x","x",ROUNDUP(F8,0)) -> x | H8: =IF(N8="x","x",IF(K8="x","x",(IF(G8=5,"Very High",IF(G8=4,"High",IF(G8=3,"Medium",IF(G8=2,"Low","Very Low"))))))) -> x | I8: =INDEX(Trends!$D$3:$D$404,MATCH(B8,Trends!$C$3:$C$404,0)) -> - | J8: =VLOOKUP($B8,Reliability!$A$3:$I$170,9,FALSE) -> Very Low | K8: =IF(OR(M8="x",L8="x"),"x",ROUND((5-GEOMEAN(((5-L8)/5*4+1),((5-M8)/5*4+1),((5-M8)/5*4+1)))/4*5,1)) -> 3.1 | L8: =VLOOKUP($B8,'Impact of the crisis'!$C$6:$N$170,12,FALSE) -> 2.5 | M8: =VLOOKUP($B8,'Impact of the crisis'!$C$6:$AB$170,26,FALSE) -> 3.4 | N8: =VLOOKUP($B8,'Conditions of people affected'!$C$6:$R$170,16,FALSE) -> x | O8: =VLOOKUP($B8,'Conditions of people affected'!$C$6:$R$170,9,FALSE) -> x | P8: =VLOOKUP($B8,'Conditions of people affected'!$C$6:$R$170,15,FALSE) -> x | Q8: =IF(OR(S8="x",R8="x"),R8,ROUND((5-GEOMEAN(((5-R8)/5*4+1),((5-S8)/5*4+1)))/4*5,1)) -> 3.3 | R8: =VLOOKUP($B8,'Complexity of the crisis'!$C$6:$AN$170,22,FALSE) -> 4 | S8: =VLOOKUP($B8,'Complexity of the crisis'!$C$6:$AN$170,38,FALSE) -> 2.5 | T8: =VLOOKUP(B8,Lists!$C$3:$E$163,3,FALSE) -> Middle east | U8: =VLOOKUP(B8,'INFORM Severity - hidden'!$C$5:$V$170,20,FALSE) -> 44496
A9: {=IFERROR(INDEX(Lists!$B$2:$B$153,SMALL(IF(Lists!$I$2:$I$153="Individual",ROW(Lists!$B$2:$B$153)),ROW(5:5))-1,1),"")} -> Complex in Burundi | B9: =VLOOKUP(A9,Lists!$B$2:$G$153,2,FALSE) -> BDI001 | C9: =VLOOKUP(B9,'INFORM Severity - hidden'!$C$5:$D$160,2,FALSE) -> Burundi | D9: =VLOOKUP(A9,Lists!$B$2:$G$153,3,FALSE) -> BDI | E9: =VLOOKUP(A9,Lists!$B$2:$G$153,5,FALSE) -> Complex crisis | F9: =IF(OR(N9="x",K9="x"),"x",ROUND((5-GEOMEAN(((5-K9)/5*4+1),((5-N9)/5*4+1),((5-N9)/5*4+1)))/4*3.5+Q9*0.3,1)) -> 3.9 | G9: =IF(F9="x","x",ROUNDUP(F9,0)) -> 4 | H9: =IF(N9="x","x",IF(K9="x","x",(IF(G9=5,"Very High",IF(G9=4,"High",IF(G9=3,"Medium",IF(G9=2,"Low","Very Low"))))))) -> High | I9: =INDEX(Trends!$D$3:$D$404,MATCH(B9,Trends!$C$3:$C$404,0)) -> Stable | J9: =VLOOKUP($B9,Reliability!$A$3:$I$170,9,FALSE) -> Medium | K9: =IF(OR(M9="x",L9="x"),"x",ROUND((5-GEOMEAN(((5-L9)/5*4+1),((5-M9)/5*4+1),((5-M9)/5*4+1)))/4*5,1)) -> 3.9 | L9: =VLOOKUP($B9,'Impact of the crisis'!$C$6:$N$170,12,FALSE) -> 4 | M9: =VLOOKUP($B9,'Impact of the crisis'!$C$6:$AB$170,26,FALSE) -> 3.8 | N9: =VLOOKUP($B9,'Conditions of people affected'!$C$6:$R$170,16,FALSE) -> 4 | O9: =VLOOKUP($B9,'Conditions of people affected'!$C$6:$R$170,9,FALSE) -> 4 | P9: =VLOOKUP($B9,'Conditions of people affected'!$C$6:$R$170,15,FALSE) -> 4 | Q9: =IF(OR(S9="x",R9="x"),R9,ROUND((5-GEOMEAN(((5-R9)/5*4+1),((5-S9)/5*4+1)))/4*5,1)) -> 3.6 | R9: =VLOOKUP($B9,'Complexity of the crisis'!$C$6:$AN$170,22,FALSE) -> 3.6 | S9: =VLOOKUP($B9,'Complexity of the crisis'!$C$6:$AN$170,38,FALSE) -> 3.5 | T9: =VLOOKUP(B9,Lists!$C$3:$E$163,3,FALSE) -> Africa | U9: =VLOOKUP(B9,'INFORM Severity - hidden'!$C$5:$V$170,20,FALSE) -> 44498
A10: {=IFERROR(INDEX(Lists!$B$2:$B$153,SMALL(IF(Lists!$I$2:$I$153="Individual",ROW(Lists!$B$2:$B$153)),ROW(6:6))-1,1),"")} -> Conflict in Burkina Faso | B10: =VLOOKUP(A10,Lists!$B$2:$G$153,2,FALSE) -> BFA002 | C10: =VLOOKUP(B10,'INFORM Severity - hidden'!$C$5:$D$160,2,FALSE) -> Burkina Faso | D10: =VLOOKUP(A10,Lists!$B$2:$G$153,3,FALSE) -> BFA | E10: =VLOOKUP(A10,Lists!$B$2:$G$153,5,FALSE) -> Conflict | F10: =IF(OR(N10="x",K10="x"),"x",ROUND((5-GEOMEAN(((5-K10)/5*4+1),((5-N10)/5*4+1),((5-N10)/5*4+1)))/4*3.5+Q10*0.3,1)) -> 4.1 | G10: =IF(F10="x","x",ROUNDUP(F10,0)) -> 5 | H10: =IF(N10="x","x",IF(K10="x","x",(IF(G10=5,"Very High",IF(G10=4,"High",IF(G10=3,"Medium",IF(G10=2,"Low","Very Low"))))))) -> Very High | I10: =INDEX(Trends!$D$3:$D$404,MATCH(B10,Trends!$C$3:$C$404,0)) -> Stable | J10: =VLOOKUP($B10,Reliability!$A$3:$I$170,9,FALSE) -> High | K10: =IF(OR(M10="x",L10="x"),"x",ROUND((5-GEOMEAN(((5-L10)/5*4+1),((5-M10)/5*4+1),((5-M10)/5*4+1)))/4*5,1)) -> 4 | L10: =VLOOKUP($B10,'Impact of the crisis'!$C$6:$N$170,12,FALSE) -> 2.5 | M10: =VLOOKUP($B10,'Impact of the crisis'!$C$6:$AB$170,26,FALSE) -> 4.5 | N10: =VLOOKUP($B10,'Conditions of people affected'!$C$6:$R$170,16,FALSE) -> 4.3 | O10: =VLOOKUP($B10,'Conditions of people affected'!$C$6:$R$170,9,FALSE) -> 3.6 | P10: =VLOOKUP($B10,'Conditions of people affected'!$C$6:$R$170,15,FALSE) -> 5 | Q10: =IF(OR(S10="x",R10="x"),R10,ROUND((5-GEOMEAN(((5-R10)/5*4+1),((5-S10)/5*4+1)))/4*5,1)) -> 3.7 | R10: =VLOOKUP($B10,'Complexity of the crisis'!$C$6:$AN$170,22,FALSE) -> 3.9 | S10: =VLOOKUP($B10,'Complexity of the crisis'!$C$6:$AN$170,38,FALSE) -> 3.5 | T10: =VLOOKUP(B10,Lists!$C$3:$E$163,3,FALSE) -> Africa | U10: =VLOOKUP(B10,'INFORM Severity - hidden'!$C$5:$V$170,20,FALSE) -> 44567
A11: {=IFERROR(INDEX(Lists!$B$2:$B$153,SMALL(IF(Lists!$I$2:$I$153="Individual",ROW(Lists!$B$2:$B$153)),ROW(7:7))-1,1),"")} -> Rohingya refugee crisis | B11: =VLOOKUP(A11,Lists!$B$2:$G$153,2,FALSE) -> BGD002 | C11: =VLOOKUP(B11,'INFORM Severity - hidden'!$C$5:$D$160,2,FALSE) -> Bangladesh | D11: =VLOOKUP(A11,Lists!$B$2:$G$153,3,FALSE) -> BGD | E11: =VLOOKUP(A11,Lists!$B$2:$G$153,5,FALSE) -> International displacement | F11: =IF(OR(N11="x",K11="x"),"x",ROUND((5-GEOMEAN(((5-K11)/5*4+1),((5-N11)/5*4+1),((5-N11)/5*4+1)))/4*3.5+Q11*0.3,1)) -> 3.3 | G11: =IF(F11="x","x",ROUNDUP(F11,0)) -> 4 | H11: =IF(N11="x","x",IF(K11="x","x",(IF(G11=5,"Very High",IF(G11=4,"High",IF(G11=3,"Medium",IF(G11=2,"Low","Very Low"))))))) -> High | I11: =INDEX(Trends!$D$3:$D$404,MATCH(B11,Trends!$C$3:$C$404,0)) -> Increasing | J11: =VLOOKUP($B11,Reliability!$A$3:$I$170,9,FALSE) -> High | K11: =IF(OR(M11="x",L11="x"),"x",ROUND((5-GEOMEAN(((5-L11)/5*4+1),((5-M11)/5*4+1),((5-M11)/5*4+1)))/4*5,1)) -> 3.4 | L11: =VLOOKUP($B11,'Impact of the crisis'!$C$6:$N$170,12,FALSE) -> 0.1 | M11: =VLOOKUP($B11,'Impact of the crisis'!$C$6:$AB$170,26,FALSE) -> 4.3 | N11: =VLOOKUP($B11,'Conditions of people affected'!$C$6:$R$170,16,FALSE) -> 3.3 | O11: =VLOOKUP($B11,'Conditions of people affected'!$C$6:$R$170,9,FALSE) -> 3.6 | P11: =VLOOKUP($B11,'Conditions of people affected'!$C$6:$R$170,15,FALSE) -> 3 | Q11: =IF(OR(S11="x",R11="x"),R11,ROUND((5-GEOMEAN(((5-R11)/5*4+1),((5-S11)/5*4+1)))/4*5,1)) -> 3.2 | R11: =VLOOKUP($B11,'Complexity of the crisis'!$C$6:$AN$170,22,FALSE) -> 3.3 | S11: =VLOOKUP($B11,'Complexity of the crisis'!$C$6:$AN$170,38,FALSE) -> 3 | T11: =VLOOKUP(B11,Lists!$C$3:$E$163,3,FALSE) -> Asia | U11: =VLOOKUP(B11,'INFORM Severity - hidden'!$C$5:$V$170,20,FALSE) -> 44585
A12: {=IFERROR(INDEX(Lists!$B$2:$B$153,SMALL(IF(Lists!$I$2:$I$153="Individual",ROW(Lists!$B$2:$B$153)),ROW(8:8))-1,1),"")} -> Venezuela displacement in Brazil | B12: =VLOOKUP(A12,Lists!$B$2:$G$153,2,FALSE) -> BRA002 | C12: =VLOOKUP(B12,'INFORM Severity - hidden'!$C$5:$D$160,2,FALSE) -> Brazil | D12: =VLOOKUP(A12,Lists!$B$2:$G$153,3,FALSE) -> BRA | E12: =VLOOKUP(A12,Lists!$B$2:$G$153,5,FALSE) -> International displacement | F12: =IF(OR(N12="x",K12="x"),"x",ROUND((5-GEOMEAN(((5-K12)/5*4+1),((5-N12)/5*4+1),((5-N12)/5*4+1)))/4*3.5+Q12*0.3,1)) -> 2.6 | G12: =IF(F12="x","x",ROUNDUP(F12,0)) -> 3 | H12: =IF(N12="x","x",IF(K12="x","x",(IF(G12=5,"Very High",IF(G12=4,"High",IF(G12=3,"Medium",IF(G12=2,"Low","Very Low"))))))) -> Medium | I12: =INDEX(Trends!$D$3:$D$404,MATCH(B12,Trends!$C$3:$C$404,0)) -> Decreasing | J12: =VLOOKUP($B12,Reliability!$A$3:$I$170,9,FALSE) -> Medium | K12: =IF(OR(M12="x",L12="x"),"x",ROUND((5-GEOMEAN(((5-L12)/5*4+1),((5-M12)/5*4+1),((5-M12)/5*4+1)))/4*5,1)) -> 2.2 | L12: =VLOOKUP($B12,'Impact of the crisis'!$C$6:$N$170,12,FALSE) -> 1.1 | M12: =VLOOKUP($B12,'Impact of the crisis'!$C$6:$AB$170,26,FALSE) -> 2.6 | N12: =VLOOKUP($B12,'Conditions of people affected'!$C$6:$R$170,16,FALSE) -> 2.8 | O12: =VLOOKUP($B12,'Conditions of people affected'!$C$6:$R$170,9,FALSE) -> 2.6 | P12: =VLOOKUP($B12,'Conditions of people affected'!$C$6:$R$170,15,FALSE) -> 3 | Q12: =IF(OR(S12="x",R12="x"),R12,ROUND((5-GEOMEAN(((5-R12)/5*4+1),((5-S12)/5*4+1)))/4*5,1)) -> 2.6 | R12: =VLOOKUP($B12,'Complexity of the crisis'!$C$6:$AN$170,22,FALSE) -> 3.4 | S12: =VLOOKUP($B12,'Complexity of the crisis'!$C$6:$AN$170,38,FALSE) -> 1.5 | T12: =VLOOKUP(B12,Lists!$C$3:$E$163,3,FALSE) -> Americas | U12: =VLOOKUP(B12,'INFORM Severity - hidden'!$C$5:$V$170,20,FALSE) -> 44525
A13: {=IFERROR(INDEX(Lists!$B$2:$B$153,SMALL(IF(Lists!$I$2:$I$153="Individual",ROW(Lists!$B$2:$B$153)),ROW(9:9))-1,1),"")} -> Floods in Bahia and Minas Gerais | B13: =VLOOKUP(A13,Lists!$B$2:$G$153,2,FALSE) -> BRA003 | C13: =VLOOKUP(B13,'INFORM Severity - hidden'!$C$5:$D$160,2,FALSE) -> Brazil | D13: =VLOOKUP(A13,Lists!$B$2:$G$153,3,FALSE) -> BRA | E13: =VLOOKUP(A13,Lists!$B$2:$G$153,5,FALSE) -> Flood | F13: =IF(OR(N13="x",K13="x"),"x",ROUND((5-GEOMEAN(((5-K13)/5*4+1),((5-N13)/5*4+1),((5-N13)/5*4+1)))/4*3.5+Q13*0.3,1)) -> 2.1 | G13: =IF(F13="x","x",ROUNDUP(F13,0)) -> 3 | H13: =IF(N13="x","x",IF(K13="x","x",(IF(G13=5,"Very High",IF(G13=4,"High",IF(G13=3,"Medium",IF(G13=2,"Low","Very Low"))))))) -> Medium | I13: =INDEX(Trends!$D$3:$D$404,MATCH(B13,Trends!$C$3:$C$404,0)) -> - | J13: =VLOOKUP($B13,Reliability!$A$3:$I$170,9,FALSE) -> High | K13: =IF(OR(M13="x",L13="x"),"x",ROUND((5-GEOMEAN(((5-L13)/5*4+1),((5-M13)/5*4+1),((5-M13)/5*4+1)))/4*5,1)) -> 2.5 | L13: =VLOOKUP($B13,'Impact of the crisis'!$C$6:$N$170,12,FALSE) -> 2.9 | M13: =VLOOKUP($B13,'Impact of the crisis'!$C$6:$AB$170,26,FALSE) -> 2.3 | N13: =VLOOKUP($B13,'Conditions of people affected'!$C$6:$R$170,16,FALSE) -> 1.3 | O13: =VLOOKUP($B13,'Conditions of people affected'!$C$6:$R$170,9,FALSE) -> 1.6 | P13: =VLOOKUP($B13,'Conditions of people affected'!$C$6:$R$170,15,FALSE) -> 1 | Q13: =IF(OR(S13="x",R13="x"),R13,ROUND((5-GEOMEAN(((5-R13)/5*4+1),((5-S13)/5*4+1)))/4*5,1)) -> 2.8 | R13: =VLOOKUP($B13,'Complexity of the crisis'!$C$6:$AN$170,22,FALSE) -> 3.4 | S13: =VLOOKUP($B13,'Complexity of the crisis'!$C$6:$AN$170,38,FALSE) -> 2 | T13: =VLOOKUP(B13,Lists!$C$3:$E$163,3,FALSE) -> Americas | U13: =VLOOKUP(B13,'INFORM Severity - hidden'!$C$5:$V$170,20,FALSE) -> 44572
A14: {=IFERROR(INDEX(Lists!$B$2:$B$153,SMALL(IF(Lists!$I$2:$I$153="Individual",ROW(Lists!$B$2:$B$153)),ROW(10:10))-1,1),"")} -> Complex crisis in CAR | B14: =VLOOKUP(A14,Lists!$B$2:$G$153,2,FALSE) -> CAF001 | C14: =VLOOKUP(B14,'INFORM Severity - hidden'!$C$5:$D$160,2,FALSE) -> CAR | D14: =VLOOKUP(A14,Lists!$B$2:$G$153,3,FALSE) -> CAF | E14: =VLOOKUP(A14,Lists!$B$2:$G$153,5,FALSE) -> Complex crisis | F14: =IF(OR(N14="x",K14="x"),"x",ROUND((5-GEOMEAN(((5-K14)/5*4+1),((5-N14)/5*4+1),((5-N14)/5*4+1)))/4*3.5+Q14*0.3,1)) -> 4.3 | G14: =IF(F14="x","x",ROUNDUP(F14,0)) -> 5 | H14: =IF(N14="x","x",IF(K14="x","x",(IF(G14=5,"Very High",IF(G14=4,"High",IF(G14=3,"Medium",IF(G14=2,"Low","Very Low"))))))) -> Very High | I14: =INDEX(Trends!$D$3:$D$404,MATCH(B14,Trends!$C$3:$C$404,0)) -> Stable | J14: =VLOOKUP($B14,Reliability!$A$3:$I$170,9,FALSE) -> Medium | K14: =IF(OR(M14="x",L14="x"),"x",ROUND((5-GEOMEAN(((5-L14)/5*4+1),((5-M14)/5*4+1),((5-M14)/5*4+1)))/4*5,1)) -> 4.4 | L14: =VLOOKUP($B14,'Impact of the crisis'!$C$6:$N$170,12,FALSE) -> 4.3 | M14: =VLOOKUP($B14,'Impact of the crisis'!$C$6:$AB$170,26,FALSE) -> 4.5 | N14: =VLOOKUP($B14,'Conditions of people affected'!$C$6:$R$170,16,FALSE) -> 4.05 | O14: =VLOOKUP($B14,'Conditions of people affected'!$C$6:$R$170,9,FALSE) -> 4.1 | P14: =VLOOKUP($B14,'Conditions of people affected'!$C$6:$R$170,15,FALSE) -> 4 | Q14: =IF(OR(S14="x",R14="x"),R14,ROUND((5-GEOMEAN(((5-R14)/5*4+1),((5-S14)/5*4+1)))/4*5,1)) -> 4.5 | R14: =VLOOKUP($B14,'Complexity of the crisis'!$C$6:$AN$170,22,FALSE) -> 4.5 | S14: =VLOOKUP($B14,'Complexity of the crisis'!$C$6:$AN$170,38,FALSE) -> 4.5 | T14: =VLOOKUP(B14,Lists!$C$3:$E$163,3,FALSE) -> Africa | U14: =VLOOKUP(B14,'INFORM Severity - hidden'!$C$5:$V$170,20,FALSE) -> 44496
A15: {=IFERROR(INDEX(Lists!$B$2:$B$153,SMALL(IF(Lists!$I$2:$I$153="Individual",ROW(Lists!$B$2:$B$153)),ROW(11:11))-1,1),"")} -> Boko Haram in Cameroon | B15: =VLOOKUP(A15,Lists!$B$2:$G$153,2,FALSE) -> CMR002 | C15: =VLOOKUP(B15,'INFORM Severity - hidden'!$C$5:$D$160,2,FALSE) -> Cameroon | D15: =VLOOKUP(A15,Lists!$B$2:$G$153,3,FALSE) -> CMR | E15: =VLOOKUP(A15,Lists!$B$2:$G$153,5,FALSE) -> Conflict | F15: =IF(OR(N15="x",K15="x"),"x",ROUND((5-GEOMEAN(((5-K15)/5*4+1),((5-N15)/5*4+1),((5-N15)/5*4+1)))/4*3.5+Q15*0.3,1)) -> 3.7 | G15: =IF(F15="x","x",ROUNDUP(F15,0)) -> 4 | H15: =IF(N15="x","x",IF(K15="x","x",(IF(G15=5,"Very High",IF(G15=4,"High",IF(G15=3,"Medium",IF(G15=2,"Low","Very Low"))))))) -> High | I15: =INDEX(Trends!$D$3:$D$404,MATCH(B15,Trends!$C$3:$C$404,0)) -> Increasing | J15: =VLOOKUP($B15,Reliability!$A$3:$I$170,9,FALSE) -> Very High | K15: =IF(OR(M15="x",L15="x"),"x",ROUND((5-GEOMEAN(((5-L15)/5*4+1),((5-M15)/5*4+1),((5-M15)/5*4+1)))/4*5,1)) -> 2.9 | L15: =VLOOKUP($B15,'Impact of the crisis'!$C$6:$N$170,12,FALSE) -> 1.3 | M15: =VLOOKUP($B15,'Impact of the crisis'!$C$6:$AB$170,26,FALSE) -> 3.5 | N15: =VLOOKUP($B15,'Conditions of people affected'!$C$6:$R$170,16,FALSE) -> 3.75 | O15: =VLOOKUP($B15,'Conditions of people affected'!$C$6:$R$170,9,FALSE) -> 3.5 | P15: =VLOOKUP($B15,'Conditions of people affected'!$C$6:$R$170,15,FALSE) -> 4 | Q15: =IF(OR(S15="x",R15="x"),R15,ROUND((5-GEOMEAN(((5-R15)/5*4+1),((5-S15)/5*4+1)))/4*5,1)) -> 4.1 | R15: =VLOOKUP($B15,'Complexity of the crisis'!$C$6:$AN$170,22,FALSE) -> 4.2 | S15: =VLOOKUP($B15,'Complexity of the crisis'!$C$6:$AN$170,38,FALSE) -> 4 | T15: =VLOOKUP(B15,Lists!$C$3:$E$163,3,FALSE) -> Africa | U15: =VLOOKUP(B15,'INFORM Severity - hidden'!$C$5:$V$170,20,FALSE) -> 44522
A16: {=IFERROR(INDEX(Lists!$B$2:$B$153,SMALL(IF(Lists!$I$2:$I$153="Individual",ROW(Lists!$B$2:$B$153)),ROW(12:12))-1,1),"")} -> Anglophone Crisis in Cameroon | B16: =VLOOKUP(A16,Lists!$B$2:$G$153,2,FALSE) -> CMR003 | C16: =VLOOKUP(B16,'INFORM Severity - hidden'!$C$5:$D$160,2,FALSE) -> Cameroon | D16: =VLOOKUP(A16,Lists!$B$2:$G$153,3,FALSE) -> CMR | E16: =VLOOKUP(A16,Lists!$B$2:$G$153,5,FALSE) -> Conflict | F16: =IF(OR(N16="x",K16="x"),"x",ROUND((5-GEOMEAN(((5-K16)/5*4+1),((5-N16)/5*4+1),((5-N16)/5*4+1)))/4*3.5+Q16*0.3,1)) -> 3.5 | G16: =IF(F16="x","x",ROUNDUP(F16,0)) -> 4 | H16: =IF(N16="x","x",IF(K16="x","x",(IF(G16=5,"Very High",IF(G16=4,"High",IF(G16=3,"Medium",IF(G16=2,"Low","Very Low"))))))) -> High | I16: =INDEX(Trends!$D$3:$D$404,MATCH(B16,Trends!$C$3:$C$404,0)) -> Increasing | J16: =VLOOKUP($B16,Reliability!$A$3:$I$170,9,FALSE) -> Medium | K16: =IF(OR(M16="x",L16="x"),"x",ROUND((5-GEOMEAN(((5-L16)/5*4+1),((5-M16)/5*4+1),((5-M16)/5*4+1)))/4*5,1)) -> 3.2 | L16: =VLOOKUP($B16,'Impact of the crisis'!$C$6:$N$170,12,FALSE) -> 1.7 | M16: =VLOOKUP($B16,'Impact of the crisis'!$C$6:$AB$170,26,FALSE) -> 3.8 | N16: =VLOOKUP($B16,'Conditions of people affected'!$C$6:$R$170,16,FALSE) -> 3.15 | O16: =VLOOKUP($B16,'Conditions of people affected'!$C$6:$R$170,9,FALSE) -> 3.3 | P16: =VLOOKUP($B16,'Conditions of people affected'!$C$6:$R$170,15,FALSE) -> 3 | Q16: =IF(OR(S16="x",R16="x"),R16,ROUND((5-GEOMEAN(((5-R16)/5*4+1),((5-S16)/5*4+1)))/4*5,1)) -> 4.4 | R16: =VLOOKUP($B16,'Complexity of the crisis'!$C$6:$AN$170,22,FALSE) -> 4.2 | S16: =VLOOKUP($B16,'Complexity of the crisis'!$C$6:$AN$170,38,FALSE) -> 4.5 | T16: =VLOOKUP(B16,Lists!$C$3:$E$163,3,FALSE) -> Africa | U16: =VLOOKUP(B16,'INFORM Severity - hidden'!$C$5:$V$170,20,FALSE) -> 44497
A17: {=IFERROR(INDEX(Lists!$B$2:$B$153,SMALL(IF(Lists!$I$2:$I$153="Individual",ROW(Lists!$B$2:$B$153)),ROW(13:13))-1,1),"")} -> CAR refugees in Cameroon | B17: =VLOOKUP(A17,Lists!$B$2:$G$153,2,FALSE) -> CMR004 | C17: =VLOOKUP(B17,'INFORM Severity - hidden'!$C$5:$D$160,2,FALSE) -> Cameroon | D17: =VLOOKUP(A17,Lists!$B$2:$G$153,3,FALSE) -> CMR | E17: =VLOOKUP(A17,Lists!$B$2:$G$153,5,FALSE) -> International displacement | F17: =IF(OR(N17="x",K17="x"),"x",ROUND((5-GEOMEAN(((5-K17)/5*4+1),((5-N17)/5*4+1),((5-N17)/5*4+1)))/4*3.5+Q17*0.3,1)) -> 3 | G17: =IF(F17="x","x",ROUNDUP(F17,0)) -> 3 | H17: =IF(N17="x","x",IF(K17="x","x",(IF(G17=5,"Very High",IF(G17=4,"High",IF(G17=3,"Medium",IF(G17=2,"Low","Very Low"))))))) -> Medium | I17: =INDEX(Trends!$D$3:$D$404,MATCH(B17,Trends!$C$3:$C$404,0)) -> Stable | J17: =VLOOKUP($B17,Reliability!$A$3:$I$170,9,FALSE) -> Medium | K17: =IF(OR(M17="x",L17="x"),"x",ROUND((5-GEOMEAN(((5-L17)/5*4+1),((5-M17)/5*4+1),((5-M17)/5*4+1)))/4*5,1)) -> 2.8 | L17: =VLOOKUP($B17,'Impact of the crisis'!$C$6:$N$170,12,FALSE) -> 1.7 | M17: =VLOOKUP($B17,'Impact of the crisis'!$C$6:$AB$170,26,FALSE) -> 3.2 | N17: =VLOOKUP($B17,'Conditions of people affected'!$C$6:$R$170,16,FALSE) -> 2.75 | O17: =VLOOKUP($B17,'Conditions of people affected'!$C$6:$R$170,9,FALSE) -> 2.5 | P17: =VLOOKUP($B17,'Conditions of people affected'!$C$6:$R$170,15,FALSE) -> 3 | Q17: =IF(OR(S17="x",R17="x"),R17,ROUND((5-GEOMEAN(((5-R17)/5*4+1),((5-S17)/5*4+1)))/4*5,1)) -> 3.5 | R17: =VLOOKUP($B17,'Complexity of the crisis'!$C$6:$AN$170,22,FALSE) -> 4.2 | S17: =VLOOKUP($B17,'Complexity of the crisis'!$C$6:$AN$170,38,FALSE) -> 2.5 | T17: =VLOOKUP(B17,Lists!$C$3:$E$163,3,FALSE) -> Africa | U17: =VLOOKUP(B17,'INFORM Severity - hidden'!$C$5:$V$170,20,FALSE) -> 44497
A18: {=IFERROR(INDEX(Lists!$B$2:$B$153,SMALL(IF(Lists!$I$2:$I$153="Individual",ROW(Lists!$B$2:$B$153)),ROW(14:14))-1,1),"")} -> Complex crisis in DRC | B18: =VLOOKUP(A18,Lists!$B$2:$G$153,2,FALSE) -> COD001 | C18: =VLOOKUP(B18,'INFORM Severity - hidden'!$C$5:$D$160,2,FALSE) -> DRC | D18: =VLOOKUP(A18,Lists!$B$2:$G$153,3,FALSE) -> COD | E18: =VLOOKUP(A18,Lists!$B$2:$G$153,5,FALSE) -> Complex crisis | F18: =IF(OR(N18="x",K18="x"),"x",ROUND((5-GEOMEAN(((5-K18)/5*4+1),((5-N18)/5*4+1),((5-N18)/5*4+1)))/4*3.5+Q18*0.3,1)) -> 4.6 | G18: =IF(F18="x","x",ROUNDUP(F18,0)) -> 5 | H18: =IF(N18="x","x",IF(K18="x","x",(IF(G18=5,"Very High",IF(G18=4,"High",IF(G18=3,"Medium",IF(G18=2,"Low","Very Low"))))))) -> Very High | I18: =INDEX(Trends!$D$3:$D$404,MATCH(B18,Trends!$C$3:$C$404,0)) -> Stable | J18: =VLOOKUP($B18,Reliability!$A$3:$I$170,9,FALSE) -> Very High | K18: =IF(OR(M18="x",L18="x"),"x",ROUND((5-GEOMEAN(((5-L18)/5*4+1),((5-M18)/5*4+1),((5-M18)/5*4+1)))/4*5,1)) -> 4.6 | L18: =VLOOKUP($B18,'Impact of the crisis'!$C$6:$N$170,12,FALSE) -> 4.3 | M18: =VLOOKUP($B18,'Impact of the crisis'!$C$6:$AB$170,26,FALSE) -> 4.8 | N18: =VLOOKUP($B18,'Conditions of people affected'!$C$6:$R$170,16,FALSE) -> 4.5 | O18: =VLOOKUP($B18,'Conditions of people affected'!$C$6:$R$170,9,FALSE) -> 5 | P18: =VLOOKUP($B18,'Conditions of people affected'!$C$6:$R$170,15,FALSE) -> 4 | Q18: =IF(OR(S18="x",R18="x"),R18,ROUND((5-GEOMEAN(((5-R18)/5*4+1),((5-S18)/5*4+1)))/4*5,1)) -> 4.8 | R18: =VLOOKUP($B18,'Complexity of the crisis'!$C$6:$AN$170,22,FALSE) -> 5.1 | S18: =VLOOKUP($B18,'Complexity of the crisis'!$C$6:$AN$170,38,FALSE) -> 4.5 | T18: =VLOOKUP(B18,Lists!$C$3:$E$163,3,FALSE) -> Africa | U18: =VLOOKUP(B18,'INFORM Severity - hidden'!$C$5:$V$170,20,FALSE) -> 44567
A19: {=IFERROR(INDEX(Lists!$B$2:$B$153,SMALL(IF(Lists!$I$2:$I$153="Individual",ROW(Lists!$B$2:$B$153)),ROW(15:15))-1,1),"")} -> Complex crisis in Congo | B19: =VLOOKUP(A19,Lists!$B$2:$G$153,2,FALSE) -> COG001 | C19: =VLOOKUP(B19,'INFORM Severity - hidden'!$C$5:$D$160,2,FALSE) -> Congo | D19: =VLOOKUP(A19,Lists!$B$2:$G$153,3,FALSE) -> COG | E19: =VLOOKUP(A19,Lists!$B$2:$G$153,5,FALSE) -> Complex crisis | F19: =IF(OR(N19="x",K19="x"),"x",ROUND((5-GEOMEAN(((5-K19)/5*4+1),((5-N19)/5*4+1),((5-N19)/5*4+1)))/4*3.5+Q19*0.3,1)) -> 3.4 | G19: =IF(F19="x","x",ROUNDUP(F19,0)) -> 4 | H19: =IF(N19="x","x",IF(K19="x","x",(IF(G19=5,"Very High",IF(G19=4,"High",IF(G19=3,"Medium",IF(G19=2,"Low","Very Low"))))))) -> High | I19: =INDEX(Trends!$D$3:$D$404,MATCH(B19,Trends!$C$3:$C$404,0)) -> Stable | J19: =VLOOKUP($B19,Reliability!$A$3:$I$170,9,FALSE) -> Low | K19: =IF(OR(M19="x",L19="x"),"x",ROUND((5-GEOMEAN(((5-L19)/5*4+1),((5-M19)/5*4+1),((5-M19)/5*4+1)))/4*5,1)) -> 3.6 | L19: =VLOOKUP($B19,'Impact of the crisis'!$C$6:$N$170,12,FALSE) -> 4.2 | M19: =VLOOKUP($B19,'Impact of the crisis'!$C$6:$AB$170,26,FALSE) -> 3.3 | N19: =VLOOKUP($B19,'Conditions of people affected'!$C$6:$R$170,16,FALSE) -> 3.25 | O19: =VLOOKUP($B19,'Conditions of people affected'!$C$6:$R$170,9,FALSE) -> 3.5 | P19: =VLOOKUP($B19,'Conditions of people affected'!$C$6:$R$170,15,FALSE) -> 3 | Q19: =IF(OR(S19="x",R19="x"),R19,ROUND((5-GEOMEAN(((5-R19)/5*4+1),((5-S19)/5*4+1)))/4*5,1)) -> 3.3 | R19: =VLOOKUP($B19,'Complexity of the crisis'!$C$6:$AN$170,22,FALSE) -> 3.1 | S19: =VLOOKUP($B19,'Complexity of the crisis'!$C$6:$AN$170,38,FALSE) -> 3.5 | T19: =VLOOKUP(B19,Lists!$C$3:$E$163,3,FALSE) -> Africa | U19: =VLOOKUP(B19,'INFORM Severity - hidden'!$C$5:$V$170,20,FALSE) -> 44497
A20: {=IFERROR(INDEX(Lists!$B$2:$B$153,SMALL(IF(Lists!$I$2:$I$153="Individual",ROW(Lists!$B$2:$B$153)),ROW(16:16))-1,1),"")} -> Complex crisis in Colombia | B20: =VLOOKUP(A20,Lists!$B$2:$G$153,2,FALSE) -> COL001 | C20: =VLOOKUP(B20,'INFORM Severity - hidden'!$C$5:$D$160,2,FALSE) -> Colombia | D20: =VLOOKUP(A20,Lists!$B$2:$G$153,3,FALSE) -> COL | E20: =VLOOKUP(A20,Lists!$B$2:$G$153,5,FALSE) -> Complex crisis | F20: =IF(OR(N20="x",K20="x"),"x",ROUND((5-GEOMEAN(((5-K20)/5*4+1),((5-N20)/5*4+1),((5-N20)/5*4+1)))/4*3.5+Q20*0.3,1)) -> 4.2 | G20: =IF(F20="x","x",ROUNDUP(F20,0)) -> 5 | H20: =IF(N20="x","x",IF(K20="x","x",(IF(G20=5,"Very High",IF(G20=4,"High",IF(G20=3,"Medium",IF(G20=2,"Low","Very Low"))))))) -> Very High | I20: =INDEX(Trends!$D$3:$D$404,MATCH(B20,Trends!$C$3:$C$404,0)) -> Increasing | J20: =VLOOKUP($B20,Reliability!$A$3:$I$170,9,FALSE) -> High | K20: =IF(OR(M20="x",L20="x"),"x",ROUND((5-GEOMEAN(((5-L20)/5*4+1),((5-M20)/5*4+1),((5-M20)/5*4+1)))/4*5,1)) -> 4 | L20: =VLOOKUP($B20,'Impact of the crisis'!$C$6:$N$170,12,FALSE) -> 5 | M20: =VLOOKUP($B20,'Impact of the crisis'!$C$6:$AB$170,26,FALSE) -> 3.3 | N20: =VLOOKUP($B20,'Conditions of people affected'!$C$6:$R$170,16,FALSE) -> 4.3 | O20: =VLOOKUP($B20,'Conditions of people affected'!$C$6:$R$170,9,FALSE) -> 4.6 | P20: =VLOOKUP($B20,'Conditions of people affected'!$C$6:$R$170,15,FALSE) -> 4 | Q20: =IF(OR(S20="x",R20="x"),R20,ROUND((5-GEOMEAN(((5-R20)/5*4+1),((5-S20)/5*4+1)))/4*5,1)) -> 4.1 | R20: =VLOOKUP($B20,'Complexity of the crisis'!$C$6:$AN$170,22,FALSE) -> 3.5 | S20: =VLOOKUP($B20,'Complexity of the crisis'!$C$6:$AN$170,38,FALSE) -> 4.5 | T20: =VLOOKUP(B20,Lists!$C$3:$E$163,3,FALSE) -> Americas | U20: =VLOOKUP(B20,'INFORM Severity - hidden'!$C$5:$V$170,20,FALSE) -> 44494
A21: {=IFERROR(INDEX(Lists!$B$2:$B$153,SMALL(IF(Lists!$I$2:$I$153="Individual",ROW(Lists!$B$2:$B$153)),ROW(17:17))-1,1),"")} -> Venezuela displacement in Colombia | B21: =VLOOKUP(A21,Lists!$B$2:$G$153,2,FALSE) -> COL002 | C21: =VLOOKUP(B21,'INFORM Severity - hidden'!$C$5:$D$160,2,FALSE) -> Colombia | D21: =VLOOKUP(A21,Lists!$B$2:$G$153,3,FALSE) -> COL | E21: =VLOOKUP(A21,Lists!$B$2:$G$153,5,FALSE) -> International displacement | F21: =IF(OR(N21="x",K21="x"),"x",ROUND((5-GEOMEAN(((5-K21)/5*4+1),((5-N21)/5*4+1),((5-N21)/5*4+1)))/4*3.5+Q21*0.3,1)) -> 3.6 | G21: =IF(F21="x","x",ROUNDUP(F21,0)) -> 4 | H21: =IF(N21="x","x",IF(K21="x","x",(IF(G21=5,"Very High",IF(G21=4,"High",IF(G21=3,"Medium",IF(G21=2,"Low","Very Low"))))))) -> High | I21: =INDEX(Trends!$D$3:$D$404,MATCH(B21,Trends!$C$3:$C$404,0)) -> Stable | J21: =VLOOKUP($B21,Reliability!$A$3:$I$170,9,FALSE) -> Medium | K21: =IF(OR(M21="x",L21="x"),"x",ROUND((5-GEOMEAN(((5-L21)/5*4+1),((5-M21)/5*4+1),((5-M21)/5*4+1)))/4*5,1)) -> 3.6 | L21: =VLOOKUP($B21,'Impact of the crisis'!$C$6:$N$170,12,FALSE) -> 2.7 | M21: =VLOOKUP($B21,'Impact of the crisis'!$C$6:$AB$170,26,FALSE) -> 3.9 | N21: =VLOOKUP($B21,'Conditions of people affected'!$C$6:$R$170,16,FALSE) -> 3.7 | O21: =VLOOKUP($B21,'Conditions of people affected'!$C$6:$R$170,9,FALSE) -> 4.4 | P21: =VLOOKUP($B21,'Conditions of people affected'!$C$6:$R$170,15,FALSE) -> 3 | Q21: =IF(OR(S21="x",R21="x"),R21,ROUND((5-GEOMEAN(((5-R21)/5*4+1),((5-S21)/5*4+1)))/4*5,1)) -> 3.5 | R21: =VLOOKUP($B21,'Complexity of the crisis'!$C$6:$AN$170,22,FALSE) -> 3.5 | S21: =VLOOKUP($B21,'Complexity of the crisis'!$C$6:$AN$170,38,FALSE) -> 3.5 | T21: =VLOOKUP(B21,Lists!$C$3:$E$163,3,FALSE) -> Americas | U21: =VLOOKUP(B21,'INFORM Severity - hidden'!$C$5:$V$170,20,FALSE) -> 44488
A22: {=IFERROR(INDEX(Lists!$B$2:$B$153,SMALL(IF(Lists!$I$2:$I$153="Individual",ROW(Lists!$B$2:$B$153)),ROW(18:18))-1,1),"")} -> Nicaraguan refugees in Costa Rica | B22: =VLOOKUP(A22,Lists!$B$2:$G$153,2,FALSE) -> CRI002 | C22: =VLOOKUP(B22,'INFORM Severity - hidden'!$C$5:$D$160,2,FALSE) -> Costa Rica | D22: =VLOOKUP(A22,Lists!$B$2:$G$153,3,FALSE) -> CRI | E22: =VLOOKUP(A22,Lists!$B$2:$G$153,5,FALSE) -> International displacement | F22: =IF(OR(N22="x",K22="x"),"x",ROUND((5-GEOMEAN(((5-K22)/5*4+1),((5-N22)/5*4+1),((5-N22)/5*4+1)))/4*3.5+Q22*0.3,1)) -> 1.1 | G22: =IF(F22="x","x",ROUNDUP(F22,0)) -> 2 | H22: =IF(N22="x","x",IF(K22="x","x",(IF(G22=5,"Very High",IF(G22=4,"High",IF(G22=3,"Medium",IF(G22=2,"Low","Very Low"))))))) -> Low | I22: =INDEX(Trends!$D$3:$D$404,MATCH(B22,Trends!$C$3:$C$404,0)) -> Decreasing | J22: =VLOOKUP($B22,Reliability!$A$3:$I$170,9,FALSE) -> Medium | K22: =IF(OR(M22="x",L22="x"),"x",ROUND((5-GEOMEAN(((5-L22)/5*4+1),((5-M22)/5*4+1),((5-M22)/5*4+1)))/4*5,1)) -> 1.3 | L22: =VLOOKUP($B22,'Impact of the crisis'!$C$6:$N$170,12,FALSE) -> 1 | M22: =VLOOKUP($B22,'Impact of the crisis'!$C$6:$AB$170,26,FALSE) -> 1.5 | N22: =VLOOKUP($B22,'Conditions of people affected'!$C$6:$R$170,16,FALSE) -> 1.05 | O22: =VLOOKUP($B22,'Conditions of people affected'!$C$6:$R$170,9,FALSE) -> 1.1 | P22: =VLOOKUP($B22,'Conditions of people affected'!$C$6:$R$170,15,FALSE) -> 1 | Q22: =IF(OR(S22="x",R22="x"),R22,ROUND((5-GEOMEAN(((5-R22)/5*4+1),((5-S22)/5*4+1)))/4*5,1)) -> 1 | R22: =VLOOKUP($B22,'Complexity of the crisis'!$C$6:$AN$170,22,FALSE) -> 0.9 | S22: =VLOOKUP($B22,'Complexity of the crisis'!$C$6:$AN$170,38,FALSE) -> 1 | T22: =VLOOKUP(B22,Lists!$C$3:$E$163,3,FALSE) -> Americas | U22: =VLOOKUP(B22,'INFORM Severity - hidden'!$C$5:$V$170,20,FALSE) -> 44495
A23: {=IFERROR(INDEX(Lists!$B$2:$B$153,SMALL(IF(Lists!$I$2:$I$153="Individual",ROW(Lists!$B$2:$B$153)),ROW(19:19))-1,1),"")} -> Mixed migration in Djibouti | B23: =VLOOKUP(A23,Lists!$B$2:$G$153,2,FALSE) -> DJI002 | C23: =VLOOKUP(B23,'INFORM Severity - hidden'!$C$5:$D$160,2,FALSE) -> Djibouti | D23: =VLOOKUP(A23,Lists!$B$2:$G$153,3,FALSE) -> DJI | E23: =VLOOKUP(A23,Lists!$B$2:$G$153,5,FALSE) -> International displacement | F23: =IF(OR(N23="x",K23="x"),"x",ROUND((5-GEOMEAN(((5-K23)/5*4+1),((5-N23)/5*4+1),((5-N23)/5*4+1)))/4*3.5+Q23*0.3,1)) -> 1.8 | G23: =IF(F23="x","x",ROUNDUP(F23,0)) -> 2 | H23: =IF(N23="x","x",IF(K23="x","x",(IF(G23=5,"Very High",IF(G23=4,"High",IF(G23=3,"Medium",IF(G23=2,"Low","Very Low"))))))) -> Low | I23: =INDEX(Trends!$D$3:$D$404,MATCH(B23,Trends!$C$3:$C$404,0)) -> Stable | J23: =VLOOKUP($B23,Reliability!$A$3:$I$170,9,FALSE) -> Very High | K23: =IF(OR(M23="x",L23="x"),"x",ROUND((5-GEOMEAN(((5-L23)/5*4+1),((5-M23)/5*4+1),((5-M23)/5*4+1)))/4*5,1)) -> 2 | L23: =VLOOKUP($B23,'Impact of the crisis'!$C$6:$N$170,12,FALSE) -> 3.1 | M23: =VLOOKUP($B23,'Impact of the crisis'!$C$6:$AB$170,26,FALSE) -> 1.3 | N23: =VLOOKUP($B23,'Conditions of people affected'!$C$6:$R$170,16,FALSE) -> 0.95 | O23: =VLOOKUP($B23,'Conditions of people affected'!$C$6:$R$170,9,FALSE) -> 0.9 | P23: =VLOOKUP($B23,'Conditions of people affected'!$C$6:$R$170,15,FALSE) -> 1 | Q23: =IF(OR(S23="x",R23="x"),R23,ROUND((5-GEOMEAN(((5-R23)/5*4+1),((5-S23)/5*4+1)))/4*5,1)) -> 2.8 | R23: =VLOOKUP($B23,'Complexity of the crisis'!$C$6:$AN$170,22,FALSE) -> 3.1 | S23: =VLOOKUP($B23,'Complexity of the crisis'!$C$6:$AN$170,38,FALSE) -> 2.5 | T23: =VLOOKUP(B23,Lists!$C$3:$E$163,3,FALSE) -> Africa | U23: =VLOOKUP(B23,'INFORM Severity - hidden'!$C$5:$V$170,20,FALSE) -> 44591
A24: {=IFERROR(INDEX(Lists!$B$2:$B$153,SMALL(IF(Lists!$I$2:$I$153="Individual",ROW(Lists!$B$2:$B$153)),ROW(20:20))-1,1),"")} -> Drought in Djibouti | B24: =VLOOKUP(A24,Lists!$B$2:$G$153,2,FALSE) -> DJI003 | C24: =VLOOKUP(B24,'INFORM Severity - hidden'!$C$5:$D$160,2,FALSE) -> Djibouti | D24: =VLOOKUP(A24,Lists!$B$2:$G$153,3,FALSE) -> DJI | E24: =VLOOKUP(A24,Lists!$B$2:$G$153,5,FALSE) -> Drought | F24: =IF(OR(N24="x",K24="x"),"x",ROUND((5-GEOMEAN(((5-K24)/5*4+1),((5-N24)/5*4+1),((5-N24)/5*4+1)))/4*3.5+Q24*0.3,1)) -> 2.7 | G24: =IF(F24="x","x",ROUNDUP(F24,0)) -> 3 | H24: =IF(N24="x","x",IF(K24="x","x",(IF(G24=5,"Very High",IF(G24=4,"High",IF(G24=3,"Medium",IF(G24=2,"Low","Very Low"))))))) -> Medium | I24: =INDEX(Trends!$D$3:$D$404,MATCH(B24,Trends!$C$3:$C$404,0)) -> Increasing | J24: =VLOOKUP($B24,Reliability!$A$3:$I$170,9,FALSE) -> High | K24: =IF(OR(M24="x",L24="x"),"x",ROUND((5-GEOMEAN(((5-L24)/5*4+1),((5-M24)/5*4+1),((5-M24)/5*4+1)))/4*5,1)) -> 2 | L24: =VLOOKUP($B24,'Impact of the crisis'!$C$6:$N$170,12,FALSE) -> 3.1 | M24: =VLOOKUP($B24,'Impact of the crisis'!$C$6:$AB$170,26,FALSE) -> 1.4 | N24: =VLOOKUP($B24,'Conditions of people affected'!$C$6:$R$170,16,FALSE) -> 2.55 | O24: =VLOOKUP($B24,'Conditions of people affected'!$C$6:$R$170,9,FALSE) -> 2.1 | P24: =VLOOKUP($B24,'Conditions of people affected'!$C$6:$R$170,15,FALSE) -> 3 | Q24: =IF(OR(S24="x",R24="x"),R24,ROUND((5-GEOMEAN(((5-R24)/5*4+1),((5-S24)/5*4+1)))/4*5,1)) -> 3.3 | R24: =VLOOKUP($B24,'Complexity of the crisis'!$C$6:$AN$170,22,FALSE) -> 3.1 | S24: =VLOOKUP($B24,'Complexity of the crisis'!$C$6:$AN$170,38,FALSE) -> 3.5 | T24: =VLOOKUP(B24,Lists!$C$3:$E$163,3,FALSE) -> Africa | U24: =VLOOKUP(B24,'INFORM Severity - hidden'!$C$5:$V$170,20,FALSE) -> 44591
A25: {=IFERROR(INDEX(Lists!$B$2:$B$153,SMALL(IF(Lists!$I$2:$I$153="Individual",ROW(Lists!$B$2:$B$153)),ROW(21:21))-1,1),"")} -> Mixed migration flows in Algeria | B25: =VLOOKUP(A25,Lists!$B$2:$G$153,2,FALSE) -> DZA002 | C25: =VLOOKUP(B25,'INFORM Severity - hidden'!$C$5:$D$160,2,FALSE) -> Algeria | D25: =VLOOKUP(A25,Lists!$B$2:$G$153,3,FALSE) -> DZA | E25: =VLOOKUP(A25,Lists!$B$2:$G$153,5,FALSE) -> International displacement | F25: =IF(OR(N25="x",K25="x"),"x",ROUND((5-GEOMEAN(((5-K25)/5*4+1),((5-N25)/5*4+1),((5-N25)/5*4+1)))/4*3.5+Q25*0.3,1)) -> x | G25: =IF(F25="x","x",ROUNDUP(F25,0)) -> x | H25: =IF(N25="x","x",IF(K25="x","x",(IF(G25=5,"Very High",IF(G25=4,"High",IF(G25=3,"Medium",IF(G25=2,"Low","Very Low"))))))) -> x | I25: =INDEX(Trends!$D$3:$D$404,MATCH(B25,Trends!$C$3:$C$404,0)) -> - | J25: =VLOOKUP($B25,Reliability!$A$3:$I$170,9,FALSE) -> Very Low | K25: =IF(OR(M25="x",L25="x"),"x",ROUND((5-GEOMEAN(((5-L25)/5*4+1),((5-M25)/5*4+1),((5-M25)/5*4+1)))/4*5,1)) -> 4.5 | L25: =VLOOKUP($B25,'Impact of the crisis'!$C$6:$N$170,12,FALSE) -> 5 | M25: =VLOOKUP($B25,'Impact of the crisis'!$C$6:$AB$170,26,FALSE) -> 4.2 | N25: =VLOOKUP($B25,'Conditions of people affected'!$C$6:$R$170,16,FALSE) -> x | O25: =VLOOKUP($B25,'Conditions of people affected'!$C$6:$R$170,9,FALSE) -> x | P25: =VLOOKUP($B25,'Conditions of people affected'!$C$6:$R$170,15,FALSE) -> x | Q25: =IF(OR(S25="x",R25="x"),R25,ROUND((5-GEOMEAN(((5-R25)/5*4+1),((5-S25)/5*4+1)))/4*5,1)) -> 2.7 | R25: =VLOOKUP($B25,'Complexity of the crisis'!$C$6:$AN$170,22,FALSE) -> 3.6 | S25: =VLOOKUP($B25,'Complexity of the crisis'!$C$6:$AN$170,38,FALSE) -> 1.5 | T25: =VLOOKUP(B25,Lists!$C$3:$E$163,3,FALSE) -> Africa | U25: =VLOOKUP(B25,'INFORM Severity - hidden'!$C$5:$V$170,20,FALSE) -> 44490
A26: {=IFERROR(INDEX(Lists!$B$2:$B$153,SMALL(IF(Lists!$I$2:$I$153="Individual",ROW(Lists!$B$2:$B$153)),ROW(22:22))-1,1),"")} -> Sahrawi refugees in Algeria | B26: =VLOOKUP(A26,Lists!$B$2:$G$153,2,FALSE) -> DZA003 | C26: =VLOOKUP(B26,'INFORM Severity - hidden'!$C$5:$D$160,2,FALSE) -> Algeria | D26: =VLOOKUP(A26,Lists!$B$2:$G$153,3,FALSE) -> DZA | E26: =VLOOKUP(A26,Lists!$B$2:$G$153,5,FALSE) -> International displacement | F26: =IF(OR(N26="x",K26="x"),"x",ROUND((5-GEOMEAN(((5-K26)/5*4+1),((5-N26)/5*4+1),((5-N26)/5*4+1)))/4*3.5+Q26*0.3,1)) -> 2.4 | G26: =IF(F26="x","x",ROUNDUP(F26,0)) -> 3 | H26: =IF(N26="x","x",IF(K26="x","x",(IF(G26=5,"Very High",IF(G26=4,"High",IF(G26=3,"Medium",IF(G26=2,"Low","Very Low"))))))) -> Medium | I26: =INDEX(Trends!$D$3:$D$404,MATCH(B26,Trends!$C$3:$C$404,0)) -> Increasing | J26: =VLOOKUP($B26,Reliability!$A$3:$I$170,9,FALSE) -> Medium | K26: =IF(OR(M26="x",L26="x"),"x",ROUND((5-GEOMEAN(((5-L26)/5*4+1),((5-M26)/5*4+1),((5-M26)/5*4+1)))/4*5,1)) -> 2.2 | L26: =VLOOKUP($B26,'Impact of the crisis'!$C$6:$N$170,12,FALSE) -> 1.1 | M26: =VLOOKUP($B26,'Impact of the crisis'!$C$6:$AB$170,26,FALSE) -> 2.6 | N26: =VLOOKUP($B26,'Conditions of people affected'!$C$6:$R$170,16,FALSE) -> 2.3 | O26: =VLOOKUP($B26,'Conditions of people affected'!$C$6:$R$170,9,FALSE) -> 1.6 | P26: =VLOOKUP($B26,'Conditions of people affected'!$C$6:$R$170,15,FALSE) -> 3 | Q26: =IF(OR(S26="x",R26="x"),R26,ROUND((5-GEOMEAN(((5-R26)/5*4+1),((5-S26)/5*4+1)))/4*5,1)) -> 2.7 | R26: =VLOOKUP($B26,'Complexity of the crisis'!$C$6:$AN$170,22,FALSE) -> 3.6 | S26: =VLOOKUP($B26,'Complexity of the crisis'!$C$6:$AN$170,38,FALSE) -> 1.5 | T26: =VLOOKUP(B26,Lists!$C$3:$E$163,3,FALSE) -> Africa | U26: =VLOOKUP(B26,'INFORM Severity - hidden'!$C$5:$V$170,20,FALSE) -> 44490
A27: {=IFERROR(INDEX(Lists!$B$2:$B$153,SMALL(IF(Lists!$I$2:$I$153="Individual",ROW(Lists!$B$2:$B$153)),ROW(23:23))-1,1),"")} -> Venezuela displacement in Ecuador | B27: =VLOOKUP(A27,Lists!$B$2:$G$153,2,FALSE) -> ECU002 | C27: =VLOOKUP(B27,'INFORM Severity - hidden'!$C$5:$D$160,2,FALSE) -> Ecuador | D27: =VLOOKUP(A27,Lists!$B$2:$G$153,3,FALSE) -> ECU | E27: =VLOOKUP(A27,Lists!$B$2:$G$153,5,FALSE) -> International displacement | F27: =IF(OR(N27="x",K27="x"),"x",ROUND((5-GEOMEAN(((5-K27)/5*4+1),((5-N27)/5*4+1),((5-N27)/5*4+1)))/4*3.5+Q27*0.3,1)) -> 2.4 | G27: =IF(F27="x","x",ROUNDUP(F27,0)) -> 3 | H27: =IF(N27="x","x",IF(K27="x","x",(IF(G27=5,"Very High",IF(G27=4,"High",IF(G27=3,"Medium",IF(G27=2,"Low","Very Low"))))))) -> Medium | I27: =INDEX(Trends!$D$3:$D$404,MATCH(B27,Trends!$C$3:$C$404,0)) -> Stable | J27: =VLOOKUP($B27,Reliability!$A$3:$I$170,9,FALSE) -> Medium | K27: =IF(OR(M27="x",L27="x"),"x",ROUND((5-GEOMEAN(((5-L27)/5*4+1),((5-M27)/5*4+1),((5-M27)/5*4+1)))/4*5,1)) -> 1.9 | L27: =VLOOKUP($B27,'Impact of the crisis'!$C$6:$N$170,12,FALSE) -> 1.4 | M27: =VLOOKUP($B27,'Impact of the crisis'!$C$6:$AB$170,26,FALSE) -> 2.2 | N27: =VLOOKUP($B27,'Conditions of people affected'!$C$6:$R$170,16,FALSE) -> 2.85 | O27: =VLOOKUP($B27,'Conditions of people affected'!$C$6:$R$170,9,FALSE) -> 2.7 | P27: =VLOOKUP($B27,'Conditions of people affected'!$C$6:$R$170,15,FALSE) -> 3 | Q27: =IF(OR(S27="x",R27="x"),R27,ROUND((5-GEOMEAN(((5-R27)/5*4+1),((5-S27)/5*4+1)))/4*5,1)) -> 2.1 | R27: =VLOOKUP($B27,'Complexity of the crisis'!$C$6:$AN$170,22,FALSE) -> 2.6 | S27: =VLOOKUP($B27,'Complexity of the crisis'!$C$6:$AN$170,38,FALSE) -> 1.5 | T27: =VLOOKUP(B27,Lists!$C$3:$E$163,3,FALSE) -> Americas | U27: =VLOOKUP(B27,'INFORM Severity - hidden'!$C$5:$V$170,20,FALSE) -> 44496
A28: {=IFERROR(INDEX(Lists!$B$2:$B$153,SMALL(IF(Lists!$I$2:$I$153="Individual",ROW(Lists!$B$2:$B$153)),ROW(24:24))-1,1),"")} -> Syrian Refugee Crisis in Egypt | B28: =VLOOKUP(A28,Lists!$B$2:$G$153,2,FALSE) -> EGY002 | C28: =VLOOKUP(B28,'INFORM Severity - hidden'!$C$5:$D$160,2,FALSE) -> Egypt | D28: =VLOOKUP(A28,Lists!$B$2:$G$153,3,FALSE) -> EGY | E28: =VLOOKUP(A28,Lists!$B$2:$G$153,5,FALSE) -> International displacement | F28: =IF(OR(N28="x",K28="x"),"x",ROUND((5-GEOMEAN(((5-K28)/5*4+1),((5-N28)/5*4+1),((5-N28)/5*4+1)))/4*3.5+Q28*0.3,1)) -> 2.5 | G28: =IF(F28="x","x",ROUNDUP(F28,0)) -> 3 | H28: =IF(N28="x","x",IF(K28="x","x",(IF(G28=5,"Very High",IF(G28=4,"High",IF(G28=3,"Medium",IF(G28=2,"Low","Very Low"))))))) -> Medium | I28: =INDEX(Trends!$D$3:$D$404,MATCH(B28,Trends!$C$3:$C$404,0)) -> Stable | J28: =VLOOKUP($B28,Reliability!$A$3:$I$170,9,FALSE) -> Medium | K28: =IF(OR(M28="x",L28="x"),"x",ROUND((5-GEOMEAN(((5-L28)/5*4+1),((5-M28)/5*4+1),((5-M28)/5*4+1)))/4*5,1)) -> 2.3 | L28: =VLOOKUP($B28,'Impact of the crisis'!$C$6:$N$170,12,FALSE) -> 2.4 | M28: =VLOOKUP($B28,'Impact of the crisis'!$C$6:$AB$170,26,FALSE) -> 2.3 | N28: =VLOOKUP($B28,'Conditions of people affected'!$C$6:$R$170,16,FALSE) -> 2.4 | O28: =VLOOKUP($B28,'Conditions of people affected'!$C$6:$R$170,9,FALSE) -> 2.8 | P28: =VLOOKUP($B28,'Conditions of people affected'!$C$6:$R$170,15,FALSE) -> 2 | Q28: =IF(OR(S28="x",R28="x"),R28,ROUND((5-GEOMEAN(((5-R28)/5*4+1),((5-S28)/5*4+1)))/4*5,1)) -> 2.8 | R28: =VLOOKUP($B28,'Complexity of the crisis'!$C$6:$AN$170,22,FALSE) -> 3.7 | S28: =VLOOKUP($B28,'Complexity of the crisis'!$C$6:$AN$170,38,FALSE) -> 1.5 | T28: =VLOOKUP(B28,Lists!$C$3:$E$163,3,FALSE) -> Africa | U28: =VLOOKUP(B28,'INFORM Severity - hidden'!$C$5:$V$170,20,FALSE) -> 44490
A29: {=IFERROR(INDEX(Lists!$B$2:$B$153,SMALL(IF(Lists!$I$2:$I$153="Individual",ROW(Lists!$B$2:$B$153)),ROW(25:25))-1,1),"")} -> Complex crisis in Eritrea | B29: =VLOOKUP(A29,Lists!$B$2:$G$153,2,FALSE) -> ERI001 | C29: =VLOOKUP(B29,'INFORM Severity - hidden'!$C$5:$D$160,2,FALSE) -> Eritrea | D29: =VLOOKUP(A29,Lists!$B$2:$G$153,3,FALSE) -> ERI | E29: =VLOOKUP(A29,Lists!$B$2:$G$153,5,FALSE) -> Complex crisis | F29: =IF(OR(N29="x",K29="x"),"x",ROUND((5-GEOMEAN(((5-K29)/5*4+1),((5-N29)/5*4+1),((5-N29)/5*4+1)))/4*3.5+Q29*0.3,1)) -> 3.8 | G29: =IF(F29="x","x",ROUNDUP(F29,0)) -> 4 | H29: =IF(N29="x","x",IF(K29="x","x",(IF(G29=5,"Very High",IF(G29=4,"High",IF(G29=3,"Medium",IF(G29=2,"Low","Very Low"))))))) -> High | I29: =INDEX(Trends!$D$3:$D$404,MATCH(B29,Trends!$C$3:$C$404,0)) -> Stable | J29: =VLOOKUP($B29,Reliability!$A$3:$I$170,9,FALSE) -> Medium | K29: =IF(OR(M29="x",L29="x"),"x",ROUND((5-GEOMEAN(((5-L29)/5*4+1),((5-M29)/5*4+1),((5-M29)/5*4+1)))/4*5,1)) -> 3.4 | L29: =VLOOKUP($B29,'Impact of the crisis'!$C$6:$N$170,12,FALSE) -> 3.8 | M29: =VLOOKUP($B29,'Impact of the crisis'!$C$6:$AB$170,26,FALSE) -> 3.1 | N29: =VLOOKUP($B29,'Conditions of people affected'!$C$6:$R$170,16,FALSE) -> 3.5 | O29: =VLOOKUP($B29,'Conditions of people affected'!$C$6:$R$170,9,FALSE) -> 4 | P29: =VLOOKUP($B29,'Conditions of people affected'!$C$6:$R$170,15,FALSE) -> 3 | Q29: =IF(OR(S29="x",R29="x"),R29,ROUND((5-GEOMEAN(((5-R29)/5*4+1),((5-S29)/5*4+1)))/4*5,1)) -> 4.6 | R29: =VLOOKUP($B29,'Complexity of the crisis'!$C$6:$AN$170,22,FALSE) -> 4.1 | S29: =VLOOKUP($B29,'Complexity of the crisis'!$C$6:$AN$170,38,FALSE) -> 5 | T29: =VLOOKUP(B29,Lists!$C$3:$E$163,3,FALSE) -> Africa | U29: =VLOOKUP(B29,'INFORM Severity - hidden'!$C$5:$V$170,20,FALSE) -> 44498
A30: {=IFERROR(INDEX(Lists!$B$2:$B$153,SMALL(IF(Lists!$I$2:$I$153="Individual",ROW(Lists!$B$2:$B$153)),ROW(26:26))-1,1),"")} -> Mixed migration flows in spain | B30: =VLOOKUP(A30,Lists!$B$2:$G$153,2,FALSE) -> ESP002 | C30: =VLOOKUP(B30,'INFORM Severity - hidden'!$C$5:$D$160,2,FALSE) -> Spain | D30: =VLOOKUP(A30,Lists!$B$2:$G$153,3,FALSE) -> ESP | E30: =VLOOKUP(A30,Lists!$B$2:$G$153,5,FALSE) -> International displacement | F30: =IF(OR(N30="x",K30="x"),"x",ROUND((5-GEOMEAN(((5-K30)/5*4+1),((5-N30)/5*4+1),((5-N30)/5*4+1)))/4*3.5+Q30*0.3,1)) -> 1.8 | G30: =IF(F30="x","x",ROUNDUP(F30,0)) -> 2 | H30: =IF(N30="x","x",IF(K30="x","x",(IF(G30=5,"Very High",IF(G30=4,"High",IF(G30=3,"Medium",IF(G30=2,"Low","Very Low"))))))) -> Low | I30: =INDEX(Trends!$D$3:$D$404,MATCH(B30,Trends!$C$3:$C$404,0)) -> Stable | J30: =VLOOKUP($B30,Reliability!$A$3:$I$170,9,FALSE) -> Medium | K30: =IF(OR(M30="x",L30="x"),"x",ROUND((5-GEOMEAN(((5-L30)/5*4+1),((5-M30)/5*4+1),((5-M30)/5*4+1)))/4*5,1)) -> 2.5 | L30: =VLOOKUP($B30,'Impact of the crisis'!$C$6:$N$170,12,FALSE) -> 2.2 | M30: =VLOOKUP($B30,'Impact of the crisis'!$C$6:$AB$170,26,FALSE) -> 2.6 | N30: =VLOOKUP($B30,'Conditions of people affected'!$C$6:$R$170,16,FALSE) -> 1.4 | O30: =VLOOKUP($B30,'Conditions of people affected'!$C$6:$R$170,9,FALSE) -> 1.8 | P30: =VLOOKUP($B30,'Conditions of people affected'!$C$6:$R$170,15,FALSE) -> 1 | Q30: =IF(OR(S30="x",R30="x"),R30,ROUND((5-GEOMEAN(((5-R30)/5*4+1),((5-S30)/5*4+1)))/4*5,1)) -> 1.8 | R30: =VLOOKUP($B30,'Complexity of the crisis'!$C$6:$AN$170,22,FALSE) -> 2.1 | S30: =VLOOKUP($B30,'Complexity of the crisis'!$C$6:$AN$170,38,FALSE) -> 1.5 | T30: =VLOOKUP(B30,Lists!$C$3:$E$163,3,FALSE) -> Europe | U30: =VLOOKUP(B30,'INFORM Severity - hidden'!$C$5:$V$170,20,FALSE) -> 44494
A31: {=IFERROR(INDEX(Lists!$B$2:$B$153,SMALL(IF(Lists!$I$2:$I$153="Individual",ROW(Lists!$B$2:$B$153)),ROW(27:27))-1,1),"")} -> Complex crisis in Ethiopia | B31: =VLOOKUP(A31,Lists!$B$2:$G$153,2,FALSE) -> ETH001 | C31: =VLOOKUP(B31,'INFORM Severity - hidden'!$C$5:$D$160,2,FALSE) -> Ethiopia | D31: =VLOOKUP(A31,Lists!$B$2:$G$153,3,FALSE) -> ETH | E31: =VLOOKUP(A31,Lists!$B$2:$G$153,5,FALSE) -> Complex crisis | F31: =IF(OR(N31="x",K31="x"),"x",ROUND((5-GEOMEAN(((5-K31)/5*4+1),((5-N31)/5*4+1),((5-N31)/5*4+1)))/4*3.5+Q31*0.3,1)) -> 4.8 | G31: =IF(F31="x","x",ROUNDUP(F31,0)) -> 5 | H31: =IF(N31="x","x",IF(K31="x","x",(IF(G31=5,"Very High",IF(G31=4,"High",IF(G31=3,"Medium",IF(G31=2,"Low","Very Low"))))))) -> Very High | I31: =INDEX(Trends!$D$3:$D$404,MATCH(B31,Trends!$C$3:$C$404,0)) -> Stable | J31: =VLOOKUP($B31,Reliability!$A$3:$I$170,9,FALSE) -> High | K31: =IF(OR(M31="x",L31="x"),"x",ROUND((5-GEOMEAN(((5-L31)/5*4+1),((5-M31)/5*4+1),((5-M31)/5*4+1)))/4*5,1)) -> 4.8 | L31: =VLOOKUP($B31,'Impact of the crisis'!$C$6:$N$170,12,FALSE) -> 5 | M31: =VLOOKUP($B31,'Impact of the crisis'!$C$6:$AB$170,26,FALSE) -> 4.7 | N31: =VLOOKUP($B31,'Conditions of people affected'!$C$6:$R$170,16,FALSE) -> 5 | O31: =VLOOKUP($B31,'Conditions of people affected'!$C$6:$R$170,9,FALSE) -> 5 | P31: =VLOOKUP($B31,'Conditions of people affected'!$C$6:$R$170,15,FALSE) -> 5 | Q31: =IF(OR(S31="x",R31="x"),R31,ROUND((5-GEOMEAN(((5-R31)/5*4+1),((5-S31)/5*4+1)))/4*5,1)) -> 4.6 | R31: =VLOOKUP($B31,'Complexity of the crisis'!$C$6:$AN$170,22,FALSE) -> 4.6 | S31: =VLOOKUP($B31,'Complexity of the crisis'!$C$6:$AN$170,38,FALSE) -> 4.5 | T31: =VLOOKUP(B31,Lists!$C$3:$E$163,3,FALSE) -> Africa | U31: =VLOOKUP(B31,'INFORM Severity - hidden'!$C$5:$V$170,20,FALSE) -> 44591
A32: {=IFERROR(INDEX(Lists!$B$2:$B$153,SMALL(IF(Lists!$I$2:$I$153="Individual",ROW(Lists!$B$2:$B$153)),ROW(28:28))-1,1),"")} -> International Displacement | B32: =VLOOKUP(A32,Lists!$B$2:$G$153,2,FALSE) -> ETH003 | C32: =VLOOKUP(B32,'INFORM Severity - hidden'!$C$5:$D$160,2,FALSE) -> Ethiopia | D32: =VLOOKUP(A32,Lists!$B$2:$G$153,3,FALSE) -> ETH | E32: =VLOOKUP(A32,Lists!$B$2:$G$153,5,FALSE) -> International displacement | F32: =IF(OR(N32="x",K32="x"),"x",ROUND((5-GEOMEAN(((5-K32)/5*4+1),((5-N32)/5*4+1),((5-N32)/5*4+1)))/4*3.5+Q32*0.3,1)) -> 3.2 | G32: =IF(F32="x","x",ROUNDUP(F32,0)) -> 4 | H32: =IF(N32="x","x",IF(K32="x","x",(IF(G32=5,"Very High",IF(G32=4,"High",IF(G32=3,"Medium",IF(G32=2,"Low","Very Low"))))))) -> High | I32: =INDEX(Trends!$D$3:$D$404,MATCH(B32,Trends!$C$3:$C$404,0)) -> Stable | J32: =VLOOKUP($B32,Reliability!$A$3:$I$170,9,FALSE) -> Very High | K32: =IF(OR(M32="x",L32="x"),"x",ROUND((5-GEOMEAN(((5-L32)/5*4+1),((5-M32)/5*4+1),((5-M32)/5*4+1)))/4*5,1)) -> 3.5 | L32: =VLOOKUP($B32,'Impact of the crisis'!$C$6:$N$170,12,FALSE) -> 5 | M32: =VLOOKUP($B32,'Impact of the crisis'!$C$6:$AB$170,26,FALSE) -> 2.2 | N32: =VLOOKUP($B32,'Conditions of people affected'!$C$6:$R$170,16,FALSE) -> 2.6 | O32: =VLOOKUP($B32,'Conditions of people affected'!$C$6:$R$170,9,FALSE) -> 3.2 | P32: =VLOOKUP($B32,'Conditions of people affected'!$C$6:$R$170,15,FALSE) -> 2 | Q32: =IF(OR(S32="x",R32="x"),R32,ROUND((5-GEOMEAN(((5-R32)/5*4+1),((5-S32)/5*4+1)))/4*5,1)) -> 3.9 | R32: =VLOOKUP($B32,'Complexity of the crisis'!$C$6:$AN$170,22,FALSE) -> 4.6 | S32: =VLOOKUP($B32,'Complexity of the crisis'!$C$6:$AN$170,38,FALSE) -> 3 | T32: =VLOOKUP(B32,Lists!$C$3:$E$163,3,FALSE) -> Africa | U32: =VLOOKUP(B32,'INFORM Severity - hidden'!$C$5:$V$170,20,FALSE) -> 44591
A33: {=IFERROR(INDEX(Lists!$B$2:$B$153,SMALL(IF(Lists!$I$2:$I$153="Individual",ROW(Lists!$B$2:$B$153)),ROW(29:29))-1,1),"")} -> Northern Ethiopia Conflict | B33: =VLOOKUP(A33,Lists!$B$2:$G$153,2,FALSE) -> ETH004 | C33: =VLOOKUP(B33,'INFORM Severity - hidden'!$C$5:$D$160,2,FALSE) -> Ethiopia | D33: =VLOOKUP(A33,Lists!$B$2:$G$153,3,FALSE) -> ETH | E33: =VLOOKUP(A33,Lists!$B$2:$G$153,5,FALSE) -> Conflict | F33: =IF(OR(N33="x",K33="x"),"x",ROUND((5-GEOMEAN(((5-K33)/5*4+1),((5-N33)/5*4+1),((5-N33)/5*4+1)))/4*3.5+Q33*0.3,1)) -> 4.5 | G33: =IF(F33="x","x",ROUNDUP(F33,0)) -> 5 | H33: =IF(N33="x","x",IF(K33="x","x",(IF(G33=5,"Very High",IF(G33=4,"High",IF(G33=3,"Medium",IF(G33=2,"Low","Very Low"))))))) -> Very High | I33: =INDEX(Trends!$D$3:$D$404,MATCH(B33,Trends!$C$3:$C$404,0)) -> Decreasing | J33: =VLOOKUP($B33,Reliability!$A$3:$I$170,9,FALSE) -> High | K33: =IF(OR(M33="x",L33="x"),"x",ROUND((5-GEOMEAN(((5-L33)/5*4+1),((5-M33)/5*4+1),((5-M33)/5*4+1)))/4*5,1)) -> 4.3 | L33: =VLOOKUP($B33,'Impact of the crisis'!$C$6:$N$170,12,FALSE) -> 3 | M33: =VLOOKUP($B33,'Impact of the crisis'!$C$6:$AB$170,26,FALSE) -> 4.7 | N33: =VLOOKUP($B33,'Conditions of people affected'!$C$6:$R$170,16,FALSE) -> 4.5 | O33: =VLOOKUP($B33,'Conditions of people affected'!$C$6:$R$170,9,FALSE) -> 5 | P33: =VLOOKUP($B33,'Conditions of people affected'!$C$6:$R$170,15,FALSE) -> 4 | Q33: =IF(OR(S33="x",R33="x"),R33,ROUND((5-GEOMEAN(((5-R33)/5*4+1),((5-S33)/5*4+1)))/4*5,1)) -> 4.6 | R33: =VLOOKUP($B33,'Complexity of the crisis'!$C$6:$AN$170,22,FALSE) -> 4.6 | S33: =VLOOKUP($B33,'Complexity of the crisis'!$C$6:$AN$170,38,FALSE) -> 4.5 | T33: =VLOOKUP(B33,Lists!$C$3:$E$163,3,FALSE) -> Africa | U33: =VLOOKUP(B33,'INFORM Severity - hidden'!$C$5:$V$170,20,FALSE) -> 44591
A34: {=IFERROR(INDEX(Lists!$B$2:$B$153,SMALL(IF(Lists!$I$2:$I$153="Individual",ROW(Lists!$B$2:$B$153)),ROW(30:30))-1,1),"")} -> Mixed migration flows in Greece | B34: =VLOOKUP(A34,Lists!$B$2:$G$153,2,FALSE) -> GRC002 | C34: =VLOOKUP(B34,'INFORM Severity - hidden'!$C$5:$D$160,2,FALSE) -> Greece | D34: =VLOOKUP(A34,Lists!$B$2:$G$153,3,FALSE) -> GRC | E34: =VLOOKUP(A34,Lists!$B$2:$G$153,5,FALSE) -> International displacement | F34: =IF(OR(N34="x",K34="x"),"x",ROUND((5-GEOMEAN(((5-K34)/5*4+1),((5-N34)/5*4+1),((5-N34)/5*4+1)))/4*3.5+Q34*0.3,1)) -> 1.6 | G34: =IF(F34="x","x",ROUNDUP(F34,0)) -> 2 | H34: =IF(N34="x","x",IF(K34="x","x",(IF(G34=5,"Very High",IF(G34=4,"High",IF(G34=3,"Medium",IF(G34=2,"Low","Very Low"))))))) -> Low | I34: =INDEX(Trends!$D$3:$D$404,MATCH(B34,Trends!$C$3:$C$404,0)) -> Decreasing | J34: =VLOOKUP($B34,Reliability!$A$3:$I$170,9,FALSE) -> High | K34: =IF(OR(M34="x",L34="x"),"x",ROUND((5-GEOMEAN(((5-L34)/5*4+1),((5-M34)/5*4+1),((5-M34)/5*4+1)))/4*5,1)) -> 1.9 | L34: =VLOOKUP($B34,'Impact of the crisis'!$C$6:$N$170,12,FALSE) -> 0.3 | M34: =VLOOKUP($B34,'Impact of the crisis'!$C$6:$AB$170,26,FALSE) -> 2.5 | N34: =VLOOKUP($B34,'Conditions of people affected'!$C$6:$R$170,16,FALSE) -> 1.2 | O34: =VLOOKUP($B34,'Conditions of people affected'!$C$6:$R$170,9,FALSE) -> 0.4 | P34: =VLOOKUP($B34,'Conditions of people affected'!$C$6:$R$170,15,FALSE) -> 2 | Q34: =IF(OR(S34="x",R34="x"),R34,ROUND((5-GEOMEAN(((5-R34)/5*4+1),((5-S34)/5*4+1)))/4*5,1)) -> 2.1 | R34: =VLOOKUP($B34,'Complexity of the crisis'!$C$6:$AN$170,22,FALSE) -> 2.2 | S34: =VLOOKUP($B34,'Complexity of the crisis'!$C$6:$AN$170,38,FALSE) -> 2 | T34: =VLOOKUP(B34,Lists!$C$3:$E$163,3,FALSE) -> Europe | U34: =VLOOKUP(B34,'INFORM Severity - hidden'!$C$5:$V$170,20,FALSE) -> 44559
A35: {=IFERROR(INDEX(Lists!$B$2:$B$153,SMALL(IF(Lists!$I$2:$I$153="Individual",ROW(Lists!$B$2:$B$153)),ROW(31:31))-1,1),"")} -> Complex crisis in Guatemala | B35: =VLOOKUP(A35,Lists!$B$2:$G$153,2,FALSE) -> GTM001 | C35: =VLOOKUP(B35,'INFORM Severity - hidden'!$C$5:$D$160,2,FALSE) -> Guatemala | D35: =VLOOKUP(A35,Lists!$B$2:$G$153,3,FALSE) -> GTM | E35: =VLOOKUP(A35,Lists!$B$2:$G$153,5,FALSE) -> Complex crisis | F35: =IF(OR(N35="x",K35="x"),"x",ROUND((5-GEOMEAN(((5-K35)/5*4+1),((5-N35)/5*4+1),((5-N35)/5*4+1)))/4*3.5+Q35*0.3,1)) -> 3.6 | G35: =IF(F35="x","x",ROUNDUP(F35,0)) -> 4 | H35: =IF(N35="x","x",IF(K35="x","x",(IF(G35=5,"Very High",IF(G35=4,"High",IF(G35=3,"Medium",IF(G35=2,"Low","Very Low"))))))) -> High | I35: =INDEX(Trends!$D$3:$D$404,MATCH(B35,Trends!$C$3:$C$404,0)) -> Increasing | J35: =VLOOKUP($B35,Reliability!$A$3:$I$170,9,FALSE) -> Very High | K35: =IF(OR(M35="x",L35="x"),"x",ROUND((5-GEOMEAN(((5-L35)/5*4+1),((5-M35)/5*4+1),((5-M35)/5*4+1)))/4*5,1)) -> 3.8 | L35: =VLOOKUP($B35,'Impact of the crisis'!$C$6:$N$170,12,FALSE) -> 4.4 | M35: =VLOOKUP($B35,'Impact of the crisis'!$C$6:$AB$170,26,FALSE) -> 3.5 | N35: =VLOOKUP($B35,'Conditions of people affected'!$C$6:$R$170,16,FALSE) -> 3.65 | O35: =VLOOKUP($B35,'Conditions of people affected'!$C$6:$R$170,9,FALSE) -> 4.3 | P35: =VLOOKUP($B35,'Conditions of people affected'!$C$6:$R$170,15,FALSE) -> 3 | Q35: =IF(OR(S35="x",R35="x"),R35,ROUND((5-GEOMEAN(((5-R35)/5*4+1),((5-S35)/5*4+1)))/4*5,1)) -> 3.2 | R35: =VLOOKUP($B35,'Complexity of the crisis'!$C$6:$AN$170,22,FALSE) -> 3.8 | S35: =VLOOKUP($B35,'Complexity of the crisis'!$C$6:$AN$170,38,FALSE) -> 2.5 | T35: =VLOOKUP(B35,Lists!$C$3:$E$163,3,FALSE) -> Americas | U35: =VLOOKUP(B35,'INFORM Severity - hidden'!$C$5:$V$170,20,FALSE) -> 44516
A36: {=IFERROR(INDEX(Lists!$B$2:$B$153,SMALL(IF(Lists!$I$2:$I$153="Individual",ROW(Lists!$B$2:$B$153)),ROW(32:32))-1,1),"")} -> Complex crisis in Honduras | B36: =VLOOKUP(A36,Lists!$B$2:$G$153,2,FALSE) -> HND001 | C36: =VLOOKUP(B36,'INFORM Severity - hidden'!$C$5:$D$160,2,FALSE) -> Honduras | D36: =VLOOKUP(A36,Lists!$B$2:$G$153,3,FALSE) -> HND | E36: =VLOOKUP(A36,Lists!$B$2:$G$153,5,FALSE) -> Complex crisis | F36: =IF(OR(N36="x",K36="x"),"x",ROUND((5-GEOMEAN(((5-K36)/5*4+1),((5-N36)/5*4+1),((5-N36)/5*4+1)))/4*3.5+Q36*0.3,1)) -> 3.8 | G36: =IF(F36="x","x",ROUNDUP(F36,0)) -> 4 | H36: =IF(N36="x","x",IF(K36="x","x",(IF(G36=5,"Very High",IF(G36=4,"High",IF(G36=3,"Medium",IF(G36=2,"Low","Very Low"))))))) -> High | I36: =INDEX(Trends!$D$3:$D$404,MATCH(B36,Trends!$C$3:$C$404,0)) -> Increasing | J36: =VLOOKUP($B36,Reliability!$A$3:$I$170,9,FALSE) -> Very High | K36: =IF(OR(M36="x",L36="x"),"x",ROUND((5-GEOMEAN(((5-L36)/5*4+1),((5-M36)/5*4+1),((5-M36)/5*4+1)))/4*5,1)) -> 3.8 | L36: =VLOOKUP($B36,'Impact of the crisis'!$C$6:$N$170,12,FALSE) -> 4.2 | M36: =VLOOKUP($B36,'Impact of the crisis'!$C$6:$AB$170,26,FALSE) -> 3.5 | N36: =VLOOKUP($B36,'Conditions of people affected'!$C$6:$R$170,16,FALSE) -> 4.1 | O36: =VLOOKUP($B36,'Conditions of people affected'!$C$6:$R$170,9,FALSE) -> 4.2 | P36: =VLOOKUP($B36,'Conditions of people affected'!$C$6:$R$170,15,FALSE) -> 4 | Q36: =IF(OR(S36="x",R36="x"),R36,ROUND((5-GEOMEAN(((5-R36)/5*4+1),((5-S36)/5*4+1)))/4*5,1)) -> 3.3 | R36: =VLOOKUP($B36,'Complexity of the crisis'!$C$6:$AN$170,22,FALSE) -> 3.6 | S36: =VLOOKUP($B36,'Complexity of the crisis'!$C$6:$AN$170,38,FALSE) -> 3 | T36: =VLOOKUP(B36,Lists!$C$3:$E$163,3,FALSE) -> Americas | U36: =VLOOKUP(B36,'INFORM Severity - hidden'!$C$5:$V$170,20,FALSE) -> 44517
A37: {=IFERROR(INDEX(Lists!$B$2:$B$153,SMALL(IF(Lists!$I$2:$I$153="Individual",ROW(Lists!$B$2:$B$153)),ROW(33:33))-1,1),"")} -> Complex crisis in Haiti | B37: =VLOOKUP(A37,Lists!$B$2:$G$153,2,FALSE) -> HTI001 | C37: =VLOOKUP(B37,'INFORM Severity - hidden'!$C$5:$D$160,2,FALSE) -> Haiti | D37: =VLOOKUP(A37,Lists!$B$2:$G$153,3,FALSE) -> HTI | E37: =VLOOKUP(A37,Lists!$B$2:$G$153,5,FALSE) -> Complex crisis | F37: =IF(OR(N37="x",K37="x"),"x",ROUND((5-GEOMEAN(((5-K37)/5*4+1),((5-N37)/5*4+1),((5-N37)/5*4+1)))/4*3.5+Q37*0.3,1)) -> 4.1 | G37: =IF(F37="x","x",ROUNDUP(F37,0)) -> 5 | H37: =IF(N37="x","x",IF(K37="x","x",(IF(G37=5,"Very High",IF(G37=4,"High",IF(G37=3,"Medium",IF(G37=2,"Low","Very Low"))))))) -> Very High | I37: =INDEX(Trends!$D$3:$D$404,MATCH(B37,Trends!$C$3:$C$404,0)) -> Stable | J37: =VLOOKUP($B37,Reliability!$A$3:$I$170,9,FALSE) -> High | K37: =IF(OR(M37="x",L37="x"),"x",ROUND((5-GEOMEAN(((5-L37)/5*4+1),((5-M37)/5*4+1),((5-M37)/5*4+1)))/4*5,1)) -> 3.8 | L37: =VLOOKUP($B37,'Impact of the crisis'!$C$6:$N$170,12,FALSE) -> 4 | M37: =VLOOKUP($B37,'Impact of the crisis'!$C$6:$AB$170,26,FALSE) -> 3.7 | N37: =VLOOKUP($B37,'Conditions of people affected'!$C$6:$R$170,16,FALSE) -> 4.75 | O37: =VLOOKUP($B37,'Conditions of people affected'!$C$6:$R$170,9,FALSE) -> 4.5 | P37: =VLOOKUP($B37,'Conditions of people affected'!$C$6:$R$170,15,FALSE) -> 5 | Q37: =IF(OR(S37="x",R37="x"),R37,ROUND((5-GEOMEAN(((5-R37)/5*4+1),((5-S37)/5*4+1)))/4*5,1)) -> 3.3 | R37: =VLOOKUP($B37,'Complexity of the crisis'!$C$6:$AN$170,22,FALSE) -> 3.6 | S37: =VLOOKUP($B37,'Complexity of the crisis'!$C$6:$AN$170,38,FALSE) -> 3 | T37: =VLOOKUP(B37,Lists!$C$3:$E$163,3,FALSE) -> Americas | U37: =VLOOKUP(B37,'INFORM Severity - hidden'!$C$5:$V$170,20,FALSE) -> 44495
A38: {=IFERROR(INDEX(Lists!$B$2:$B$153,SMALL(IF(Lists!$I$2:$I$153="Individual",ROW(Lists!$B$2:$B$153)),ROW(34:34))-1,1),"")} -> Nippes Earthquake | B38: =VLOOKUP(A38,Lists!$B$2:$G$153,2,FALSE) -> HTI002 | C38: =VLOOKUP(B38,'INFORM Severity - hidden'!$C$5:$D$160,2,FALSE) -> Haiti | D38: =VLOOKUP(A38,Lists!$B$2:$G$153,3,FALSE) -> HTI | E38: =VLOOKUP(A38,Lists!$B$2:$G$153,5,FALSE) -> Earthquake | F38: =IF(OR(N38="x",K38="x"),"x",ROUND((5-GEOMEAN(((5-K38)/5*4+1),((5-N38)/5*4+1),((5-N38)/5*4+1)))/4*3.5+Q38*0.3,1)) -> 3.1 | G38: =IF(F38="x","x",ROUNDUP(F38,0)) -> 4 | H38: =IF(N38="x","x",IF(K38="x","x",(IF(G38=5,"Very High",IF(G38=4,"High",IF(G38=3,"Medium",IF(G38=2,"Low","Very Low"))))))) -> High | I38: =INDEX(Trends!$D$3:$D$404,MATCH(B38,Trends!$C$3:$C$404,0)) -> Stable | J38: =VLOOKUP($B38,Reliability!$A$3:$I$170,9,FALSE) -> High | K38: =IF(OR(M38="x",L38="x"),"x",ROUND((5-GEOMEAN(((5-L38)/5*4+1),((5-M38)/5*4+1),((5-M38)/5*4+1)))/4*5,1)) -> 3.1 | L38: =VLOOKUP($B38,'Impact of the crisis'!$C$6:$N$170,12,FALSE) -> 2.4 | M38: =VLOOKUP($B38,'Impact of the crisis'!$C$6:$AB$170,26,FALSE) -> 3.4 | N38: =VLOOKUP($B38,'Conditions of people affected'!$C$6:$R$170,16,FALSE) -> 3 | O38: =VLOOKUP($B38,'Conditions of people affected'!$C$6:$R$170,9,FALSE) -> 3 | P38: =VLOOKUP($B38,'Conditions of people affected'!$C$6:$R$170,15,FALSE) -> 3 | Q38: =IF(OR(S38="x",R38="x"),R38,ROUND((5-GEOMEAN(((5-R38)/5*4+1),((5-S38)/5*4+1)))/4*5,1)) -> 3.3 | R38: =VLOOKUP($B38,'Complexity of the crisis'!$C$6:$AN$170,22,FALSE) -> 3.6 | S38: =VLOOKUP($B38,'Complexity of the crisis'!$C$6:$AN$170,38,FALSE) -> 3 | T38: =VLOOKUP(B38,Lists!$C$3:$E$163,3,FALSE) -> Americas | U38: =VLOOKUP(B38,'INFORM Severity - hidden'!$C$5:$V$170,20,FALSE) -> 44495
A39: {=IFERROR(INDEX(Lists!$B$2:$B$153,SMALL(IF(Lists!$I$2:$I$153="Individual",ROW(Lists!$B$2:$B$153)),ROW(35:35))-1,1),"")} -> Papua Conflict | B39: =VLOOKUP(A39,Lists!$B$2:$G$153,2,FALSE) -> IDN002 | C39: =VLOOKUP(B39,'INFORM Severity - hidden'!$C$5:$D$160,2,FALSE) -> Indonesia | D39: =VLOOKUP(A39,Lists!$B$2:$G$153,3,FALSE) -> IDN | E39: =VLOOKUP(A39,Lists!$B$2:$G$153,5,FALSE) -> Conflict | F39: =IF(OR(N39="x",K39="x"),"x",ROUND((5-GEOMEAN(((5-K39)/5*4+1),((5-N39)/5*4+1),((5-N39)/5*4+1)))/4*3.5+Q39*0.3,1)) -> 2.2 | G39: =IF(F39="x","x",ROUNDUP(F39,0)) -> 3 | H39: =IF(N39="x","x",IF(K39="x","x",(IF(G39=5,"Very High",IF(G39=4,"High",IF(G39=3,"Medium",IF(G39=2,"Low","Very Low"))))))) -> Medium | I39: =INDEX(Trends!$D$3:$D$404,MATCH(B39,Trends!$C$3:$C$404,0)) -> - | J39: =VLOOKUP($B39,Reliability!$A$3:$I$170,9,FALSE) -> Medium | K39: =IF(OR(M39="x",L39="x"),"x",ROUND((5-GEOMEAN(((5-L39)/5*4+1),((5-M39)/5*4+1),((5-M39)/5*4+1)))/4*5,1)) -> 2.8 | L39: =VLOOKUP($B39,'Impact of the crisis'!$C$6:$N$170,12,FALSE) -> 1.9 | M39: =VLOOKUP($B39,'Impact of the crisis'!$C$6:$AB$170,26,FALSE) -> 3.2 | N39: =VLOOKUP($B39,'Conditions of people affected'!$C$6:$R$170,16,FALSE) -> 1.15 | O39: =VLOOKUP($B39,'Conditions of people affected'!$C$6:$R$170,9,FALSE) -> 1.3 | P39: =VLOOKUP($B39,'Conditions of people affected'!$C$6:$R$170,15,FALSE) -> 1 | Q39: =IF(OR(S39="x",R39="x"),R39,ROUND((5-GEOMEAN(((5-R39)/5*4+1),((5-S39)/5*4+1)))/4*5,1)) -> 3.3 | R39: =VLOOKUP($B39,'Complexity of the crisis'!$C$6:$AN$170,22,FALSE) -> 3 | S39: =VLOOKUP($B39,'Complexity of the crisis'!$C$6:$AN$170,38,FALSE) -> 3.5 | T39: =VLOOKUP(B39,Lists!$C$3:$E$163,3,FALSE) -> Asia | U39: =VLOOKUP(B39,'INFORM Severity - hidden'!$C$5:$V$170,20,FALSE) -> 44584
A40: {=IFERROR(INDEX(Lists!$B$2:$B$153,SMALL(IF(Lists!$I$2:$I$153="Individual",ROW(Lists!$B$2:$B$153)),ROW(36:36))-1,1),"")} -> Conflict in Jammu and Kashmir | B40: =VLOOKUP(A40,Lists!$B$2:$G$153,2,FALSE) -> IND002 | C40: =VLOOKUP(B40,'INFORM Severity - hidden'!$C$5:$D$160,2,FALSE) -> India | D40: =VLOOKUP(A40,Lists!$B$2:$G$153,3,FALSE) -> IND | E40: =VLOOKUP(A40,Lists!$B$2:$G$153,5,FALSE) -> Conflict | F40: =IF(OR(N40="x",K40="x"),"x",ROUND((5-GEOMEAN(((5-K40)/5*4+1),((5-N40)/5*4+1),((5-N40)/5*4+1)))/4*3.5+Q40*0.3,1)) -> x | G40: =IF(F40="x","x",ROUNDUP(F40,0)) -> x | H40: =IF(N40="x","x",IF(K40="x","x",(IF(G40=5,"Very High",IF(G40=4,"High",IF(G40=3,"Medium",IF(G40=2,"Low","Very Low"))))))) -> x | I40: =INDEX(Trends!$D$3:$D$404,MATCH(B40,Trends!$C$3:$C$404,0)) -> - | J40: =VLOOKUP($B40,Reliability!$A$3:$I$170,9,FALSE) -> Very Low | K40: =IF(OR(M40="x",L40="x"),"x",ROUND((5-GEOMEAN(((5-L40)/5*4+1),((5-M40)/5*4+1),((5-M40)/5*4+1)))/4*5,1)) -> 2.8 | L40: =VLOOKUP($B40,'Impact of the crisis'!$C$6:$N$170,12,FALSE) -> 2 | M40: =VLOOKUP($B40,'Impact of the crisis'!$C$6:$AB$170,26,FALSE) -> 3.2 | N40: =VLOOKUP($B40,'Conditions of people affected'!$C$6:$R$170,16,FALSE) -> x | O40: =VLOOKUP($B40,'Conditions of people affected'!$C$6:$R$170,9,FALSE) -> x | P40: =VLOOKUP($B40,'Conditions of people affected'!$C$6:$R$170,15,FALSE) -> x | Q40: =IF(OR(S40="x",R40="x"),R40,ROUND((5-GEOMEAN(((5-R40)/5*4+1),((5-S40)/5*4+1)))/4*5,1)) -> 2.2 | R40: =VLOOKUP($B40,'Complexity of the crisis'!$C$6:$AN$170,22,FALSE) -> 3.1 | S40: =VLOOKUP($B40,'Complexity of the crisis'!$C$6:$AN$170,38,FALSE) -> 1 | T40: =VLOOKUP(B40,Lists!$C$3:$E$163,3,FALSE) -> Asia | U40: =VLOOKUP(B40,'INFORM Severity - hidden'!$C$5:$V$170,20,FALSE) -> 44584
A41: {=IFERROR(INDEX(Lists!$B$2:$B$153,SMALL(IF(Lists!$I$2:$I$153="Individual",ROW(Lists!$B$2:$B$153)),ROW(37:37))-1,1),"")} -> Afghan Refugees in Iran | B41: =VLOOKUP(A41,Lists!$B$2:$G$153,2,FALSE) -> IRN004 | C41: =VLOOKUP(B41,'INFORM Severity - hidden'!$C$5:$D$160,2,FALSE) -> Iran | D41: =VLOOKUP(A41,Lists!$B$2:$G$153,3,FALSE) -> IRN | E41: =VLOOKUP(A41,Lists!$B$2:$G$153,5,FALSE) -> International displacement | F41: =IF(OR(N41="x",K41="x"),"x",ROUND((5-GEOMEAN(((5-K41)/5*4+1),((5-N41)/5*4+1),((5-N41)/5*4+1)))/4*3.5+Q41*0.3,1)) -> 3.5 | G41: =IF(F41="x","x",ROUNDUP(F41,0)) -> 4 | H41: =IF(N41="x","x",IF(K41="x","x",(IF(G41=5,"Very High",IF(G41=4,"High",IF(G41=3,"Medium",IF(G41=2,"Low","Very Low"))))))) -> High | I41: =INDEX(Trends!$D$3:$D$404,MATCH(B41,Trends!$C$3:$C$404,0)) -> Increasing | J41: =VLOOKUP($B41,Reliability!$A$3:$I$170,9,FALSE) -> High | K41: =IF(OR(M41="x",L41="x"),"x",ROUND((5-GEOMEAN(((5-L41)/5*4+1),((5-M41)/5*4+1),((5-M41)/5*4+1)))/4*5,1)) -> 2.8 | L41: =VLOOKUP($B41,'Impact of the crisis'!$C$6:$N$170,12,FALSE) -> 2.7 | M41: =VLOOKUP($B41,'Impact of the crisis'!$C$6:$AB$170,26,FALSE) -> 2.8 | N41: =VLOOKUP($B41,'Conditions of people affected'!$C$6:$R$170,16,FALSE) -> 4.1 | O41: =VLOOKUP($B41,'Conditions of people affected'!$C$6:$R$170,9,FALSE) -> 4.2 | P41: =VLOOKUP($B41,'Conditions of people affected'!$C$6:$R$170,15,FALSE) -> 4 | Q41: =IF(OR(S41="x",R41="x"),R41,ROUND((5-GEOMEAN(((5-R41)/5*4+1),((5-S41)/5*4+1)))/4*5,1)) -> 2.9 | R41: =VLOOKUP($B41,'Complexity of the crisis'!$C$6:$AN$170,22,FALSE) -> 3.3 | S41: =VLOOKUP($B41,'Complexity of the crisis'!$C$6:$AN$170,38,FALSE) -> 2.5 | T41: =VLOOKUP(B41,Lists!$C$3:$E$163,3,FALSE) -> Middle east | U41: =VLOOKUP(B41,'INFORM Severity - hidden'!$C$5:$V$170,20,FALSE) -> 44558
A42: {=IFERROR(INDEX(Lists!$B$2:$B$153,SMALL(IF(Lists!$I$2:$I$153="Individual",ROW(Lists!$B$2:$B$153)),ROW(38:38))-1,1),"")} -> Conflict in Iraq | B42: =VLOOKUP(A42,Lists!$B$2:$G$153,2,FALSE) -> IRQ002 | C42: =VLOOKUP(B42,'INFORM Severity - hidden'!$C$5:$D$160,2,FALSE) -> Iraq | D42: =VLOOKUP(A42,Lists!$B$2:$G$153,3,FALSE) -> IRQ | E42: =VLOOKUP(A42,Lists!$B$2:$G$153,5,FALSE) -> Conflict | F42: =IF(OR(N42="x",K42="x"),"x",ROUND((5-GEOMEAN(((5-K42)/5*4+1),((5-N42)/5*4+1),((5-N42)/5*4+1)))/4*3.5+Q42*0.3,1)) -> 4 | G42: =IF(F42="x","x",ROUNDUP(F42,0)) -> 4 | H42: =IF(N42="x","x",IF(K42="x","x",(IF(G42=5,"Very High",IF(G42=4,"High",IF(G42=3,"Medium",IF(G42=2,"Low","Very Low"))))))) -> High | I42: =INDEX(Trends!$D$3:$D$404,MATCH(B42,Trends!$C$3:$C$404,0)) -> Decreasing | J42: =VLOOKUP($B42,Reliability!$A$3:$I$170,9,FALSE) -> Very High | K42: =IF(OR(M42="x",L42="x"),"x",ROUND((5-GEOMEAN(((5-L42)/5*4+1),((5-M42)/5*4+1),((5-M42)/5*4+1)))/4*5,1)) -> 4.3 | L42: =VLOOKUP($B42,'Impact of the crisis'!$C$6:$N$170,12,FALSE) -> 4.9 | M42: =VLOOKUP($B42,'Impact of the crisis'!$C$6:$AB$170,26,FALSE) -> 3.9 | N42: =VLOOKUP($B42,'Conditions of people affected'!$C$6:$R$170,16,FALSE) -> 3.5 | O42: =VLOOKUP($B42,'Conditions of people affected'!$C$6:$R$170,9,FALSE) -> 4 | P42: =VLOOKUP($B42,'Conditions of people affected'!$C$6:$R$170,15,FALSE) -> 3 | Q42: =IF(OR(S42="x",R42="x"),R42,ROUND((5-GEOMEAN(((5-R42)/5*4+1),((5-S42)/5*4+1)))/4*5,1)) -> 4.5 | R42: =VLOOKUP($B42,'Complexity of the crisis'!$C$6:$AN$170,22,FALSE) -> 4.4 | S42: =VLOOKUP($B42,'Complexity of the crisis'!$C$6:$AN$170,38,FALSE) -> 4.5 | T42: =VLOOKUP(B42,Lists!$C$3:$E$163,3,FALSE) -> Middle east | U42: =VLOOKUP(B42,'INFORM Severity - hidden'!$C$5:$V$170,20,FALSE) -> 44584
A43: {=IFERROR(INDEX(Lists!$B$2:$B$153,SMALL(IF(Lists!$I$2:$I$153="Individual",ROW(Lists!$B$2:$B$153)),ROW(39:39))-1,1),"")} -> Syrian and Palestinian refugees in iraq | B43: =VLOOKUP(A43,Lists!$B$2:$G$153,2,FALSE) -> IRQ003 | C43: =VLOOKUP(B43,'INFORM Severity - hidden'!$C$5:$D$160,2,FALSE) -> Iraq | D43: =VLOOKUP(A43,Lists!$B$2:$G$153,3,FALSE) -> IRQ | E43: =VLOOKUP(A43,Lists!$B$2:$G$153,5,FALSE) -> International displacement | F43: =IF(OR(N43="x",K43="x"),"x",ROUND((5-GEOMEAN(((5-K43)/5*4+1),((5-N43)/5*4+1),((5-N43)/5*4+1)))/4*3.5+Q43*0.3,1)) -> 3 | G43: =IF(F43="x","x",ROUNDUP(F43,0)) -> 3 | H43: =IF(N43="x","x",IF(K43="x","x",(IF(G43=5,"Very High",IF(G43=4,"High",IF(G43=3,"Medium",IF(G43=2,"Low","Very Low"))))))) -> Medium | I43: =INDEX(Trends!$D$3:$D$404,MATCH(B43,Trends!$C$3:$C$404,0)) -> Stable | J43: =VLOOKUP($B43,Reliability!$A$3:$I$170,9,FALSE) -> Medium | K43: =IF(OR(M43="x",L43="x"),"x",ROUND((5-GEOMEAN(((5-L43)/5*4+1),((5-M43)/5*4+1),((5-M43)/5*4+1)))/4*5,1)) -> 1.8 | L43: =VLOOKUP($B43,'Impact of the crisis'!$C$6:$N$170,12,FALSE) -> 1.5 | M43: =VLOOKUP($B43,'Impact of the crisis'!$C$6:$AB$170,26,FALSE) -> 2 | N43: =VLOOKUP($B43,'Conditions of people affected'!$C$6:$R$170,16,FALSE) -> 2.9 | O43: =VLOOKUP($B43,'Conditions of people affected'!$C$6:$R$170,9,FALSE) -> 2.8 | P43: =VLOOKUP($B43,'Conditions of people affected'!$C$6:$R$170,15,FALSE) -> 3 | Q43: =IF(OR(S43="x",R43="x"),R43,ROUND((5-GEOMEAN(((5-R43)/5*4+1),((5-S43)/5*4+1)))/4*5,1)) -> 4 | R43: =VLOOKUP($B43,'Complexity of the crisis'!$C$6:$AN$170,22,FALSE) -> 4.4 | S43: =VLOOKUP($B43,'Complexity of the crisis'!$C$6:$AN$170,38,FALSE) -> 3.5 | T43: =VLOOKUP(B43,Lists!$C$3:$E$163,3,FALSE) -> Middle east | U43: =VLOOKUP(B43,'INFORM Severity - hidden'!$C$5:$V$170,20,FALSE) -> 44584
A44: {=IFERROR(INDEX(Lists!$B$2:$B$153,SMALL(IF(Lists!$I$2:$I$153="Individual",ROW(Lists!$B$2:$B$153)),ROW(40:40))-1,1),"")} -> Mixed migration flows in Italy | B44: =VLOOKUP(A44,Lists!$B$2:$G$153,2,FALSE) -> ITA002 | C44: =VLOOKUP(B44,'INFORM Severity - hidden'!$C$5:$D$160,2,FALSE) -> Italy | D44: =VLOOKUP(A44,Lists!$B$2:$G$153,3,FALSE) -> ITA | E44: =VLOOKUP(A44,Lists!$B$2:$G$153,5,FALSE) -> International displacement | F44: =IF(OR(N44="x",K44="x"),"x",ROUND((5-GEOMEAN(((5-K44)/5*4+1),((5-N44)/5*4+1),((5-N44)/5*4+1)))/4*3.5+Q44*0.3,1)) -> 1.9 | G44: =IF(F44="x","x",ROUNDUP(F44,0)) -> 2 | H44: =IF(N44="x","x",IF(K44="x","x",(IF(G44=5,"Very High",IF(G44=4,"High",IF(G44=3,"Medium",IF(G44=2,"Low","Very Low"))))))) -> Low | I44: =INDEX(Trends!$D$3:$D$404,MATCH(B44,Trends!$C$3:$C$404,0)) -> Stable | J44: =VLOOKUP($B44,Reliability!$A$3:$I$170,9,FALSE) -> Medium | K44: =IF(OR(M44="x",L44="x"),"x",ROUND((5-GEOMEAN(((5-L44)/5*4+1),((5-M44)/5*4+1),((5-M44)/5*4+1)))/4*5,1)) -> 2.7 | L44: =VLOOKUP($B44,'Impact of the crisis'!$C$6:$N$170,12,FALSE) -> 1.7 | M44: =VLOOKUP($B44,'Impact of the crisis'!$C$6:$AB$170,26,FALSE) -> 3.1 | N44: =VLOOKUP($B44,'Conditions of people affected'!$C$6:$R$170,16,FALSE) -> 1.6 | O44: =VLOOKUP($B44,'Conditions of people affected'!$C$6:$R$170,9,FALSE) -> 2.2 | P44: =VLOOKUP($B44,'Conditions of people affected'!$C$6:$R$170,15,FALSE) -> 1 | Q44: =IF(OR(S44="x",R44="x"),R44,ROUND((5-GEOMEAN(((5-R44)/5*4+1),((5-S44)/5*4+1)))/4*5,1)) -> 1.5 | R44: =VLOOKUP($B44,'Complexity of the crisis'!$C$6:$AN$170,22,FALSE) -> 1.5 | S44: =VLOOKUP($B44,'Complexity of the crisis'!$C$6:$AN$170,38,FALSE) -> 1.5 | T44: =VLOOKUP(B44,Lists!$C$3:$E$163,3,FALSE) -> Europe | U44: =VLOOKUP(B44,'INFORM Severity - hidden'!$C$5:$V$170,20,FALSE) -> 44494
A45: {=IFERROR(INDEX(Lists!$B$2:$B$153,SMALL(IF(Lists!$I$2:$I$153="Individual",ROW(Lists!$B$2:$B$153)),ROW(41:41))-1,1),"")} -> Syrian refugees in Jordan | B45: =VLOOKUP(A45,Lists!$B$2:$G$153,2,FALSE) -> JOR002 | C45: =VLOOKUP(B45,'INFORM Severity - hidden'!$C$5:$D$160,2,FALSE) -> Jordan | D45: =VLOOKUP(A45,Lists!$B$2:$G$153,3,FALSE) -> JOR | E45: =VLOOKUP(A45,Lists!$B$2:$G$153,5,FALSE) -> International displacement | F45: =IF(OR(N45="x",K45="x"),"x",ROUND((5-GEOMEAN(((5-K45)/5*4+1),((5-N45)/5*4+1),((5-N45)/5*4+1)))/4*3.5+Q45*0.3,1)) -> 2.7 | G45: =IF(F45="x","x",ROUNDUP(F45,0)) -> 3 | H45: =IF(N45="x","x",IF(K45="x","x",(IF(G45=5,"Very High",IF(G45=4,"High",IF(G45=3,"Medium",IF(G45=2,"Low","Very Low"))))))) -> Medium | I45: =INDEX(Trends!$D$3:$D$404,MATCH(B45,Trends!$C$3:$C$404,0)) -> Decreasing | J45: =VLOOKUP($B45,Reliability!$A$3:$I$170,9,FALSE) -> High | K45: =IF(OR(M45="x",L45="x"),"x",ROUND((5-GEOMEAN(((5-L45)/5*4+1),((5-M45)/5*4+1),((5-M45)/5*4+1)))/4*5,1)) -> 2.7 | L45: =VLOOKUP($B45,'Impact of the crisis'!$C$6:$N$170,12,FALSE) -> 3 | M45: =VLOOKUP($B45,'Impact of the crisis'!$C$6:$AB$170,26,FALSE) -> 2.6 | N45: =VLOOKUP($B45,'Conditions of people affected'!$C$6:$R$170,16,FALSE) -> 3.05 | O45: =VLOOKUP($B45,'Conditions of people affected'!$C$6:$R$170,9,FALSE) -> 3.1 | P45: =VLOOKUP($B45,'Conditions of people affected'!$C$6:$R$170,15,FALSE) -> 3 | Q45: =IF(OR(S45="x",R45="x"),R45,ROUND((5-GEOMEAN(((5-R45)/5*4+1),((5-S45)/5*4+1)))/4*5,1)) -> 2.3 | R45: =VLOOKUP($B45,'Complexity of the crisis'!$C$6:$AN$170,22,FALSE) -> 3 | S45: =VLOOKUP($B45,'Complexity of the crisis'!$C$6:$AN$170,38,FALSE) -> 1.5 | T45: =VLOOKUP(B45,Lists!$C$3:$E$163,3,FALSE) -> Middle east | U45: =VLOOKUP(B45,'INFORM Severity - hidden'!$C$5:$V$170,20,FALSE) -> 44584
A46: {=IFERROR(INDEX(Lists!$B$2:$B$153,SMALL(IF(Lists!$I$2:$I$153="Individual",ROW(Lists!$B$2:$B$153)),ROW(42:42))-1,1),"")} -> Refugee situation in Kenya | B46: =VLOOKUP(A46,Lists!$B$2:$G$153,2,FALSE) -> KEN002 | C46: =VLOOKUP(B46,'INFORM Severity - hidden'!$C$5:$D$160,2,FALSE) -> Kenya | D46: =VLOOKUP(A46,Lists!$B$2:$G$153,3,FALSE) -> KEN | E46: =VLOOKUP(A46,Lists!$B$2:$G$153,5,FALSE) -> International displacement | F46: =IF(OR(N46="x",K46="x"),"x",ROUND((5-GEOMEAN(((5-K46)/5*4+1),((5-N46)/5*4+1),((5-N46)/5*4+1)))/4*3.5+Q46*0.3,1)) -> 2.8 | G46: =IF(F46="x","x",ROUNDUP(F46,0)) -> 3 | H46: =IF(N46="x","x",IF(K46="x","x",(IF(G46=5,"Very High",IF(G46=4,"High",IF(G46=3,"Medium",IF(G46=2,"Low","Very Low"))))))) -> Medium | I46: =INDEX(Trends!$D$3:$D$404,MATCH(B46,Trends!$C$3:$C$404,0)) -> Stable | J46: =VLOOKUP($B46,Reliability!$A$3:$I$170,9,FALSE) -> High | K46: =IF(OR(M46="x",L46="x"),"x",ROUND((5-GEOMEAN(((5-L46)/5*4+1),((5-M46)/5*4+1),((5-M46)/5*4+1)))/4*5,1)) -> 2.1 | L46: =VLOOKUP($B46,'Impact of the crisis'!$C$6:$N$170,12,FALSE) -> 0.8 | M46: =VLOOKUP($B46,'Impact of the crisis'!$C$6:$AB$170,26,FALSE) -> 2.6 | N46: =VLOOKUP($B46,'Conditions of people affected'!$C$6:$R$170,16,FALSE) -> 2.95 | O46: =VLOOKUP($B46,'Conditions of people affected'!$C$6:$R$170,9,FALSE) -> 2.9 | P46: =VLOOKUP($B46,'Conditions of people affected'!$C$6:$R$170,15,FALSE) -> 3 | Q46: =IF(OR(S46="x",R46="x"),R46,ROUND((5-GEOMEAN(((5-R46)/5*4+1),((5-S46)/5*4+1)))/4*5,1)) -> 2.9 | R46: =VLOOKUP($B46,'Complexity of the crisis'!$C$6:$AN$170,22,FALSE) -> 3.6 | S46: =VLOOKUP($B46,'Complexity of the crisis'!$C$6:$AN$170,38,FALSE) -> 2 | T46: =VLOOKUP(B46,Lists!$C$3:$E$163,3,FALSE) -> Africa | U46: =VLOOKUP(B46,'INFORM Severity - hidden'!$C$5:$V$170,20,FALSE) -> 44547
A47: {=IFERROR(INDEX(Lists!$B$2:$B$153,SMALL(IF(Lists!$I$2:$I$153="Individual",ROW(Lists!$B$2:$B$153)),ROW(43:43))-1,1),"")} -> Drought in Kenya | B47: =VLOOKUP(A47,Lists!$B$2:$G$153,2,FALSE) -> KEN003 | C47: =VLOOKUP(B47,'INFORM Severity - hidden'!$C$5:$D$160,2,FALSE) -> Kenya | D47: =VLOOKUP(A47,Lists!$B$2:$G$153,3,FALSE) -> KEN | E47: =VLOOKUP(A47,Lists!$B$2:$G$153,5,FALSE) -> Drought | F47: =IF(OR(N47="x",K47="x"),"x",ROUND((5-GEOMEAN(((5-K47)/5*4+1),((5-N47)/5*4+1),((5-N47)/5*4+1)))/4*3.5+Q47*0.3,1)) -> 3.1 | G47: =IF(F47="x","x",ROUNDUP(F47,0)) -> 4 | H47: =IF(N47="x","x",IF(K47="x","x",(IF(G47=5,"Very High",IF(G47=4,"High",IF(G47=3,"Medium",IF(G47=2,"Low","Very Low"))))))) -> High | I47: =INDEX(Trends!$D$3:$D$404,MATCH(B47,Trends!$C$3:$C$404,0)) -> Increasing | J47: =VLOOKUP($B47,Reliability!$A$3:$I$170,9,FALSE) -> Medium | K47: =IF(OR(M47="x",L47="x"),"x",ROUND((5-GEOMEAN(((5-L47)/5*4+1),((5-M47)/5*4+1),((5-M47)/5*4+1)))/4*5,1)) -> 2.2 | L47: =VLOOKUP($B47,'Impact of the crisis'!$C$6:$N$170,12,FALSE) -> 3.8 | M47: =VLOOKUP($B47,'Impact of the crisis'!$C$6:$AB$170,26,FALSE) -> 1.1 | N47: =VLOOKUP($B47,'Conditions of people affected'!$C$6:$R$170,16,FALSE) -> 3.55 | O47: =VLOOKUP($B47,'Conditions of people affected'!$C$6:$R$170,9,FALSE) -> 4.1 | P47: =VLOOKUP($B47,'Conditions of people affected'!$C$6:$R$170,15,FALSE) -> 3 | Q47: =IF(OR(S47="x",R47="x"),R47,ROUND((5-GEOMEAN(((5-R47)/5*4+1),((5-S47)/5*4+1)))/4*5,1)) -> 2.9 | R47: =VLOOKUP($B47,'Complexity of the crisis'!$C$6:$AN$170,22,FALSE) -> 3.6 | S47: =VLOOKUP($B47,'Complexity of the crisis'!$C$6:$AN$170,38,FALSE) -> 2 | T47: =VLOOKUP(B47,Lists!$C$3:$E$163,3,FALSE) -> Africa | U47: =VLOOKUP(B47,'INFORM Severity - hidden'!$C$5:$V$170,20,FALSE) -> 44547
A48: {=IFERROR(INDEX(Lists!$B$2:$B$153,SMALL(IF(Lists!$I$2:$I$153="Individual",ROW(Lists!$B$2:$B$153)),ROW(44:44))-1,1),"")} -> Syrian refugees in Lebanon | B48: =VLOOKUP(A48,Lists!$B$2:$G$153,2,FALSE) -> LBN002 | C48: =VLOOKUP(B48,'INFORM Severity - hidden'!$C$5:$D$160,2,FALSE) -> Lebanon | D48: =VLOOKUP(A48,Lists!$B$2:$G$153,3,FALSE) -> LBN | E48: =VLOOKUP(A48,Lists!$B$2:$G$153,5,FALSE) -> International displacement | F48: =IF(OR(N48="x",K48="x"),"x",ROUND((5-GEOMEAN(((5-K48)/5*4+1),((5-N48)/5*4+1),((5-N48)/5*4+1)))/4*3.5+Q48*0.3,1)) -> 3.4 | G48: =IF(F48="x","x",ROUNDUP(F48,0)) -> 4 | H48: =IF(N48="x","x",IF(K48="x","x",(IF(G48=5,"Very High",IF(G48=4,"High",IF(G48=3,"Medium",IF(G48=2,"Low","Very Low"))))))) -> High | I48: =INDEX(Trends!$D$3:$D$404,MATCH(B48,Trends!$C$3:$C$404,0)) -> Stable | J48: =VLOOKUP($B48,Reliability!$A$3:$I$170,9,FALSE) -> High | K48: =IF(OR(M48="x",L48="x"),"x",ROUND((5-GEOMEAN(((5-L48)/5*4+1),((5-M48)/5*4+1),((5-M48)/5*4+1)))/4*5,1)) -> 3.2 | L48: =VLOOKUP($B48,'Impact of the crisis'!$C$6:$N$170,12,FALSE) -> 3.6 | M48: =VLOOKUP($B48,'Impact of the crisis'!$C$6:$AB$170,26,FALSE) -> 3 | N48: =VLOOKUP($B48,'Conditions of people affected'!$C$6:$R$170,16,FALSE) -> 3.8 | O48: =VLOOKUP($B48,'Conditions of people affected'!$C$6:$R$170,9,FALSE) -> 3.6 | P48: =VLOOKUP($B48,'Conditions of people affected'!$C$6:$R$170,15,FALSE) -> 4 | Q48: =IF(OR(S48="x",R48="x"),R48,ROUND((5-GEOMEAN(((5-R48)/5*4+1),((5-S48)/5*4+1)))/4*5,1)) -> 2.9 | R48: =VLOOKUP($B48,'Complexity of the crisis'!$C$6:$AN$170,22,FALSE) -> 3.3 | S48: =VLOOKUP($B48,'Complexity of the crisis'!$C$6:$AN$170,38,FALSE) -> 2.5 | T48: =VLOOKUP(B48,Lists!$C$3:$E$163,3,FALSE) -> Middle east | U48: =VLOOKUP(B48,'INFORM Severity - hidden'!$C$5:$V$170,20,FALSE) -> 44584
A49: {=IFERROR(INDEX(Lists!$B$2:$B$153,SMALL(IF(Lists!$I$2:$I$153="Individual",ROW(Lists!$B$2:$B$153)),ROW(45:45))-1,1),"")} -> Socioeconomic crisis in Lebanon | B49: =VLOOKUP(A49,Lists!$B$2:$G$153,2,FALSE) -> LBN004 | C49: =VLOOKUP(B49,'INFORM Severity - hidden'!$C$5:$D$160,2,FALSE) -> Lebanon | D49: =VLOOKUP(A49,Lists!$B$2:$G$153,3,FALSE) -> LBN | E49: =VLOOKUP(A49,Lists!$B$2:$G$153,5,FALSE) -> Political and economic crisis | F49: =IF(OR(N49="x",K49="x"),"x",ROUND((5-GEOMEAN(((5-K49)/5*4+1),((5-N49)/5*4+1),((5-N49)/5*4+1)))/4*3.5+Q49*0.3,1)) -> 3.6 | G49: =IF(F49="x","x",ROUNDUP(F49,0)) -> 4 | H49: =IF(N49="x","x",IF(K49="x","x",(IF(G49=5,"Very High",IF(G49=4,"High",IF(G49=3,"Medium",IF(G49=2,"Low","Very Low"))))))) -> High | I49: =INDEX(Trends!$D$3:$D$404,MATCH(B49,Trends!$C$3:$C$404,0)) -> Stable | J49: =VLOOKUP($B49,Reliability!$A$3:$I$170,9,FALSE) -> Medium | K49: =IF(OR(M49="x",L49="x"),"x",ROUND((5-GEOMEAN(((5-L49)/5*4+1),((5-M49)/5*4+1),((5-M49)/5*4+1)))/4*5,1)) -> 2.9 | L49: =VLOOKUP($B49,'Impact of the crisis'!$C$6:$N$170,12,FALSE) -> 3.6 | M49: =VLOOKUP($B49,'Impact of the crisis'!$C$6:$AB$170,26,FALSE) -> 2.5 | N49: =VLOOKUP($B49,'Conditions of people affected'!$C$6:$R$170,16,FALSE) -> 4.1 | O49: =VLOOKUP($B49,'Conditions of people affected'!$C$6:$R$170,9,FALSE) -> 4.2 | P49: =VLOOKUP($B49,'Conditions of people affected'!$C$6:$R$170,15,FALSE) -> 4 | Q49: =IF(OR(S49="x",R49="x"),R49,ROUND((5-GEOMEAN(((5-R49)/5*4+1),((5-S49)/5*4+1)))/4*5,1)) -> 3.2 | R49: =VLOOKUP($B49,'Complexity of the crisis'!$C$6:$AN$170,22,FALSE) -> 3.3 | S49: =VLOOKUP($B49,'Complexity of the crisis'!$C$6:$AN$170,38,FALSE) -> 3 | T49: =VLOOKUP(B49,Lists!$C$3:$E$163,3,FALSE) -> Middle east | U49: =VLOOKUP(B49,'INFORM Severity - hidden'!$C$5:$V$170,20,FALSE) -> 44584
A50: {=IFERROR(INDEX(Lists!$B$2:$B$153,SMALL(IF(Lists!$I$2:$I$153="Individual",ROW(Lists!$B$2:$B$153)),ROW(46:46))-1,1),"")} -> Mixed migration flows in Libya | B50: =VLOOKUP(A50,Lists!$B$2:$G$153,2,FALSE) -> LBY002 | C50: =VLOOKUP(B50,'INFORM Severity - hidden'!$C$5:$D$160,2,FALSE) -> Libya | D50: =VLOOKUP(A50,Lists!$B$2:$G$153,3,FALSE) -> LBY | E50: =VLOOKUP(A50,Lists!$B$2:$G$153,5,FALSE) -> International displacement | F50: =IF(OR(N50="x",K50="x"),"x",ROUND((5-GEOMEAN(((5-K50)/5*4+1),((5-N50)/5*4+1),((5-N50)/5*4+1)))/4*3.5+Q50*0.3,1)) -> 3.1 | G50: =IF(F50="x","x",ROUNDUP(F50,0)) -> 4 | H50: =IF(N50="x","x",IF(K50="x","x",(IF(G50=5,"Very High",IF(G50=4,"High",IF(G50=3,"Medium",IF(G50=2,"Low","Very Low"))))))) -> High | I50: =INDEX(Trends!$D$3:$D$404,MATCH(B50,Trends!$C$3:$C$404,0)) -> Stable | J50: =VLOOKUP($B50,Reliability!$A$3:$I$170,9,FALSE) -> High | K50: =IF(OR(M50="x",L50="x"),"x",ROUND((5-GEOMEAN(((5-L50)/5*4+1),((5-M50)/5*4+1),((5-M50)/5*4+1)))/4*5,1)) -> 3.9 | L50: =VLOOKUP($B50,'Impact of the crisis'!$C$6:$N$170,12,FALSE) -> 4.6 | M50: =VLOOKUP($B50,'Impact of the crisis'!$C$6:$AB$170,26,FALSE) -> 3.4 | N50: =VLOOKUP($B50,'Conditions of people affected'!$C$6:$R$170,16,FALSE) -> 2.3 | O50: =VLOOKUP($B50,'Conditions of people affected'!$C$6:$R$170,9,FALSE) -> 2.6 | P50: =VLOOKUP($B50,'Conditions of people affected'!$C$6:$R$170,15,FALSE) -> 2 | Q50: =IF(OR(S50="x",R50="x"),R50,ROUND((5-GEOMEAN(((5-R50)/5*4+1),((5-S50)/5*4+1)))/4*5,1)) -> 3.6 | R50: =VLOOKUP($B50,'Complexity of the crisis'!$C$6:$AN$170,22,FALSE) -> 4.4 | S50: =VLOOKUP($B50,'Complexity of the crisis'!$C$6:$AN$170,38,FALSE) -> 2.5 | T50: =VLOOKUP(B50,Lists!$C$3:$E$163,3,FALSE) -> Africa | U50: =VLOOKUP(B50,'INFORM Severity - hidden'!$C$5:$V$170,20,FALSE) -> 44496
A51: {=IFERROR(INDEX(Lists!$B$2:$B$153,SMALL(IF(Lists!$I$2:$I$153="Individual",ROW(Lists!$B$2:$B$153)),ROW(47:47))-1,1),"")} -> Drought in Lesotho | B51: =VLOOKUP(A51,Lists!$B$2:$G$153,2,FALSE) -> LSO002 | C51: =VLOOKUP(B51,'INFORM Severity - hidden'!$C$5:$D$160,2,FALSE) -> Lesotho | D51: =VLOOKUP(A51,Lists!$B$2:$G$153,3,FALSE) -> LSO | E51: =VLOOKUP(A51,Lists!$B$2:$G$153,5,FALSE) -> Drought | F51: =IF(OR(N51="x",K51="x"),"x",ROUND((5-GEOMEAN(((5-K51)/5*4+1),((5-N51)/5*4+1),((5-N51)/5*4+1)))/4*3.5+Q51*0.3,1)) -> 2.2 | G51: =IF(F51="x","x",ROUNDUP(F51,0)) -> 3 | H51: =IF(N51="x","x",IF(K51="x","x",(IF(G51=5,"Very High",IF(G51=4,"High",IF(G51=3,"Medium",IF(G51=2,"Low","Very Low"))))))) -> Medium | I51: =INDEX(Trends!$D$3:$D$404,MATCH(B51,Trends!$C$3:$C$404,0)) -> Stable | J51: =VLOOKUP($B51,Reliability!$A$3:$I$170,9,FALSE) -> Very High | K51: =IF(OR(M51="x",L51="x"),"x",ROUND((5-GEOMEAN(((5-L51)/5*4+1),((5-M51)/5*4+1),((5-M51)/5*4+1)))/4*5,1)) -> 2.1 | L51: =VLOOKUP($B51,'Impact of the crisis'!$C$6:$N$170,12,FALSE) -> 3 | M51: =VLOOKUP($B51,'Impact of the crisis'!$C$6:$AB$170,26,FALSE) -> 1.5 | N51: =VLOOKUP($B51,'Conditions of people affected'!$C$6:$R$170,16,FALSE) -> 2.75 | O51: =VLOOKUP($B51,'Conditions of people affected'!$C$6:$R$170,9,FALSE) -> 2.5 | P51: =VLOOKUP($B51,'Conditions of people affected'!$C$6:$R$170,15,FALSE) -> 3 | Q51: =IF(OR(S51="x",R51="x"),R51,ROUND((5-GEOMEAN(((5-R51)/5*4+1),((5-S51)/5*4+1)))/4*5,1)) -> 1.3 | R51: =VLOOKUP($B51,'Complexity of the crisis'!$C$6:$AN$170,22,FALSE) -> 1.6 | S51: =VLOOKUP($B51,'Complexity of the crisis'!$C$6:$AN$170,38,FALSE) -> 1 | T51: =VLOOKUP(B51,Lists!$C$3:$E$163,3,FALSE) -> Africa | U51: =VLOOKUP(B51,'INFORM Severity - hidden'!$C$5:$V$170,20,FALSE) -> 44591
A52: {=IFERROR(INDEX(Lists!$B$2:$B$153,SMALL(IF(Lists!$I$2:$I$153="Individual",ROW(Lists!$B$2:$B$153)),ROW(48:48))-1,1),"")} -> Mixed migration flows in Morocco | B52: =VLOOKUP(A52,Lists!$B$2:$G$153,2,FALSE) -> MAR002 | C52: =VLOOKUP(B52,'INFORM Severity - hidden'!$C$5:$D$160,2,FALSE) -> Morocco | D52: =VLOOKUP(A52,Lists!$B$2:$G$153,3,FALSE) -> MAR | E52: =VLOOKUP(A52,Lists!$B$2:$G$153,5,FALSE) -> International displacement | F52: =IF(OR(N52="x",K52="x"),"x",ROUND((5-GEOMEAN(((5-K52)/5*4+1),((5-N52)/5*4+1),((5-N52)/5*4+1)))/4*3.5+Q52*0.3,1)) -> x | G52: =IF(F52="x","x",ROUNDUP(F52,0)) -> x | H52: =IF(N52="x","x",IF(K52="x","x",(IF(G52=5,"Very High",IF(G52=4,"High",IF(G52=3,"Medium",IF(G52=2,"Low","Very Low"))))))) -> x | I52: =INDEX(Trends!$D$3:$D$404,MATCH(B52,Trends!$C$3:$C$404,0)) -> - | J52: =VLOOKUP($B52,Reliability!$A$3:$I$170,9,FALSE) -> Very Low | K52: =IF(OR(M52="x",L52="x"),"x",ROUND((5-GEOMEAN(((5-L52)/5*4+1),((5-M52)/5*4+1),((5-M52)/5*4+1)))/4*5,1)) -> 3.9 | L52: =VLOOKUP($B52,'Impact of the crisis'!$C$6:$N$170,12,FALSE) -> 4.8 | M52: =VLOOKUP($B52,'Impact of the crisis'!$C$6:$AB$170,26,FALSE) -> 3.2 | N52: =VLOOKUP($B52,'Conditions of people affected'!$C$6:$R$170,16,FALSE) -> x | O52: =VLOOKUP($B52,'Conditions of people affected'!$C$6:$R$170,9,FALSE) -> x | P52: =VLOOKUP($B52,'Conditions of people affected'!$C$6:$R$170,15,FALSE) -> x | Q52: =IF(OR(S52="x",R52="x"),R52,ROUND((5-GEOMEAN(((5-R52)/5*4+1),((5-S52)/5*4+1)))/4*5,1)) -> 2.7 | R52: =VLOOKUP($B52,'Complexity of the crisis'!$C$6:$AN$170,22,FALSE) -> 3.6 | S52: =VLOOKUP($B52,'Complexity of the crisis'!$C$6:$AN$170,38,FALSE) -> 1.5 | T52: =VLOOKUP(B52,Lists!$C$3:$E$163,3,FALSE) -> Africa | U52: =VLOOKUP(B52,'INFORM Severity - hidden'!$C$5:$V$170,20,FALSE) -> 44494
A53: {=IFERROR(INDEX(Lists!$B$2:$B$153,SMALL(IF(Lists!$I$2:$I$153="Individual",ROW(Lists!$B$2:$B$153)),ROW(49:49))-1,1),"")} -> Drought in Madagascar | B53: =VLOOKUP(A53,Lists!$B$2:$G$153,2,FALSE) -> MDG002 | C53: =VLOOKUP(B53,'INFORM Severity - hidden'!$C$5:$D$160,2,FALSE) -> Madagascar | D53: =VLOOKUP(A53,Lists!$B$2:$G$153,3,FALSE) -> MDG | E53: =VLOOKUP(A53,Lists!$B$2:$G$153,5,FALSE) -> Drought | F53: =IF(OR(N53="x",K53="x"),"x",ROUND((5-GEOMEAN(((5-K53)/5*4+1),((5-N53)/5*4+1),((5-N53)/5*4+1)))/4*3.5+Q53*0.3,1)) -> 2.9 | G53: =IF(F53="x","x",ROUNDUP(F53,0)) -> 3 | H53: =IF(N53="x","x",IF(K53="x","x",(IF(G53=5,"Very High",IF(G53=4,"High",IF(G53=3,"Medium",IF(G53=2,"Low","Very Low"))))))) -> Medium | I53: =INDEX(Trends!$D$3:$D$404,MATCH(B53,Trends!$C$3:$C$404,0)) -> Increasing | J53: =VLOOKUP($B53,Reliability!$A$3:$I$170,9,FALSE) -> Very High | K53: =IF(OR(M53="x",L53="x"),"x",ROUND((5-GEOMEAN(((5-L53)/5*4+1),((5-M53)/5*4+1),((5-M53)/5*4+1)))/4*5,1)) -> 2.2 | L53: =VLOOKUP($B53,'Impact of the crisis'!$C$6:$N$170,12,FALSE) -> 2.2 | M53: =VLOOKUP($B53,'Impact of the crisis'!$C$6:$AB$170,26,FALSE) -> 2.2 | N53: =VLOOKUP($B53,'Conditions of people affected'!$C$6:$R$170,16,FALSE) -> 3.85 | O53: =VLOOKUP($B53,'Conditions of people affected'!$C$6:$R$170,9,FALSE) -> 3.7 | P53: =VLOOKUP($B53,'Conditions of people affected'!$C$6:$R$170,15,FALSE) -> 4 | Q53: =IF(OR(S53="x",R53="x"),R53,ROUND((5-GEOMEAN(((5-R53)/5*4+1),((5-S53)/5*4+1)))/4*5,1)) -> 1.9 | R53: =VLOOKUP($B53,'Complexity of the crisis'!$C$6:$AN$170,22,FALSE) -> 2.3 | S53: =VLOOKUP($B53,'Complexity of the crisis'!$C$6:$AN$170,38,FALSE) -> 1.5 | T53: =VLOOKUP(B53,Lists!$C$3:$E$163,3,FALSE) -> Africa | U53: =VLOOKUP(B53,'INFORM Severity - hidden'!$C$5:$V$170,20,FALSE) -> 44591
A54: {=IFERROR(INDEX(Lists!$B$2:$B$153,SMALL(IF(Lists!$I$2:$I$153="Individual",ROW(Lists!$B$2:$B$153)),ROW(50:50))-1,1),"")} -> Tropical Cyclone Ana in Madagascar | B54: =VLOOKUP(A54,Lists!$B$2:$G$153,2,FALSE) -> MDG006 | C54: =VLOOKUP(B54,'INFORM Severity - hidden'!$C$5:$D$160,2,FALSE) -> Madagascar | D54: =VLOOKUP(A54,Lists!$B$2:$G$153,3,FALSE) -> MDG | E54: =VLOOKUP(A54,Lists!$B$2:$G$153,5,FALSE) -> Tropical cyclone | F54: =IF(OR(N54="x",K54="x"),"x",ROUND((5-GEOMEAN(((5-K54)/5*4+1),((5-N54)/5*4+1),((5-N54)/5*4+1)))/4*3.5+Q54*0.3,1)) -> 1.7 | G54: =IF(F54="x","x",ROUNDUP(F54,0)) -> 2 | H54: =IF(N54="x","x",IF(K54="x","x",(IF(G54=5,"Very High",IF(G54=4,"High",IF(G54=3,"Medium",IF(G54=2,"Low","Very Low"))))))) -> Low | I54: =INDEX(Trends!$D$3:$D$404,MATCH(B54,Trends!$C$3:$C$404,0)) -> - | J54: =VLOOKUP($B54,Reliability!$A$3:$I$170,9,FALSE) -> Very High | K54: =IF(OR(M54="x",L54="x"),"x",ROUND((5-GEOMEAN(((5-L54)/5*4+1),((5-M54)/5*4+1),((5-M54)/5*4+1)))/4*5,1)) -> 2.6 | L54: =VLOOKUP($B54,'Impact of the crisis'!$C$6:$N$170,12,FALSE) -> 2.8 | M54: =VLOOKUP($B54,'Impact of the crisis'!$C$6:$AB$170,26,FALSE) -> 2.5 | N54: =VLOOKUP($B54,'Conditions of people affected'!$C$6:$R$170,16,FALSE) -> 1.2 | O54: =VLOOKUP($B54,'Conditions of people affected'!$C$6:$R$170,9,FALSE) -> 1.4 | P54: =VLOOKUP($B54,'Conditions of people affected'!$C$6:$R$170,15,FALSE) -> 1 | Q54: =IF(OR(S54="x",R54="x"),R54,ROUND((5-GEOMEAN(((5-R54)/5*4+1),((5-S54)/5*4+1)))/4*5,1)) -> 1.7 | R54: =VLOOKUP($B54,'Complexity of the crisis'!$C$6:$AN$170,22,FALSE) -> 2.3 | S54: =VLOOKUP($B54,'Complexity of the crisis'!$C$6:$AN$170,38,FALSE) -> 1 | T54: =VLOOKUP(B54,Lists!$C$3:$E$163,3,FALSE) -> Africa | U54: =VLOOKUP(B54,'INFORM Severity - hidden'!$C$5:$V$170,20,FALSE) -> 44591
A55: {=IFERROR(INDEX(Lists!$B$2:$B$153,SMALL(IF(Lists!$I$2:$I$153="Individual",ROW(Lists!$B$2:$B$153)),ROW(51:51))-1,1),"")} -> Criminal Violence in Mexico | B55: =VLOOKUP(A55,Lists!$B$2:$G$153,2,FALSE) -> MEX002 | C55: =VLOOKUP(B55,'INFORM Severity - hidden'!$C$5:$D$160,2,FALSE) -> Mexico | D55: =VLOOKUP(A55,Lists!$B$2:$G$153,3,FALSE) -> MEX | E55: =VLOOKUP(A55,Lists!$B$2:$G$153,5,FALSE) -> Other type of violence | F55: =IF(OR(N55="x",K55="x"),"x",ROUND((5-GEOMEAN(((5-K55)/5*4+1),((5-N55)/5*4+1),((5-N55)/5*4+1)))/4*3.5+Q55*0.3,1)) -> x | G55: =IF(F55="x","x",ROUNDUP(F55,0)) -> x | H55: =IF(N55="x","x",IF(K55="x","x",(IF(G55=5,"Very High",IF(G55=4,"High",IF(G55=3,"Medium",IF(G55=2,"Low","Very Low"))))))) -> x | I55: =INDEX(Trends!$D$3:$D$404,MATCH(B55,Trends!$C$3:$C$404,0)) -> - | J55: =VLOOKUP($B55,Reliability!$A$3:$I$170,9,FALSE) -> Medium | K55: =IF(OR(M55="x",L55="x"),"x",ROUND((5-GEOMEAN(((5-L55)/5*4+1),((5-M55)/5*4+1),((5-M55)/5*4+1)))/4*5,1)) -> 4.1 | L55: =VLOOKUP($B55,'Impact of the crisis'!$C$6:$N$170,12,FALSE) -> 5 | M55: =VLOOKUP($B55,'Impact of the crisis'!$C$6:$AB$170,26,FALSE) -> 3.4 | N55: =VLOOKUP($B55,'Conditions of people affected'!$C$6:$R$170,16,FALSE) -> x | O55: =VLOOKUP($B55,'Conditions of people affected'!$C$6:$R$170,9,FALSE) -> x | P55: =VLOOKUP($B55,'Conditions of people affected'!$C$6:$R$170,15,FALSE) -> x | Q55: =IF(OR(S55="x",R55="x"),R55,ROUND((5-GEOMEAN(((5-R55)/5*4+1),((5-S55)/5*4+1)))/4*5,1)) -> 3.6 | R55: =VLOOKUP($B55,'Complexity of the crisis'!$C$6:$AN$170,22,FALSE) -> 3.7 | S55: =VLOOKUP($B55,'Complexity of the crisis'!$C$6:$AN$170,38,FALSE) -> 3.5 | T55: =VLOOKUP(B55,Lists!$C$3:$E$163,3,FALSE) -> Americas | U55: =VLOOKUP(B55,'INFORM Severity - hidden'!$C$5:$V$170,20,FALSE) -> 44488
A56: {=IFERROR(INDEX(Lists!$B$2:$B$153,SMALL(IF(Lists!$I$2:$I$153="Individual",ROW(Lists!$B$2:$B$153)),ROW(52:52))-1,1),"")} -> Mixed Migration in Mexico | B56: =VLOOKUP(A56,Lists!$B$2:$G$153,2,FALSE) -> MEX003 | C56: =VLOOKUP(B56,'INFORM Severity - hidden'!$C$5:$D$160,2,FALSE) -> Mexico | D56: =VLOOKUP(A56,Lists!$B$2:$G$153,3,FALSE) -> MEX | E56: =VLOOKUP(A56,Lists!$B$2:$G$153,5,FALSE) -> International displacement | F56: =IF(OR(N56="x",K56="x"),"x",ROUND((5-GEOMEAN(((5-K56)/5*4+1),((5-N56)/5*4+1),((5-N56)/5*4+1)))/4*3.5+Q56*0.3,1)) -> x | G56: =IF(F56="x","x",ROUNDUP(F56,0)) -> x | H56: =IF(N56="x","x",IF(K56="x","x",(IF(G56=5,"Very High",IF(G56=4,"High",IF(G56=3,"Medium",IF(G56=2,"Low","Very Low"))))))) -> x | I56: =INDEX(Trends!$D$3:$D$404,MATCH(B56,Trends!$C$3:$C$404,0)) -> - | J56: =VLOOKUP($B56,Reliability!$A$3:$I$170,9,FALSE) -> High | K56: =IF(OR(M56="x",L56="x"),"x",ROUND((5-GEOMEAN(((5-L56)/5*4+1),((5-M56)/5*4+1),((5-M56)/5*4+1)))/4*5,1)) -> 3.8 | L56: =VLOOKUP($B56,'Impact of the crisis'!$C$6:$N$170,12,FALSE) -> 5 | M56: =VLOOKUP($B56,'Impact of the crisis'!$C$6:$AB$170,26,FALSE) -> 2.8 | N56: =VLOOKUP($B56,'Conditions of people affected'!$C$6:$R$170,16,FALSE) -> x | O56: =VLOOKUP($B56,'Conditions of people affected'!$C$6:$R$170,9,FALSE) -> x | P56: =VLOOKUP($B56,'Conditions of people affected'!$C$6:$R$170,15,FALSE) -> x | Q56: =IF(OR(S56="x",R56="x"),R56,ROUND((5-GEOMEAN(((5-R56)/5*4+1),((5-S56)/5*4+1)))/4*5,1)) -> 3.4 | R56: =VLOOKUP($B56,'Complexity of the crisis'!$C$6:$AN$170,22,FALSE) -> 3.7 | S56: =VLOOKUP($B56,'Complexity of the crisis'!$C$6:$AN$170,38,FALSE) -> 3 | T56: =VLOOKUP(B56,Lists!$C$3:$E$163,3,FALSE) -> Americas | U56: =VLOOKUP(B56,'INFORM Severity - hidden'!$C$5:$V$170,20,FALSE) -> 44489
A57: {=IFERROR(INDEX(Lists!$B$2:$B$153,SMALL(IF(Lists!$I$2:$I$153="Individual",ROW(Lists!$B$2:$B$153)),ROW(53:53))-1,1),"")} -> Complex crisis in Mali | B57: =VLOOKUP(A57,Lists!$B$2:$G$153,2,FALSE) -> MLI001 | C57: =VLOOKUP(B57,'INFORM Severity - hidden'!$C$5:$D$160,2,FALSE) -> Mali | D57: =VLOOKUP(A57,Lists!$B$2:$G$153,3,FALSE) -> MLI | E57: =VLOOKUP(A57,Lists!$B$2:$G$153,5,FALSE) -> Complex crisis | F57: =IF(OR(N57="x",K57="x"),"x",ROUND((5-GEOMEAN(((5-K57)/5*4+1),((5-N57)/5*4+1),((5-N57)/5*4+1)))/4*3.5+Q57*0.3,1)) -> 4.4 | G57: =IF(F57="x","x",ROUNDUP(F57,0)) -> 5 | H57: =IF(N57="x","x",IF(K57="x","x",(IF(G57=5,"Very High",IF(G57=4,"High",IF(G57=3,"Medium",IF(G57=2,"Low","Very Low"))))))) -> Very High | I57: =INDEX(Trends!$D$3:$D$404,MATCH(B57,Trends!$C$3:$C$404,0)) -> Stable | J57: =VLOOKUP($B57,Reliability!$A$3:$I$170,9,FALSE) -> Medium | K57: =IF(OR(M57="x",L57="x"),"x",ROUND((5-GEOMEAN(((5-L57)/5*4+1),((5-M57)/5*4+1),((5-M57)/5*4+1)))/4*5,1)) -> 4.2 | L57: =VLOOKUP($B57,'Impact of the crisis'!$C$6:$N$170,12,FALSE) -> 4.9 | M57: =VLOOKUP($B57,'Impact of the crisis'!$C$6:$AB$170,26,FALSE) -> 3.7 | N57: =VLOOKUP($B57,'Conditions of people affected'!$C$6:$R$170,16,FALSE) -> 4.3 | O57: =VLOOKUP($B57,'Conditions of people affected'!$C$6:$R$170,9,FALSE) -> 4.6 | P57: =VLOOKUP($B57,'Conditions of people affected'!$C$6:$R$170,15,FALSE) -> 4 | Q57: =IF(OR(S57="x",R57="x"),R57,ROUND((5-GEOMEAN(((5-R57)/5*4+1),((5-S57)/5*4+1)))/4*5,1)) -> 4.6 | R57: =VLOOKUP($B57,'Complexity of the crisis'!$C$6:$AN$170,22,FALSE) -> 4 | S57: =VLOOKUP($B57,'Complexity of the crisis'!$C$6:$AN$170,38,FALSE) -> 5 | T57: =VLOOKUP(B57,Lists!$C$3:$E$163,3,FALSE) -> Africa | U57: =VLOOKUP(B57,'INFORM Severity - hidden'!$C$5:$V$170,20,FALSE) -> 44519
A58: {=IFERROR(INDEX(Lists!$B$2:$B$153,SMALL(IF(Lists!$I$2:$I$153="Individual",ROW(Lists!$B$2:$B$153)),ROW(54:54))-1,1),"")} -> Rakhine Conflict | B58: =VLOOKUP(A58,Lists!$B$2:$G$153,2,FALSE) -> MMR002 | C58: =VLOOKUP(B58,'INFORM Severity - hidden'!$C$5:$D$160,2,FALSE) -> Myanmar | D58: =VLOOKUP(A58,Lists!$B$2:$G$153,3,FALSE) -> MMR | E58: =VLOOKUP(A58,Lists!$B$2:$G$153,5,FALSE) -> Conflict | F58: =IF(OR(N58="x",K58="x"),"x",ROUND((5-GEOMEAN(((5-K58)/5*4+1),((5-N58)/5*4+1),((5-N58)/5*4+1)))/4*3.5+Q58*0.3,1)) -> 3.7 | G58: =IF(F58="x","x",ROUNDUP(F58,0)) -> 4 | H58: =IF(N58="x","x",IF(K58="x","x",(IF(G58=5,"Very High",IF(G58=4,"High",IF(G58=3,"Medium",IF(G58=2,"Low","Very Low"))))))) -> High | I58: =INDEX(Trends!$D$3:$D$404,MATCH(B58,Trends!$C$3:$C$404,0)) -> Decreasing | J58: =VLOOKUP($B58,Reliability!$A$3:$I$170,9,FALSE) -> Very High | K58: =IF(OR(M58="x",L58="x"),"x",ROUND((5-GEOMEAN(((5-L58)/5*4+1),((5-M58)/5*4+1),((5-M58)/5*4+1)))/4*5,1)) -> 2.8 | L58: =VLOOKUP($B58,'Impact of the crisis'!$C$6:$N$170,12,FALSE) -> 1.3 | M58: =VLOOKUP($B58,'Impact of the crisis'!$C$6:$AB$170,26,FALSE) -> 3.4 | N58: =VLOOKUP($B58,'Conditions of people affected'!$C$6:$R$170,16,FALSE) -> 3.8 | O58: =VLOOKUP($B58,'Conditions of people affected'!$C$6:$R$170,9,FALSE) -> 3.6 | P58: =VLOOKUP($B58,'Conditions of people affected'!$C$6:$R$170,15,FALSE) -> 4 | Q58: =IF(OR(S58="x",R58="x"),R58,ROUND((5-GEOMEAN(((5-R58)/5*4+1),((5-S58)/5*4+1)))/4*5,1)) -> 4.2 | R58: =VLOOKUP($B58,'Complexity of the crisis'!$C$6:$AN$170,22,FALSE) -> 4.4 | S58: =VLOOKUP($B58,'Complexity of the crisis'!$C$6:$AN$170,38,FALSE) -> 4 | T58: =VLOOKUP(B58,Lists!$C$3:$E$163,3,FALSE) -> Asia | U58: =VLOOKUP(B58,'INFORM Severity - hidden'!$C$5:$V$170,20,FALSE) -> 44585
A59: {=IFERROR(INDEX(Lists!$B$2:$B$153,SMALL(IF(Lists!$I$2:$I$153="Individual",ROW(Lists!$B$2:$B$153)),ROW(55:55))-1,1),"")} -> Kachin and Shan Conflict | B59: =VLOOKUP(A59,Lists!$B$2:$G$153,2,FALSE) -> MMR003 | C59: =VLOOKUP(B59,'INFORM Severity - hidden'!$C$5:$D$160,2,FALSE) -> Myanmar | D59: =VLOOKUP(A59,Lists!$B$2:$G$153,3,FALSE) -> MMR | E59: =VLOOKUP(A59,Lists!$B$2:$G$153,5,FALSE) -> Conflict | F59: =IF(OR(N59="x",K59="x"),"x",ROUND((5-GEOMEAN(((5-K59)/5*4+1),((5-N59)/5*4+1),((5-N59)/5*4+1)))/4*3.5+Q59*0.3,1)) -> 3.9 | G59: =IF(F59="x","x",ROUNDUP(F59,0)) -> 4 | H59: =IF(N59="x","x",IF(K59="x","x",(IF(G59=5,"Very High",IF(G59=4,"High",IF(G59=3,"Medium",IF(G59=2,"Low","Very Low"))))))) -> High | I59: =INDEX(Trends!$D$3:$D$404,MATCH(B59,Trends!$C$3:$C$404,0)) -> Increasing | J59: =VLOOKUP($B59,Reliability!$A$3:$I$170,9,FALSE) -> Very High | K59: =IF(OR(M59="x",L59="x"),"x",ROUND((5-GEOMEAN(((5-L59)/5*4+1),((5-M59)/5*4+1),((5-M59)/5*4+1)))/4*5,1)) -> 3.6 | L59: =VLOOKUP($B59,'Impact of the crisis'!$C$6:$N$170,12,FALSE) -> 2.4 | M59: =VLOOKUP($B59,'Impact of the crisis'!$C$6:$AB$170,26,FALSE) -> 4 | N59: =VLOOKUP($B59,'Conditions of people affected'!$C$6:$R$170,16,FALSE) -> 4.05 | O59: =VLOOKUP($B59,'Conditions of people affected'!$C$6:$R$170,9,FALSE) -> 4.1 | P59: =VLOOKUP($B59,'Conditions of people affected'!$C$6:$R$170,15,FALSE) -> 4 | Q59: =IF(OR(S59="x",R59="x"),R59,ROUND((5-GEOMEAN(((5-R59)/5*4+1),((5-S59)/5*4+1)))/4*5,1)) -> 4 | R59: =VLOOKUP($B59,'Complexity of the crisis'!$C$6:$AN$170,22,FALSE) -> 4.4 | S59: =VLOOKUP($B59,'Complexity of the crisis'!$C$6:$AN$170,38,FALSE) -> 3.5 | T59: =VLOOKUP(B59,Lists!$C$3:$E$163,3,FALSE) -> Asia | U59: =VLOOKUP(B59,'INFORM Severity - hidden'!$C$5:$V$170,20,FALSE) -> 44585
A60: {=IFERROR(INDEX(Lists!$B$2:$B$153,SMALL(IF(Lists!$I$2:$I$153="Individual",ROW(Lists!$B$2:$B$153)),ROW(56:56))-1,1),"")} -> Post-coup conflict in Myanmar | B60: =VLOOKUP(A60,Lists!$B$2:$G$153,2,FALSE) -> MMR004 | C60: =VLOOKUP(B60,'INFORM Severity - hidden'!$C$5:$D$160,2,FALSE) -> Myanmar | D60: =VLOOKUP(A60,Lists!$B$2:$G$153,3,FALSE) -> MMR | E60: =VLOOKUP(A60,Lists!$B$2:$G$153,5,FALSE) -> Conflict | F60: =IF(OR(N60="x",K60="x"),"x",ROUND((5-GEOMEAN(((5-K60)/5*4+1),((5-N60)/5*4+1),((5-N60)/5*4+1)))/4*3.5+Q60*0.3,1)) -> 4.2 | G60: =IF(F60="x","x",ROUNDUP(F60,0)) -> 5 | H60: =IF(N60="x","x",IF(K60="x","x",(IF(G60=5,"Very High",IF(G60=4,"High",IF(G60=3,"Medium",IF(G60=2,"Low","Very Low"))))))) -> Very High | I60: =INDEX(Trends!$D$3:$D$404,MATCH(B60,Trends!$C$3:$C$404,0)) -> Increasing | J60: =VLOOKUP($B60,Reliability!$A$3:$I$170,9,FALSE) -> Very High | K60: =IF(OR(M60="x",L60="x"),"x",ROUND((5-GEOMEAN(((5-L60)/5*4+1),((5-M60)/5*4+1),((5-M60)/5*4+1)))/4*5,1)) -> 3.7 | L60: =VLOOKUP($B60,'Impact of the crisis'!$C$6:$N$170,12,FALSE) -> 4.1 | M60: =VLOOKUP($B60,'Impact of the crisis'!$C$6:$AB$170,26,FALSE) -> 3.5 | N60: =VLOOKUP($B60,'Conditions of people affected'!$C$6:$R$170,16,FALSE) -> 4.5 | O60: =VLOOKUP($B60,'Conditions of people affected'!$C$6:$R$170,9,FALSE) -> 5 | P60: =VLOOKUP($B60,'Conditions of people affected'!$C$6:$R$170,15,FALSE) -> 4 | Q60: =IF(OR(S60="x",R60="x"),R60,ROUND((5-GEOMEAN(((5-R60)/5*4+1),((5-S60)/5*4+1)))/4*5,1)) -> 4 | R60: =VLOOKUP($B60,'Complexity of the crisis'!$C$6:$AN$170,22,FALSE) -> 4.4 | S60: =VLOOKUP($B60,'Complexity of the crisis'!$C$6:$AN$170,38,FALSE) -> 3.5 | T60: =VLOOKUP(B60,Lists!$C$3:$E$163,3,FALSE) -> Asia | U60: =VLOOKUP(B60,'INFORM Severity - hidden'!$C$5:$V$170,20,FALSE) -> 44585
A61: {=IFERROR(INDEX(Lists!$B$2:$B$153,SMALL(IF(Lists!$I$2:$I$153="Individual",ROW(Lists!$B$2:$B$153)),ROW(57:57))-1,1),"")} -> Cabo Delgado Islamist Insurgency | B61: =VLOOKUP(A61,Lists!$B$2:$G$153,2,FALSE) -> MOZ004 | C61: =VLOOKUP(B61,'INFORM Severity - hidden'!$C$5:$D$160,2,FALSE) -> Mozambique | D61: =VLOOKUP(A61,Lists!$B$2:$G$153,3,FALSE) -> MOZ | E61: =VLOOKUP(A61,Lists!$B$2:$G$153,5,FALSE) -> Other type of violence | F61: =IF(OR(N61="x",K61="x"),"x",ROUND((5-GEOMEAN(((5-K61)/5*4+1),((5-N61)/5*4+1),((5-N61)/5*4+1)))/4*3.5+Q61*0.3,1)) -> 3.6 | G61: =IF(F61="x","x",ROUNDUP(F61,0)) -> 4 | H61: =IF(N61="x","x",IF(K61="x","x",(IF(G61=5,"Very High",IF(G61=4,"High",IF(G61=3,"Medium",IF(G61=2,"Low","Very Low"))))))) -> High | I61: =INDEX(Trends!$D$3:$D$404,MATCH(B61,Trends!$C$3:$C$404,0)) -> Stable | J61: =VLOOKUP($B61,Reliability!$A$3:$I$170,9,FALSE) -> High | K61: =IF(OR(M61="x",L61="x"),"x",ROUND((5-GEOMEAN(((5-L61)/5*4+1),((5-M61)/5*4+1),((5-M61)/5*4+1)))/4*5,1)) -> 3.7 | L61: =VLOOKUP($B61,'Impact of the crisis'!$C$6:$N$170,12,FALSE) -> 2.8 | M61: =VLOOKUP($B61,'Impact of the crisis'!$C$6:$AB$170,26,FALSE) -> 4 | N61: =VLOOKUP($B61,'Conditions of people affected'!$C$6:$R$170,16,FALSE) -> 3.25 | O61: =VLOOKUP($B61,'Conditions of people affected'!$C$6:$R$170,9,FALSE) -> 3.5 | P61: =VLOOKUP($B61,'Conditions of people affected'!$C$6:$R$170,15,FALSE) -> 3 | Q61: =IF(OR(S61="x",R61="x"),R61,ROUND((5-GEOMEAN(((5-R61)/5*4+1),((5-S61)/5*4+1)))/4*5,1)) -> 3.9 | R61: =VLOOKUP($B61,'Complexity of the crisis'!$C$6:$AN$170,22,FALSE) -> 4.5 | S61: =VLOOKUP($B61,'Complexity of the crisis'!$C$6:$AN$170,38,FALSE) -> 3 | T61: =VLOOKUP(B61,Lists!$C$3:$E$163,3,FALSE) -> Africa | U61: =VLOOKUP(B61,'INFORM Severity - hidden'!$C$5:$V$170,20,FALSE) -> 44592
A62: {=IFERROR(INDEX(Lists!$B$2:$B$153,SMALL(IF(Lists!$I$2:$I$153="Individual",ROW(Lists!$B$2:$B$153)),ROW(58:58))-1,1),"")} -> Tropical Cyclone Ana in Mozambique | B62: =VLOOKUP(A62,Lists!$B$2:$G$153,2,FALSE) -> MOZ008 | C62: =VLOOKUP(B62,'INFORM Severity - hidden'!$C$5:$D$160,2,FALSE) -> Mozambique | D62: =VLOOKUP(A62,Lists!$B$2:$G$153,3,FALSE) -> MOZ | E62: =VLOOKUP(A62,Lists!$B$2:$G$153,5,FALSE) -> Tropical cyclone | F62: =IF(OR(N62="x",K62="x"),"x",ROUND((5-GEOMEAN(((5-K62)/5*4+1),((5-N62)/5*4+1),((5-N62)/5*4+1)))/4*3.5+Q62*0.3,1)) -> 2.4 | G62: =IF(F62="x","x",ROUNDUP(F62,0)) -> 3 | H62: =IF(N62="x","x",IF(K62="x","x",(IF(G62=5,"Very High",IF(G62=4,"High",IF(G62=3,"Medium",IF(G62=2,"Low","Very Low"))))))) -> Medium | I62: =INDEX(Trends!$D$3:$D$404,MATCH(B62,Trends!$C$3:$C$404,0)) -> - | J62: =VLOOKUP($B62,Reliability!$A$3:$I$170,9,FALSE) -> High | K62: =IF(OR(M62="x",L62="x"),"x",ROUND((5-GEOMEAN(((5-L62)/5*4+1),((5-M62)/5*4+1),((5-M62)/5*4+1)))/4*5,1)) -> 2.7 | L62: =VLOOKUP($B62,'Impact of the crisis'!$C$6:$N$170,12,FALSE) -> 3.3 | M62: =VLOOKUP($B62,'Impact of the crisis'!$C$6:$AB$170,26,FALSE) -> 2.4 | N62: =VLOOKUP($B62,'Conditions of people affected'!$C$6:$R$170,16,FALSE) -> 1.45 | O62: =VLOOKUP($B62,'Conditions of people affected'!$C$6:$R$170,9,FALSE) -> 1.9 | P62: =VLOOKUP($B62,'Conditions of people affected'!$C$6:$R$170,15,FALSE) -> 1 | Q62: =IF(OR(S62="x",R62="x"),R62,ROUND((5-GEOMEAN(((5-R62)/5*4+1),((5-S62)/5*4+1)))/4*5,1)) -> 3.7 | R62: =VLOOKUP($B62,'Complexity of the crisis'!$C$6:$AN$170,22,FALSE) -> 4.5 | S62: =VLOOKUP($B62,'Complexity of the crisis'!$C$6:$AN$170,38,FALSE) -> 2.5 | T62: =VLOOKUP(B62,Lists!$C$3:$E$163,3,FALSE) -> Africa | U62: =VLOOKUP(B62,'INFORM Severity - hidden'!$C$5:$V$170,20,FALSE) -> 44592
A63: {=IFERROR(INDEX(Lists!$B$2:$B$153,SMALL(IF(Lists!$I$2:$I$153="Individual",ROW(Lists!$B$2:$B$153)),ROW(59:59))-1,1),"")} -> Refugees from Mali in Mauritania | B63: =VLOOKUP(A63,Lists!$B$2:$G$153,2,FALSE) -> MRT002 | C63: =VLOOKUP(B63,'INFORM Severity - hidden'!$C$5:$D$160,2,FALSE) -> Mauritania | D63: =VLOOKUP(A63,Lists!$B$2:$G$153,3,FALSE) -> MRT | E63: =VLOOKUP(A63,Lists!$B$2:$G$153,5,FALSE) -> International displacement | F63: =IF(OR(N63="x",K63="x"),"x",ROUND((5-GEOMEAN(((5-K63)/5*4+1),((5-N63)/5*4+1),((5-N63)/5*4+1)))/4*3.5+Q63*0.3,1)) -> 2.2 | G63: =IF(F63="x","x",ROUNDUP(F63,0)) -> 3 | H63: =IF(N63="x","x",IF(K63="x","x",(IF(G63=5,"Very High",IF(G63=4,"High",IF(G63=3,"Medium",IF(G63=2,"Low","Very Low"))))))) -> Medium | I63: =INDEX(Trends!$D$3:$D$404,MATCH(B63,Trends!$C$3:$C$404,0)) -> Increasing | J63: =VLOOKUP($B63,Reliability!$A$3:$I$170,9,FALSE) -> High | K63: =IF(OR(M63="x",L63="x"),"x",ROUND((5-GEOMEAN(((5-L63)/5*4+1),((5-M63)/5*4+1),((5-M63)/5*4+1)))/4*5,1)) -> 1.8 | L63: =VLOOKUP($B63,'Impact of the crisis'!$C$6:$N$170,12,FALSE) -> 0 | M63: =VLOOKUP($B63,'Impact of the crisis'!$C$6:$AB$170,26,FALSE) -> 2.5 | N63: =VLOOKUP($B63,'Conditions of people affected'!$C$6:$R$170,16,FALSE) -> 2.25 | O63: =VLOOKUP($B63,'Conditions of people affected'!$C$6:$R$170,9,FALSE) -> 1.5 | P63: =VLOOKUP($B63,'Conditions of people affected'!$C$6:$R$170,15,FALSE) -> 3 | Q63: =IF(OR(S63="x",R63="x"),R63,ROUND((5-GEOMEAN(((5-R63)/5*4+1),((5-S63)/5*4+1)))/4*5,1)) -> 2.4 | R63: =VLOOKUP($B63,'Complexity of the crisis'!$C$6:$AN$170,22,FALSE) -> 2.7 | S63: =VLOOKUP($B63,'Complexity of the crisis'!$C$6:$AN$170,38,FALSE) -> 2 | T63: =VLOOKUP(B63,Lists!$C$3:$E$163,3,FALSE) -> Africa | U63: =VLOOKUP(B63,'INFORM Severity - hidden'!$C$5:$V$170,20,FALSE) -> 44494
A64: {=IFERROR(INDEX(Lists!$B$2:$B$153,SMALL(IF(Lists!$I$2:$I$153="Individual",ROW(Lists!$B$2:$B$153)),ROW(60:60))-1,1),"")} -> Food Security in Mauritania | B64: =VLOOKUP(A64,Lists!$B$2:$G$153,2,FALSE) -> MRT003 | C64: =VLOOKUP(B64,'INFORM Severity - hidden'!$C$5:$D$160,2,FALSE) -> Mauritania | D64: =VLOOKUP(A64,Lists!$B$2:$G$153,3,FALSE) -> MRT | E64: =VLOOKUP(A64,Lists!$B$2:$G$153,5,FALSE) -> Drought | F64: =IF(OR(N64="x",K64="x"),"x",ROUND((5-GEOMEAN(((5-K64)/5*4+1),((5-N64)/5*4+1),((5-N64)/5*4+1)))/4*3.5+Q64*0.3,1)) -> 2.9 | G64: =IF(F64="x","x",ROUNDUP(F64,0)) -> 3 | H64: =IF(N64="x","x",IF(K64="x","x",(IF(G64=5,"Very High",IF(G64=4,"High",IF(G64=3,"Medium",IF(G64=2,"Low","Very Low"))))))) -> Medium | I64: =INDEX(Trends!$D$3:$D$404,MATCH(B64,Trends!$C$3:$C$404,0)) -> Stable | J64: =VLOOKUP($B64,Reliability!$A$3:$I$170,9,FALSE) -> Medium | K64: =IF(OR(M64="x",L64="x"),"x",ROUND((5-GEOMEAN(((5-L64)/5*4+1),((5-M64)/5*4+1),((5-M64)/5*4+1)))/4*5,1)) -> 3.4 | L64: =VLOOKUP($B64,'Impact of the crisis'!$C$6:$N$170,12,FALSE) -> 4.4 | M64: =VLOOKUP($B64,'Impact of the crisis'!$C$6:$AB$170,26,FALSE) -> 2.8 | N64: =VLOOKUP($B64,'Conditions of people affected'!$C$6:$R$170,16,FALSE) -> 2.9 | O64: =VLOOKUP($B64,'Conditions of people affected'!$C$6:$R$170,9,FALSE) -> 2.8 | P64: =VLOOKUP($B64,'Conditions of people affected'!$C$6:$R$170,15,FALSE) -> 3 | Q64: =IF(OR(S64="x",R64="x"),R64,ROUND((5-GEOMEAN(((5-R64)/5*4+1),((5-S64)/5*4+1)))/4*5,1)) -> 2.4 | R64: =VLOOKUP($B64,'Complexity of the crisis'!$C$6:$AN$170,22,FALSE) -> 2.7 | S64: =VLOOKUP($B64,'Complexity of the crisis'!$C$6:$AN$170,38,FALSE) -> 2 | T64: =VLOOKUP(B64,Lists!$C$3:$E$163,3,FALSE) -> Africa | U64: =VLOOKUP(B64,'INFORM Severity - hidden'!$C$5:$V$170,20,FALSE) -> 44494
A65: {=IFERROR(INDEX(Lists!$B$2:$B$153,SMALL(IF(Lists!$I$2:$I$153="Individual",ROW(Lists!$B$2:$B$153)),ROW(61:61))-1,1),"")} -> Complex crisis in Malawi | B65: =VLOOKUP(A65,Lists!$B$2:$G$153,2,FALSE) -> MWI002 | C65: =VLOOKUP(B65,'INFORM Severity - hidden'!$C$5:$D$160,2,FALSE) -> Malawi | D65: =VLOOKUP(A65,Lists!$B$2:$G$153,3,FALSE) -> MWI | E65: =VLOOKUP(A65,Lists!$B$2:$G$153,5,FALSE) -> Complex crisis | F65: =IF(OR(N65="x",K65="x"),"x",ROUND((5-GEOMEAN(((5-K65)/5*4+1),((5-N65)/5*4+1),((5-N65)/5*4+1)))/4*3.5+Q65*0.3,1)) -> 3 | G65: =IF(F65="x","x",ROUNDUP(F65,0)) -> 3 | H65: =IF(N65="x","x",IF(K65="x","x",(IF(G65=5,"Very High",IF(G65=4,"High",IF(G65=3,"Medium",IF(G65=2,"Low","Very Low"))))))) -> Medium | I65: =INDEX(Trends!$D$3:$D$404,MATCH(B65,Trends!$C$3:$C$404,0)) -> Increasing | J65: =VLOOKUP($B65,Reliability!$A$3:$I$170,9,FALSE) -> Very High | K65: =IF(OR(M65="x",L65="x"),"x",ROUND((5-GEOMEAN(((5-L65)/5*4+1),((5-M65)/5*4+1),((5-M65)/5*4+1)))/4*5,1)) -> 3.1 | L65: =VLOOKUP($B65,'Impact of the crisis'!$C$6:$N$170,12,FALSE) -> 4.4 | M65: =VLOOKUP($B65,'Impact of the crisis'!$C$6:$AB$170,26,FALSE) -> 2.1 | N65: =VLOOKUP($B65,'Conditions of people affected'!$C$6:$R$170,16,FALSE) -> 3.35 | O65: =VLOOKUP($B65,'Conditions of people affected'!$C$6:$R$170,9,FALSE) -> 3.7 | P65: =VLOOKUP($B65,'Conditions of people affected'!$C$6:$R$170,15,FALSE) -> 3 | Q65: =IF(OR(S65="x",R65="x"),R65,ROUND((5-GEOMEAN(((5-R65)/5*4+1),((5-S65)/5*4+1)))/4*5,1)) -> 2.3 | R65: =VLOOKUP($B65,'Complexity of the crisis'!$C$6:$AN$170,22,FALSE) -> 2 | S65: =VLOOKUP($B65,'Complexity of the crisis'!$C$6:$AN$170,38,FALSE) -> 2.5 | T65: =VLOOKUP(B65,Lists!$C$3:$E$163,3,FALSE) -> Africa | U65: =VLOOKUP(B65,'INFORM Severity - hidden'!$C$5:$V$170,20,FALSE) -> 44592
A66: {=IFERROR(INDEX(Lists!$B$2:$B$153,SMALL(IF(Lists!$I$2:$I$153="Individual",ROW(Lists!$B$2:$B$153)),ROW(62:62))-1,1),"")} -> Tropical Cyclone Ana in Malawi | B66: =VLOOKUP(A66,Lists!$B$2:$G$153,2,FALSE) -> MWI004 | C66: =VLOOKUP(B66,'INFORM Severity - hidden'!$C$5:$D$160,2,FALSE) -> Malawi | D66: =VLOOKUP(A66,Lists!$B$2:$G$153,3,FALSE) -> MWI | E66: =VLOOKUP(A66,Lists!$B$2:$G$153,5,FALSE) -> Tropical cyclone | F66: =IF(OR(N66="x",K66="x"),"x",ROUND((5-GEOMEAN(((5-K66)/5*4+1),((5-N66)/5*4+1),((5-N66)/5*4+1)))/4*3.5+Q66*0.3,1)) -> 2.1 | G66: =IF(F66="x","x",ROUNDUP(F66,0)) -> 3 | H66: =IF(N66="x","x",IF(K66="x","x",(IF(G66=5,"Very High",IF(G66=4,"High",IF(G66=3,"Medium",IF(G66=2,"Low","Very Low"))))))) -> Medium | I66: =INDEX(Trends!$D$3:$D$404,MATCH(B66,Trends!$C$3:$C$404,0)) -> - | J66: =VLOOKUP($B66,Reliability!$A$3:$I$170,9,FALSE) -> Very High | K66: =IF(OR(M66="x",L66="x"),"x",ROUND((5-GEOMEAN(((5-L66)/5*4+1),((5-M66)/5*4+1),((5-M66)/5*4+1)))/4*5,1)) -> 3.2 | L66: =VLOOKUP($B66,'Impact of the crisis'!$C$6:$N$170,12,FALSE) -> 4.2 | M66: =VLOOKUP($B66,'Impact of the crisis'!$C$6:$AB$170,26,FALSE) -> 2.5 | N66: =VLOOKUP($B66,'Conditions of people affected'!$C$6:$R$170,16,FALSE) -> 1.25 | O66: =VLOOKUP($B66,'Conditions of people affected'!$C$6:$R$170,9,FALSE) -> 1.5 | P66: =VLOOKUP($B66,'Conditions of people affected'!$C$6:$R$170,15,FALSE) -> 1 | Q66: =IF(OR(S66="x",R66="x"),R66,ROUND((5-GEOMEAN(((5-R66)/5*4+1),((5-S66)/5*4+1)))/4*5,1)) -> 2.3 | R66: =VLOOKUP($B66,'Complexity of the crisis'!$C$6:$AN$170,22,FALSE) -> 2 | S66: =VLOOKUP($B66,'Complexity of the crisis'!$C$6:$AN$170,38,FALSE) -> 2.5 | T66: =VLOOKUP(B66,Lists!$C$3:$E$163,3,FALSE) -> Africa | U66: =VLOOKUP(B66,'INFORM Severity - hidden'!$C$5:$V$170,20,FALSE) -> 44592
A67: {=IFERROR(INDEX(Lists!$B$2:$B$153,SMALL(IF(Lists!$I$2:$I$153="Individual",ROW(Lists!$B$2:$B$153)),ROW(63:63))-1,1),"")} -> International Refugees in Malaysia | B67: =VLOOKUP(A67,Lists!$B$2:$G$153,2,FALSE) -> MYS001 | C67: =VLOOKUP(B67,'INFORM Severity - hidden'!$C$5:$D$160,2,FALSE) -> Malaysia | D67: =VLOOKUP(A67,Lists!$B$2:$G$153,3,FALSE) -> MYS | E67: =VLOOKUP(A67,Lists!$B$2:$G$153,5,FALSE) -> International displacement | F67: =IF(OR(N67="x",K67="x"),"x",ROUND((5-GEOMEAN(((5-K67)/5*4+1),((5-N67)/5*4+1),((5-N67)/5*4+1)))/4*3.5+Q67*0.3,1)) -> 1.7 | G67: =IF(F67="x","x",ROUNDUP(F67,0)) -> 2 | H67: =IF(N67="x","x",IF(K67="x","x",(IF(G67=5,"Very High",IF(G67=4,"High",IF(G67=3,"Medium",IF(G67=2,"Low","Very Low"))))))) -> Low | I67: =INDEX(Trends!$D$3:$D$404,MATCH(B67,Trends!$C$3:$C$404,0)) -> Decreasing | J67: =VLOOKUP($B67,Reliability!$A$3:$I$170,9,FALSE) -> High | K67: =IF(OR(M67="x",L67="x"),"x",ROUND((5-GEOMEAN(((5-L67)/5*4+1),((5-M67)/5*4+1),((5-M67)/5*4+1)))/4*5,1)) -> 1.5 | L67: =VLOOKUP($B67,'Impact of the crisis'!$C$6:$N$170,12,FALSE) -> 1 | M67: =VLOOKUP($B67,'Impact of the crisis'!$C$6:$AB$170,26,FALSE) -> 1.8 | N67: =VLOOKUP($B67,'Conditions of people affected'!$C$6:$R$170,16,FALSE) -> 1.55 | O67: =VLOOKUP($B67,'Conditions of people affected'!$C$6:$R$170,9,FALSE) -> 2.1 | P67: =VLOOKUP($B67,'Conditions of people affected'!$C$6:$R$170,15,FALSE) -> 1 | Q67: =IF(OR(S67="x",R67="x"),R67,ROUND((5-GEOMEAN(((5-R67)/5*4+1),((5-S67)/5*4+1)))/4*5,1)) -> 2 | R67: =VLOOKUP($B67,'Complexity of the crisis'!$C$6:$AN$170,22,FALSE) -> 2 | S67: =VLOOKUP($B67,'Complexity of the crisis'!$C$6:$AN$170,38,FALSE) -> 2 | T67: =VLOOKUP(B67,Lists!$C$3:$E$163,3,FALSE) -> Asia | U67: =VLOOKUP(B67,'INFORM Severity - hidden'!$C$5:$V$170,20,FALSE) -> 44584
A68: {=IFERROR(INDEX(Lists!$B$2:$B$153,SMALL(IF(Lists!$I$2:$I$153="Individual",ROW(Lists!$B$2:$B$153)),ROW(64:64))-1,1),"")} -> Food Security Crisis in Namibia | B68: =VLOOKUP(A68,Lists!$B$2:$G$153,2,FALSE) -> NAM002 | C68: =VLOOKUP(B68,'INFORM Severity - hidden'!$C$5:$D$160,2,FALSE) -> Namibia | D68: =VLOOKUP(A68,Lists!$B$2:$G$153,3,FALSE) -> NAM | E68: =VLOOKUP(A68,Lists!$B$2:$G$153,5,FALSE) -> Food Security | F68: =IF(OR(N68="x",K68="x"),"x",ROUND((5-GEOMEAN(((5-K68)/5*4+1),((5-N68)/5*4+1),((5-N68)/5*4+1)))/4*3.5+Q68*0.3,1)) -> 2.4 | G68: =IF(F68="x","x",ROUNDUP(F68,0)) -> 3 | H68: =IF(N68="x","x",IF(K68="x","x",(IF(G68=5,"Very High",IF(G68=4,"High",IF(G68=3,"Medium",IF(G68=2,"Low","Very Low"))))))) -> Medium | I68: =INDEX(Trends!$D$3:$D$404,MATCH(B68,Trends!$C$3:$C$404,0)) -> Stable | J68: =VLOOKUP($B68,Reliability!$A$3:$I$170,9,FALSE) -> High | K68: =IF(OR(M68="x",L68="x"),"x",ROUND((5-GEOMEAN(((5-L68)/5*4+1),((5-M68)/5*4+1),((5-M68)/5*4+1)))/4*5,1)) -> 2.8 | L68: =VLOOKUP($B68,'Impact of the crisis'!$C$6:$N$170,12,FALSE) -> 4.3 | M68: =VLOOKUP($B68,'Impact of the crisis'!$C$6:$AB$170,26,FALSE) -> 1.7 | N68: =VLOOKUP($B68,'Conditions of people affected'!$C$6:$R$170,16,FALSE) -> 3.05 | O68: =VLOOKUP($B68,'Conditions of people affected'!$C$6:$R$170,9,FALSE) -> 3.1 | P68: =VLOOKUP($B68,'Conditions of people affected'!$C$6:$R$170,15,FALSE) -> 3 | Q68: =IF(OR(S68="x",R68="x"),R68,ROUND((5-GEOMEAN(((5-R68)/5*4+1),((5-S68)/5*4+1)))/4*5,1)) -> 1 | R68: =VLOOKUP($B68,'Complexity of the crisis'!$C$6:$AN$170,22,FALSE) -> 1.5 | S68: =VLOOKUP($B68,'Complexity of the crisis'!$C$6:$AN$170,38,FALSE) -> 0.5 | T68: =VLOOKUP(B68,Lists!$C$3:$E$163,3,FALSE) -> Africa | U68: =VLOOKUP(B68,'INFORM Severity - hidden'!$C$5:$V$170,20,FALSE) -> 44591
A69: {=IFERROR(INDEX(Lists!$B$2:$B$153,SMALL(IF(Lists!$I$2:$I$153="Individual",ROW(Lists!$B$2:$B$153)),ROW(65:65))-1,1),"")} -> Boko Haram in Niger | B69: =VLOOKUP(A69,Lists!$B$2:$G$153,2,FALSE) -> NER002 | C69: =VLOOKUP(B69,'INFORM Severity - hidden'!$C$5:$D$160,2,FALSE) -> Niger | D69: =VLOOKUP(A69,Lists!$B$2:$G$153,3,FALSE) -> NER | E69: =VLOOKUP(A69,Lists!$B$2:$G$153,5,FALSE) -> Conflict | F69: =IF(OR(N69="x",K69="x"),"x",ROUND((5-GEOMEAN(((5-K69)/5*4+1),((5-N69)/5*4+1),((5-N69)/5*4+1)))/4*3.5+Q69*0.3,1)) -> 3.1 | G69: =IF(F69="x","x",ROUNDUP(F69,0)) -> 4 | H69: =IF(N69="x","x",IF(K69="x","x",(IF(G69=5,"Very High",IF(G69=4,"High",IF(G69=3,"Medium",IF(G69=2,"Low","Very Low"))))))) -> High | I69: =INDEX(Trends!$D$3:$D$404,MATCH(B69,Trends!$C$3:$C$404,0)) -> Stable | J69: =VLOOKUP($B69,Reliability!$A$3:$I$170,9,FALSE) -> Medium | K69: =IF(OR(M69="x",L69="x"),"x",ROUND((5-GEOMEAN(((5-L69)/5*4+1),((5-M69)/5*4+1),((5-M69)/5*4+1)))/4*5,1)) -> 2.6 | L69: =VLOOKUP($B69,'Impact of the crisis'!$C$6:$N$170,12,FALSE) -> 1.2 | M69: =VLOOKUP($B69,'Impact of the crisis'!$C$6:$AB$170,26,FALSE) -> 3.1 | N69: =VLOOKUP($B69,'Conditions of people affected'!$C$6:$R$170,16,FALSE) -> 2.7 | O69: =VLOOKUP($B69,'Conditions of people affected'!$C$6:$R$170,9,FALSE) -> 2.4 | P69: =VLOOKUP($B69,'Conditions of people affected'!$C$6:$R$170,15,FALSE) -> 3 | Q69: =IF(OR(S69="x",R69="x"),R69,ROUND((5-GEOMEAN(((5-R69)/5*4+1),((5-S69)/5*4+1)))/4*5,1)) -> 4 | R69: =VLOOKUP($B69,'Complexity of the crisis'!$C$6:$AN$170,22,FALSE) -> 3.3 | S69: =VLOOKUP($B69,'Complexity of the crisis'!$C$6:$AN$170,38,FALSE) -> 4.5 | T69: =VLOOKUP(B69,Lists!$C$3:$E$163,3,FALSE) -> Africa | U69: =VLOOKUP(B69,'INFORM Severity - hidden'!$C$5:$V$170,20,FALSE) -> 44499
A70: {=IFERROR(INDEX(Lists!$B$2:$B$153,SMALL(IF(Lists!$I$2:$I$153="Individual",ROW(Lists!$B$2:$B$153)),ROW(66:66))-1,1),"")} -> Mali/Burkina Faso conflict | B70: =VLOOKUP(A70,Lists!$B$2:$G$153,2,FALSE) -> NER003 | C70: =VLOOKUP(B70,'INFORM Severity - hidden'!$C$5:$D$160,2,FALSE) -> Niger | D70: =VLOOKUP(A70,Lists!$B$2:$G$153,3,FALSE) -> NER | E70: =VLOOKUP(A70,Lists!$B$2:$G$153,5,FALSE) -> Conflict | F70: =IF(OR(N70="x",K70="x"),"x",ROUND((5-GEOMEAN(((5-K70)/5*4+1),((5-N70)/5*4+1),((5-N70)/5*4+1)))/4*3.5+Q70*0.3,1)) -> 3.3 | G70: =IF(F70="x","x",ROUNDUP(F70,0)) -> 4 | H70: =IF(N70="x","x",IF(K70="x","x",(IF(G70=5,"Very High",IF(G70=4,"High",IF(G70=3,"Medium",IF(G70=2,"Low","Very Low"))))))) -> High | I70: =INDEX(Trends!$D$3:$D$404,MATCH(B70,Trends!$C$3:$C$404,0)) -> Decreasing | J70: =VLOOKUP($B70,Reliability!$A$3:$I$170,9,FALSE) -> Medium | K70: =IF(OR(M70="x",L70="x"),"x",ROUND((5-GEOMEAN(((5-L70)/5*4+1),((5-M70)/5*4+1),((5-M70)/5*4+1)))/4*5,1)) -> 3 | L70: =VLOOKUP($B70,'Impact of the crisis'!$C$6:$N$170,12,FALSE) -> 2.4 | M70: =VLOOKUP($B70,'Impact of the crisis'!$C$6:$AB$170,26,FALSE) -> 3.3 | N70: =VLOOKUP($B70,'Conditions of people affected'!$C$6:$R$170,16,FALSE) -> 3.25 | O70: =VLOOKUP($B70,'Conditions of people affected'!$C$6:$R$170,9,FALSE) -> 3.5 | P70: =VLOOKUP($B70,'Conditions of people affected'!$C$6:$R$170,15,FALSE) -> 3 | Q70: =IF(OR(S70="x",R70="x"),R70,ROUND((5-GEOMEAN(((5-R70)/5*4+1),((5-S70)/5*4+1)))/4*5,1)) -> 3.7 | R70: =VLOOKUP($B70,'Complexity of the crisis'!$C$6:$AN$170,22,FALSE) -> 3.3 | S70: =VLOOKUP($B70,'Complexity of the crisis'!$C$6:$AN$170,38,FALSE) -> 4 | T70: =VLOOKUP(B70,Lists!$C$3:$E$163,3,FALSE) -> Africa | U70: =VLOOKUP(B70,'INFORM Severity - hidden'!$C$5:$V$170,20,FALSE) -> 44498
A71: {=IFERROR(INDEX(Lists!$B$2:$B$153,SMALL(IF(Lists!$I$2:$I$153="Individual",ROW(Lists!$B$2:$B$153)),ROW(67:67))-1,1),"")} -> Nigerian Refugees | B71: =VLOOKUP(A71,Lists!$B$2:$G$153,2,FALSE) -> NER004 | C71: =VLOOKUP(B71,'INFORM Severity - hidden'!$C$5:$D$160,2,FALSE) -> Niger | D71: =VLOOKUP(A71,Lists!$B$2:$G$153,3,FALSE) -> NER | E71: =VLOOKUP(A71,Lists!$B$2:$G$153,5,FALSE) -> International displacement | F71: =IF(OR(N71="x",K71="x"),"x",ROUND((5-GEOMEAN(((5-K71)/5*4+1),((5-N71)/5*4+1),((5-N71)/5*4+1)))/4*3.5+Q71*0.3,1)) -> 2.8 | G71: =IF(F71="x","x",ROUNDUP(F71,0)) -> 3 | H71: =IF(N71="x","x",IF(K71="x","x",(IF(G71=5,"Very High",IF(G71=4,"High",IF(G71=3,"Medium",IF(G71=2,"Low","Very Low"))))))) -> Medium | I71: =INDEX(Trends!$D$3:$D$404,MATCH(B71,Trends!$C$3:$C$404,0)) -> Stable | J71: =VLOOKUP($B71,Reliability!$A$3:$I$170,9,FALSE) -> Medium | K71: =IF(OR(M71="x",L71="x"),"x",ROUND((5-GEOMEAN(((5-L71)/5*4+1),((5-M71)/5*4+1),((5-M71)/5*4+1)))/4*5,1)) -> 2.1 | L71: =VLOOKUP($B71,'Impact of the crisis'!$C$6:$N$170,12,FALSE) -> 0.6 | M71: =VLOOKUP($B71,'Impact of the crisis'!$C$6:$AB$170,26,FALSE) -> 2.7 | N71: =VLOOKUP($B71,'Conditions of people affected'!$C$6:$R$170,16,FALSE) -> 3.05 | O71: =VLOOKUP($B71,'Conditions of people affected'!$C$6:$R$170,9,FALSE) -> 3.1 | P71: =VLOOKUP($B71,'Conditions of people affected'!$C$6:$R$170,15,FALSE) -> 3 | Q71: =IF(OR(S71="x",R71="x"),R71,ROUND((5-GEOMEAN(((5-R71)/5*4+1),((5-S71)/5*4+1)))/4*5,1)) -> 2.9 | R71: =VLOOKUP($B71,'Complexity of the crisis'!$C$6:$AN$170,22,FALSE) -> 3.3 | S71: =VLOOKUP($B71,'Complexity of the crisis'!$C$6:$AN$170,38,FALSE) -> 2.5 | T71: =VLOOKUP(B71,Lists!$C$3:$E$163,3,FALSE) -> Africa | U71: =VLOOKUP(B71,'INFORM Severity - hidden'!$C$5:$V$170,20,FALSE) -> 44499
A72: {=IFERROR(INDEX(Lists!$B$2:$B$153,SMALL(IF(Lists!$I$2:$I$153="Individual",ROW(Lists!$B$2:$B$153)),ROW(68:68))-1,1),"")} -> Complex crisis in Nigeria | B72: =VLOOKUP(A72,Lists!$B$2:$G$153,2,FALSE) -> NGA001 | C72: =VLOOKUP(B72,'INFORM Severity - hidden'!$C$5:$D$160,2,FALSE) -> Nigeria | D72: =VLOOKUP(A72,Lists!$B$2:$G$153,3,FALSE) -> NGA | E72: =VLOOKUP(A72,Lists!$B$2:$G$153,5,FALSE) -> Complex crisis | F72: =IF(OR(N72="x",K72="x"),"x",ROUND((5-GEOMEAN(((5-K72)/5*4+1),((5-N72)/5*4+1),((5-N72)/5*4+1)))/4*3.5+Q72*0.3,1)) -> 4.3 | G72: =IF(F72="x","x",ROUNDUP(F72,0)) -> 5 | H72: =IF(N72="x","x",IF(K72="x","x",(IF(G72=5,"Very High",IF(G72=4,"High",IF(G72=3,"Medium",IF(G72=2,"Low","Very Low"))))))) -> Very High | I72: =INDEX(Trends!$D$3:$D$404,MATCH(B72,Trends!$C$3:$C$404,0)) -> Stable | J72: =VLOOKUP($B72,Reliability!$A$3:$I$170,9,FALSE) -> High | K72: =IF(OR(M72="x",L72="x"),"x",ROUND((5-GEOMEAN(((5-L72)/5*4+1),((5-M72)/5*4+1),((5-M72)/5*4+1)))/4*5,1)) -> 4.2 | L72: =VLOOKUP($B72,'Impact of the crisis'!$C$6:$N$170,12,FALSE) -> 4.3 | M72: =VLOOKUP($B72,'Impact of the crisis'!$C$6:$AB$170,26,FALSE) -> 4.2 | N72: =VLOOKUP($B72,'Conditions of people affected'!$C$6:$R$170,16,FALSE) -> 4 | O72: =VLOOKUP($B72,'Conditions of people affected'!$C$6:$R$170,9,FALSE) -> 5 | P72: =VLOOKUP($B72,'Conditions of people affected'!$C$6:$R$170,15,FALSE) -> 3 | Q72: =IF(OR(S72="x",R72="x"),R72,ROUND((5-GEOMEAN(((5-R72)/5*4+1),((5-S72)/5*4+1)))/4*5,1)) -> 4.7 | R72: =VLOOKUP($B72,'Complexity of the crisis'!$C$6:$AN$170,22,FALSE) -> 4.3 | S72: =VLOOKUP($B72,'Complexity of the crisis'!$C$6:$AN$170,38,FALSE) -> 5 | T72: =VLOOKUP(B72,Lists!$C$3:$E$163,3,FALSE) -> Africa | U72: =VLOOKUP(B72,'INFORM Severity - hidden'!$C$5:$V$170,20,FALSE) -> 44526
A73: {=IFERROR(INDEX(Lists!$B$2:$B$153,SMALL(IF(Lists!$I$2:$I$153="Individual",ROW(Lists!$B$2:$B$153)),ROW(69:69))-1,1),"")} -> Middle belt conflict | B73: =VLOOKUP(A73,Lists!$B$2:$G$153,2,FALSE) -> NGA003 | C73: =VLOOKUP(B73,'INFORM Severity - hidden'!$C$5:$D$160,2,FALSE) -> Nigeria | D73: =VLOOKUP(A73,Lists!$B$2:$G$153,3,FALSE) -> NGA | E73: =VLOOKUP(A73,Lists!$B$2:$G$153,5,FALSE) -> Conflict | F73: =IF(OR(N73="x",K73="x"),"x",ROUND((5-GEOMEAN(((5-K73)/5*4+1),((5-N73)/5*4+1),((5-N73)/5*4+1)))/4*3.5+Q73*0.3,1)) -> 3.3 | G73: =IF(F73="x","x",ROUNDUP(F73,0)) -> 4 | H73: =IF(N73="x","x",IF(K73="x","x",(IF(G73=5,"Very High",IF(G73=4,"High",IF(G73=3,"Medium",IF(G73=2,"Low","Very Low"))))))) -> High | I73: =INDEX(Trends!$D$3:$D$404,MATCH(B73,Trends!$C$3:$C$404,0)) -> Decreasing | J73: =VLOOKUP($B73,Reliability!$A$3:$I$170,9,FALSE) -> High | K73: =IF(OR(M73="x",L73="x"),"x",ROUND((5-GEOMEAN(((5-L73)/5*4+1),((5-M73)/5*4+1),((5-M73)/5*4+1)))/4*5,1)) -> 3 | L73: =VLOOKUP($B73,'Impact of the crisis'!$C$6:$N$170,12,FALSE) -> 2.3 | M73: =VLOOKUP($B73,'Impact of the crisis'!$C$6:$AB$170,26,FALSE) -> 3.3 | N73: =VLOOKUP($B73,'Conditions of people affected'!$C$6:$R$170,16,FALSE) -> 3.15 | O73: =VLOOKUP($B73,'Conditions of people affected'!$C$6:$R$170,9,FALSE) -> 3.3 | P73: =VLOOKUP($B73,'Conditions of people affected'!$C$6:$R$170,15,FALSE) -> 3 | Q73: =IF(OR(S73="x",R73="x"),R73,ROUND((5-GEOMEAN(((5-R73)/5*4+1),((5-S73)/5*4+1)))/4*5,1)) -> 3.9 | R73: =VLOOKUP($B73,'Complexity of the crisis'!$C$6:$AN$170,22,FALSE) -> 4.3 | S73: =VLOOKUP($B73,'Complexity of the crisis'!$C$6:$AN$170,38,FALSE) -> 3.5 | T73: =VLOOKUP(B73,Lists!$C$3:$E$163,3,FALSE) -> Africa | U73: =VLOOKUP(B73,'INFORM Severity - hidden'!$C$5:$V$170,20,FALSE) -> 44526
A74: {=IFERROR(INDEX(Lists!$B$2:$B$153,SMALL(IF(Lists!$I$2:$I$153="Individual",ROW(Lists!$B$2:$B$153)),ROW(70:70))-1,1),"")} -> Boko Haram crisis in Nigeria | B74: =VLOOKUP(A74,Lists!$B$2:$G$153,2,FALSE) -> NGA004 | C74: =VLOOKUP(B74,'INFORM Severity - hidden'!$C$5:$D$160,2,FALSE) -> Nigeria | D74: =VLOOKUP(A74,Lists!$B$2:$G$153,3,FALSE) -> NGA | E74: =VLOOKUP(A74,Lists!$B$2:$G$153,5,FALSE) -> Conflict | F74: =IF(OR(N74="x",K74="x"),"x",ROUND((5-GEOMEAN(((5-K74)/5*4+1),((5-N74)/5*4+1),((5-N74)/5*4+1)))/4*3.5+Q74*0.3,1)) -> 4.3 | G74: =IF(F74="x","x",ROUNDUP(F74,0)) -> 5 | H74: =IF(N74="x","x",IF(K74="x","x",(IF(G74=5,"Very High",IF(G74=4,"High",IF(G74=3,"Medium",IF(G74=2,"Low","Very Low"))))))) -> Very High | I74: =INDEX(Trends!$D$3:$D$404,MATCH(B74,Trends!$C$3:$C$404,0)) -> Stable | J74: =VLOOKUP($B74,Reliability!$A$3:$I$170,9,FALSE) -> Medium | K74: =IF(OR(M74="x",L74="x"),"x",ROUND((5-GEOMEAN(((5-L74)/5*4+1),((5-M74)/5*4+1),((5-M74)/5*4+1)))/4*5,1)) -> 4 | L74: =VLOOKUP($B74,'Impact of the crisis'!$C$6:$N$170,12,FALSE) -> 2.1 | M74: =VLOOKUP($B74,'Impact of the crisis'!$C$6:$AB$170,26,FALSE) -> 4.6 | N74: =VLOOKUP($B74,'Conditions of people affected'!$C$6:$R$170,16,FALSE) -> 4.45 | O74: =VLOOKUP($B74,'Conditions of people affected'!$C$6:$R$170,9,FALSE) -> 4.9 | P74: =VLOOKUP($B74,'Conditions of people affected'!$C$6:$R$170,15,FALSE) -> 4 | Q74: =IF(OR(S74="x",R74="x"),R74,ROUND((5-GEOMEAN(((5-R74)/5*4+1),((5-S74)/5*4+1)))/4*5,1)) -> 4.2 | R74: =VLOOKUP($B74,'Complexity of the crisis'!$C$6:$AN$170,22,FALSE) -> 4.3 | S74: =VLOOKUP($B74,'Complexity of the crisis'!$C$6:$AN$170,38,FALSE) -> 4 | T74: =VLOOKUP(B74,Lists!$C$3:$E$163,3,FALSE) -> Africa | U74: =VLOOKUP(B74,'INFORM Severity - hidden'!$C$5:$V$170,20,FALSE) -> 44526
A75: {=IFERROR(INDEX(Lists!$B$2:$B$153,SMALL(IF(Lists!$I$2:$I$153="Individual",ROW(Lists!$B$2:$B$153)),ROW(71:71))-1,1),"")} -> Northwest Banditry | B75: =VLOOKUP(A75,Lists!$B$2:$G$153,2,FALSE) -> NGA007 | C75: =VLOOKUP(B75,'INFORM Severity - hidden'!$C$5:$D$160,2,FALSE) -> Nigeria | D75: =VLOOKUP(A75,Lists!$B$2:$G$153,3,FALSE) -> NGA | E75: =VLOOKUP(A75,Lists!$B$2:$G$153,5,FALSE) -> Other type of violence | F75: =IF(OR(N75="x",K75="x"),"x",ROUND((5-GEOMEAN(((5-K75)/5*4+1),((5-N75)/5*4+1),((5-N75)/5*4+1)))/4*3.5+Q75*0.3,1)) -> 3.7 | G75: =IF(F75="x","x",ROUNDUP(F75,0)) -> 4 | H75: =IF(N75="x","x",IF(K75="x","x",(IF(G75=5,"Very High",IF(G75=4,"High",IF(G75=3,"Medium",IF(G75=2,"Low","Very Low"))))))) -> High | I75: =INDEX(Trends!$D$3:$D$404,MATCH(B75,Trends!$C$3:$C$404,0)) -> Decreasing | J75: =VLOOKUP($B75,Reliability!$A$3:$I$170,9,FALSE) -> High | K75: =IF(OR(M75="x",L75="x"),"x",ROUND((5-GEOMEAN(((5-L75)/5*4+1),((5-M75)/5*4+1),((5-M75)/5*4+1)))/4*5,1)) -> 3.3 | L75: =VLOOKUP($B75,'Impact of the crisis'!$C$6:$N$170,12,FALSE) -> 2.8 | M75: =VLOOKUP($B75,'Impact of the crisis'!$C$6:$AB$170,26,FALSE) -> 3.5 | N75: =VLOOKUP($B75,'Conditions of people affected'!$C$6:$R$170,16,FALSE) -> 3.65 | O75: =VLOOKUP($B75,'Conditions of people affected'!$C$6:$R$170,9,FALSE) -> 4.3 | P75: =VLOOKUP($B75,'Conditions of people affected'!$C$6:$R$170,15,FALSE) -> 3 | Q75: =IF(OR(S75="x",R75="x"),R75,ROUND((5-GEOMEAN(((5-R75)/5*4+1),((5-S75)/5*4+1)))/4*5,1)) -> 4.2 | R75: =VLOOKUP($B75,'Complexity of the crisis'!$C$6:$AN$170,22,FALSE) -> 4.3 | S75: =VLOOKUP($B75,'Complexity of the crisis'!$C$6:$AN$170,38,FALSE) -> 4 | T75: =VLOOKUP(B75,Lists!$C$3:$E$163,3,FALSE) -> Africa | U75: =VLOOKUP(B75,'INFORM Severity - hidden'!$C$5:$V$170,20,FALSE) -> 44526
A76: {=IFERROR(INDEX(Lists!$B$2:$B$153,SMALL(IF(Lists!$I$2:$I$153="Individual",ROW(Lists!$B$2:$B$153)),ROW(72:72))-1,1),"")} -> Cameroonian Refugees in Nigeria | B76: =VLOOKUP(A76,Lists!$B$2:$G$153,2,FALSE) -> NGA008 | C76: =VLOOKUP(B76,'INFORM Severity - hidden'!$C$5:$D$160,2,FALSE) -> Nigeria | D76: =VLOOKUP(A76,Lists!$B$2:$G$153,3,FALSE) -> NGA | E76: =VLOOKUP(A76,Lists!$B$2:$G$153,5,FALSE) -> International displacement | F76: =IF(OR(N76="x",K76="x"),"x",ROUND((5-GEOMEAN(((5-K76)/5*4+1),((5-N76)/5*4+1),((5-N76)/5*4+1)))/4*3.5+Q76*0.3,1)) -> 2.1 | G76: =IF(F76="x","x",ROUNDUP(F76,0)) -> 3 | H76: =IF(N76="x","x",IF(K76="x","x",(IF(G76=5,"Very High",IF(G76=4,"High",IF(G76=3,"Medium",IF(G76=2,"Low","Very Low"))))))) -> Medium | I76: =INDEX(Trends!$D$3:$D$404,MATCH(B76,Trends!$C$3:$C$404,0)) -> Stable | J76: =VLOOKUP($B76,Reliability!$A$3:$I$170,9,FALSE) -> High | K76: =IF(OR(M76="x",L76="x"),"x",ROUND((5-GEOMEAN(((5-L76)/5*4+1),((5-M76)/5*4+1),((5-M76)/5*4+1)))/4*5,1)) -> 1.6 | L76: =VLOOKUP($B76,'Impact of the crisis'!$C$6:$N$170,12,FALSE) -> 2 | M76: =VLOOKUP($B76,'Impact of the crisis'!$C$6:$AB$170,26,FALSE) -> 1.4 | N76: =VLOOKUP($B76,'Conditions of people affected'!$C$6:$R$170,16,FALSE) -> 1.2 | O76: =VLOOKUP($B76,'Conditions of people affected'!$C$6:$R$170,9,FALSE) -> 1.4 | P76: =VLOOKUP($B76,'Conditions of people affected'!$C$6:$R$170,15,FALSE) -> 1 | Q76: =IF(OR(S76="x",R76="x"),R76,ROUND((5-GEOMEAN(((5-R76)/5*4+1),((5-S76)/5*4+1)))/4*5,1)) -> 3.9 | R76: =VLOOKUP($B76,'Complexity of the crisis'!$C$6:$AN$170,22,FALSE) -> 4.3 | S76: =VLOOKUP($B76,'Complexity of the crisis'!$C$6:$AN$170,38,FALSE) -> 3.5 | T76: =VLOOKUP(B76,Lists!$C$3:$E$163,3,FALSE) -> Africa | U76: =VLOOKUP(B76,'INFORM Severity - hidden'!$C$5:$V$170,20,FALSE) -> 44526
A77: {=IFERROR(INDEX(Lists!$B$2:$B$153,SMALL(IF(Lists!$I$2:$I$153="Individual",ROW(Lists!$B$2:$B$153)),ROW(73:73))-1,1),"")} -> Socioeconomic crisis in Nicaragua | B77: =VLOOKUP(A77,Lists!$B$2:$G$153,2,FALSE) -> NIC001 | C77: =VLOOKUP(B77,'INFORM Severity - hidden'!$C$5:$D$160,2,FALSE) -> Nicaragua | D77: =VLOOKUP(A77,Lists!$B$2:$G$153,3,FALSE) -> NIC | E77: =VLOOKUP(A77,Lists!$B$2:$G$153,5,FALSE) -> Political and economic crisis | F77: =IF(OR(N77="x",K77="x"),"x",ROUND((5-GEOMEAN(((5-K77)/5*4+1),((5-N77)/5*4+1),((5-N77)/5*4+1)))/4*3.5+Q77*0.3,1)) -> x | G77: =IF(F77="x","x",ROUNDUP(F77,0)) -> x | H77: =IF(N77="x","x",IF(K77="x","x",(IF(G77=5,"Very High",IF(G77=4,"High",IF(G77=3,"Medium",IF(G77=2,"Low","Very Low"))))))) -> x | I77: =INDEX(Trends!$D$3:$D$404,MATCH(B77,Trends!$C$3:$C$404,0)) -> - | J77: =VLOOKUP($B77,Reliability!$A$3:$I$170,9,FALSE) -> Low | K77: =IF(OR(M77="x",L77="x"),"x",ROUND((5-GEOMEAN(((5-L77)/5*4+1),((5-M77)/5*4+1),((5-M77)/5*4+1)))/4*5,1)) -> 2.9 | L77: =VLOOKUP($B77,'Impact of the crisis'!$C$6:$N$170,12,FALSE) -> 4.1 | M77: =VLOOKUP($B77,'Impact of the crisis'!$C$6:$AB$170,26,FALSE) -> 2 | N77: =VLOOKUP($B77,'Conditions of people affected'!$C$6:$R$170,16,FALSE) -> x | O77: =VLOOKUP($B77,'Conditions of people affected'!$C$6:$R$170,9,FALSE) -> x | P77: =VLOOKUP($B77,'Conditions of people affected'!$C$6:$R$170,15,FALSE) -> x | Q77: =IF(OR(S77="x",R77="x"),R77,ROUND((5-GEOMEAN(((5-R77)/5*4+1),((5-S77)/5*4+1)))/4*5,1)) -> 2.8 | R77: =VLOOKUP($B77,'Complexity of the crisis'!$C$6:$AN$170,22,FALSE) -> 3.4 | S77: =VLOOKUP($B77,'Complexity of the crisis'!$C$6:$AN$170,38,FALSE) -> 2 | T77: =VLOOKUP(B77,Lists!$C$3:$E$163,3,FALSE) -> Americas | U77: =VLOOKUP(B77,'INFORM Severity - hidden'!$C$5:$V$170,20,FALSE) -> 44497
A78: {=IFERROR(INDEX(Lists!$B$2:$B$153,SMALL(IF(Lists!$I$2:$I$153="Individual",ROW(Lists!$B$2:$B$153)),ROW(74:74))-1,1),"")} -> Complex crisis in Pakistan | B78: =VLOOKUP(A78,Lists!$B$2:$G$153,2,FALSE) -> PAK001 | C78: =VLOOKUP(B78,'INFORM Severity - hidden'!$C$5:$D$160,2,FALSE) -> Pakistan | D78: =VLOOKUP(A78,Lists!$B$2:$G$153,3,FALSE) -> PAK | E78: =VLOOKUP(A78,Lists!$B$2:$G$153,5,FALSE) -> Complex crisis | F78: =IF(OR(N78="x",K78="x"),"x",ROUND((5-GEOMEAN(((5-K78)/5*4+1),((5-N78)/5*4+1),((5-N78)/5*4+1)))/4*3.5+Q78*0.3,1)) -> 3.7 | G78: =IF(F78="x","x",ROUNDUP(F78,0)) -> 4 | H78: =IF(N78="x","x",IF(K78="x","x",(IF(G78=5,"Very High",IF(G78=4,"High",IF(G78=3,"Medium",IF(G78=2,"Low","Very Low"))))))) -> High | I78: =INDEX(Trends!$D$3:$D$404,MATCH(B78,Trends!$C$3:$C$404,0)) -> Decreasing | J78: =VLOOKUP($B78,Reliability!$A$3:$I$170,9,FALSE) -> High | K78: =IF(OR(M78="x",L78="x"),"x",ROUND((5-GEOMEAN(((5-L78)/5*4+1),((5-M78)/5*4+1),((5-M78)/5*4+1)))/4*5,1)) -> 4.2 | L78: =VLOOKUP($B78,'Impact of the crisis'!$C$6:$N$170,12,FALSE) -> 5 | M78: =VLOOKUP($B78,'Impact of the crisis'!$C$6:$AB$170,26,FALSE) -> 3.7 | N78: =VLOOKUP($B78,'Conditions of people affected'!$C$6:$R$170,16,FALSE) -> 3.5 | O78: =VLOOKUP($B78,'Conditions of people affected'!$C$6:$R$170,9,FALSE) -> 5 | P78: =VLOOKUP($B78,'Conditions of people affected'!$C$6:$R$170,15,FALSE) -> 2 | Q78: =IF(OR(S78="x",R78="x"),R78,ROUND((5-GEOMEAN(((5-R78)/5*4+1),((5-S78)/5*4+1)))/4*5,1)) -> 3.6 | R78: =VLOOKUP($B78,'Complexity of the crisis'!$C$6:$AN$170,22,FALSE) -> 3.7 | S78: =VLOOKUP($B78,'Complexity of the crisis'!$C$6:$AN$170,38,FALSE) -> 3.5 | T78: =VLOOKUP(B78,Lists!$C$3:$E$163,3,FALSE) -> Asia | U78: =VLOOKUP(B78,'INFORM Severity - hidden'!$C$5:$V$170,20,FALSE) -> 44571
A79: {=IFERROR(INDEX(Lists!$B$2:$B$153,SMALL(IF(Lists!$I$2:$I$153="Individual",ROW(Lists!$B$2:$B$153)),ROW(75:75))-1,1),"")} -> Kashmir conflict in Pakistan | B79: =VLOOKUP(A79,Lists!$B$2:$G$153,2,FALSE) -> PAK004 | C79: =VLOOKUP(B79,'INFORM Severity - hidden'!$C$5:$D$160,2,FALSE) -> Pakistan | D79: =VLOOKUP(A79,Lists!$B$2:$G$153,3,FALSE) -> PAK | E79: =VLOOKUP(A79,Lists!$B$2:$G$153,5,FALSE) -> Conflict | F79: =IF(OR(N79="x",K79="x"),"x",ROUND((5-GEOMEAN(((5-K79)/5*4+1),((5-N79)/5*4+1),((5-N79)/5*4+1)))/4*3.5+Q79*0.3,1)) -> x | G79: =IF(F79="x","x",ROUNDUP(F79,0)) -> x | H79: =IF(N79="x","x",IF(K79="x","x",(IF(G79=5,"Very High",IF(G79=4,"High",IF(G79=3,"Medium",IF(G79=2,"Low","Very Low"))))))) -> x | I79: =INDEX(Trends!$D$3:$D$404,MATCH(B79,Trends!$C$3:$C$404,0)) -> - | J79: =VLOOKUP($B79,Reliability!$A$3:$I$170,9,FALSE) -> Low | K79: =IF(OR(M79="x",L79="x"),"x",ROUND((5-GEOMEAN(((5-L79)/5*4+1),((5-M79)/5*4+1),((5-M79)/5*4+1)))/4*5,1)) -> 0.4 | L79: =VLOOKUP($B79,'Impact of the crisis'!$C$6:$N$170,12,FALSE) -> 1 | M79: =VLOOKUP($B79,'Impact of the crisis'!$C$6:$AB$170,26,FALSE) -> 0 | N79: =VLOOKUP($B79,'Conditions of people affected'!$C$6:$R$170,16,FALSE) -> x | O79: =VLOOKUP($B79,'Conditions of people affected'!$C$6:$R$170,9,FALSE) -> x | P79: =VLOOKUP($B79,'Conditions of people affected'!$C$6:$R$170,15,FALSE) -> x | Q79: =IF(OR(S79="x",R79="x"),R79,ROUND((5-GEOMEAN(((5-R79)/5*4+1),((5-S79)/5*4+1)))/4*5,1)) -> 3.2 | R79: =VLOOKUP($B79,'Complexity of the crisis'!$C$6:$AN$170,22,FALSE) -> 3.7 | S79: =VLOOKUP($B79,'Complexity of the crisis'!$C$6:$AN$170,38,FALSE) -> 2.5 | T79: =VLOOKUP(B79,Lists!$C$3:$E$163,3,FALSE) -> Asia | U79: =VLOOKUP(B79,'INFORM Severity - hidden'!$C$5:$V$170,20,FALSE) -> 44571
A80: {=IFERROR(INDEX(Lists!$B$2:$B$153,SMALL(IF(Lists!$I$2:$I$153="Individual",ROW(Lists!$B$2:$B$153)),ROW(76:76))-1,1),"")} -> Venezuela displacement in Peru | B80: =VLOOKUP(A80,Lists!$B$2:$G$153,2,FALSE) -> PER002 | C80: =VLOOKUP(B80,'INFORM Severity - hidden'!$C$5:$D$160,2,FALSE) -> Peru | D80: =VLOOKUP(A80,Lists!$B$2:$G$153,3,FALSE) -> PER | E80: =VLOOKUP(A80,Lists!$B$2:$G$153,5,FALSE) -> International displacement | F80: =IF(OR(N80="x",K80="x"),"x",ROUND((5-GEOMEAN(((5-K80)/5*4+1),((5-N80)/5*4+1),((5-N80)/5*4+1)))/4*3.5+Q80*0.3,1)) -> 3 | G80: =IF(F80="x","x",ROUNDUP(F80,0)) -> 3 | H80: =IF(N80="x","x",IF(K80="x","x",(IF(G80=5,"Very High",IF(G80=4,"High",IF(G80=3,"Medium",IF(G80=2,"Low","Very Low"))))))) -> Medium | I80: =INDEX(Trends!$D$3:$D$404,MATCH(B80,Trends!$C$3:$C$404,0)) -> Increasing | J80: =VLOOKUP($B80,Reliability!$A$3:$I$170,9,FALSE) -> Medium | K80: =IF(OR(M80="x",L80="x"),"x",ROUND((5-GEOMEAN(((5-L80)/5*4+1),((5-M80)/5*4+1),((5-M80)/5*4+1)))/4*5,1)) -> 3.3 | L80: =VLOOKUP($B80,'Impact of the crisis'!$C$6:$N$170,12,FALSE) -> 1.3 | M80: =VLOOKUP($B80,'Impact of the crisis'!$C$6:$AB$170,26,FALSE) -> 4 | N80: =VLOOKUP($B80,'Conditions of people affected'!$C$6:$R$170,16,FALSE) -> 3.05 | O80: =VLOOKUP($B80,'Conditions of people affected'!$C$6:$R$170,9,FALSE) -> 3.1 | P80: =VLOOKUP($B80,'Conditions of people affected'!$C$6:$R$170,15,FALSE) -> 3 | Q80: =IF(OR(S80="x",R80="x"),R80,ROUND((5-GEOMEAN(((5-R80)/5*4+1),((5-S80)/5*4+1)))/4*5,1)) -> 2.8 | R80: =VLOOKUP($B80,'Complexity of the crisis'!$C$6:$AN$170,22,FALSE) -> 3.7 | S80: =VLOOKUP($B80,'Complexity of the crisis'!$C$6:$AN$170,38,FALSE) -> 1.5 | T80: =VLOOKUP(B80,Lists!$C$3:$E$163,3,FALSE) -> Americas | U80: =VLOOKUP(B80,'INFORM Severity - hidden'!$C$5:$V$170,20,FALSE) -> 44522
A81: {=IFERROR(INDEX(Lists!$B$2:$B$153,SMALL(IF(Lists!$I$2:$I$153="Individual",ROW(Lists!$B$2:$B$153)),ROW(77:77))-1,1),"")} -> Mindanao conflict | B81: =VLOOKUP(A81,Lists!$B$2:$G$153,2,FALSE) -> PHL003 | C81: =VLOOKUP(B81,'INFORM Severity - hidden'!$C$5:$D$160,2,FALSE) -> Philippines | D81: =VLOOKUP(A81,Lists!$B$2:$G$153,3,FALSE) -> PHL | E81: =VLOOKUP(A81,Lists!$B$2:$G$153,5,FALSE) -> Conflict | F81: =IF(OR(N81="x",K81="x"),"x",ROUND((5-GEOMEAN(((5-K81)/5*4+1),((5-N81)/5*4+1),((5-N81)/5*4+1)))/4*3.5+Q81*0.3,1)) -> 2.2 | G81: =IF(F81="x","x",ROUNDUP(F81,0)) -> 3 | H81: =IF(N81="x","x",IF(K81="x","x",(IF(G81=5,"Very High",IF(G81=4,"High",IF(G81=3,"Medium",IF(G81=2,"Low","Very Low"))))))) -> Medium | I81: =INDEX(Trends!$D$3:$D$404,MATCH(B81,Trends!$C$3:$C$404,0)) -> Decreasing | J81: =VLOOKUP($B81,Reliability!$A$3:$I$170,9,FALSE) -> High | K81: =IF(OR(M81="x",L81="x"),"x",ROUND((5-GEOMEAN(((5-L81)/5*4+1),((5-M81)/5*4+1),((5-M81)/5*4+1)))/4*5,1)) -> 2.7 | L81: =VLOOKUP($B81,'Impact of the crisis'!$C$6:$N$170,12,FALSE) -> 3 | M81: =VLOOKUP($B81,'Impact of the crisis'!$C$6:$AB$170,26,FALSE) -> 2.6 | N81: =VLOOKUP($B81,'Conditions of people affected'!$C$6:$R$170,16,FALSE) -> 1.4 | O81: =VLOOKUP($B81,'Conditions of people affected'!$C$6:$R$170,9,FALSE) -> 1.8 | P81: =VLOOKUP($B81,'Conditions of people affected'!$C$6:$R$170,15,FALSE) -> 1 | Q81: =IF(OR(S81="x",R81="x"),R81,ROUND((5-GEOMEAN(((5-R81)/5*4+1),((5-S81)/5*4+1)))/4*5,1)) -> 3 | R81: =VLOOKUP($B81,'Complexity of the crisis'!$C$6:$AN$170,22,FALSE) -> 3.5 | S81: =VLOOKUP($B81,'Complexity of the crisis'!$C$6:$AN$170,38,FALSE) -> 2.5 | T81: =VLOOKUP(B81,Lists!$C$3:$E$163,3,FALSE) -> Asia | U81: =VLOOKUP(B81,'INFORM Severity - hidden'!$C$5:$V$170,20,FALSE) -> 44584
A82: {=IFERROR(INDEX(Lists!$B$2:$B$153,SMALL(IF(Lists!$I$2:$I$153="Individual",ROW(Lists!$B$2:$B$153)),ROW(78:78))-1,1),"")} -> Typhoon RAI | B82: =VLOOKUP(A82,Lists!$B$2:$G$153,2,FALSE) -> PHL010 | C82: =VLOOKUP(B82,'INFORM Severity - hidden'!$C$5:$D$160,2,FALSE) -> Philippines | D82: =VLOOKUP(A82,Lists!$B$2:$G$153,3,FALSE) -> PHL | E82: =VLOOKUP(A82,Lists!$B$2:$G$153,5,FALSE) -> Tropical cyclone | F82: =IF(OR(N82="x",K82="x"),"x",ROUND((5-GEOMEAN(((5-K82)/5*4+1),((5-N82)/5*4+1),((5-N82)/5*4+1)))/4*3.5+Q82*0.3,1)) -> 3.2 | G82: =IF(F82="x","x",ROUNDUP(F82,0)) -> 4 | H82: =IF(N82="x","x",IF(K82="x","x",(IF(G82=5,"Very High",IF(G82=4,"High",IF(G82=3,"Medium",IF(G82=2,"Low","Very Low"))))))) -> High | I82: =INDEX(Trends!$D$3:$D$404,MATCH(B82,Trends!$C$3:$C$404,0)) -> - | J82: =VLOOKUP($B82,Reliability!$A$3:$I$170,9,FALSE) -> High | K82: =IF(OR(M82="x",L82="x"),"x",ROUND((5-GEOMEAN(((5-L82)/5*4+1),((5-M82)/5*4+1),((5-M82)/5*4+1)))/4*5,1)) -> 2.9 | L82: =VLOOKUP($B82,'Impact of the crisis'!$C$6:$N$170,12,FALSE) -> 3 | M82: =VLOOKUP($B82,'Impact of the crisis'!$C$6:$AB$170,26,FALSE) -> 2.9 | N82: =VLOOKUP($B82,'Conditions of people affected'!$C$6:$R$170,16,FALSE) -> 3.5 | O82: =VLOOKUP($B82,'Conditions of people affected'!$C$6:$R$170,9,FALSE) -> 4 | P82: =VLOOKUP($B82,'Conditions of people affected'!$C$6:$R$170,15,FALSE) -> 3 | Q82: =IF(OR(S82="x",R82="x"),R82,ROUND((5-GEOMEAN(((5-R82)/5*4+1),((5-S82)/5*4+1)))/4*5,1)) -> 3 | R82: =VLOOKUP($B82,'Complexity of the crisis'!$C$6:$AN$170,22,FALSE) -> 3.5 | S82: =VLOOKUP($B82,'Complexity of the crisis'!$C$6:$AN$170,38,FALSE) -> 2.5 | T82: =VLOOKUP(B82,Lists!$C$3:$E$163,3,FALSE) -> Asia | U82: =VLOOKUP(B82,'INFORM Severity - hidden'!$C$5:$V$170,20,FALSE) -> 44584
A83: {=IFERROR(INDEX(Lists!$B$2:$B$153,SMALL(IF(Lists!$I$2:$I$153="Individual",ROW(Lists!$B$2:$B$153)),ROW(79:79))-1,1),"")} -> Complex crisis in DPRK | B83: =VLOOKUP(A83,Lists!$B$2:$G$153,2,FALSE) -> PRK001 | C83: =VLOOKUP(B83,'INFORM Severity - hidden'!$C$5:$D$160,2,FALSE) -> DPRK | D83: =VLOOKUP(A83,Lists!$B$2:$G$153,3,FALSE) -> PRK | E83: =VLOOKUP(A83,Lists!$B$2:$G$153,5,FALSE) -> Complex crisis | F83: =IF(OR(N83="x",K83="x"),"x",ROUND((5-GEOMEAN(((5-K83)/5*4+1),((5-N83)/5*4+1),((5-N83)/5*4+1)))/4*3.5+Q83*0.3,1)) -> 3.8 | G83: =IF(F83="x","x",ROUNDUP(F83,0)) -> 4 | H83: =IF(N83="x","x",IF(K83="x","x",(IF(G83=5,"Very High",IF(G83=4,"High",IF(G83=3,"Medium",IF(G83=2,"Low","Very Low"))))))) -> High | I83: =INDEX(Trends!$D$3:$D$404,MATCH(B83,Trends!$C$3:$C$404,0)) -> Increasing | J83: =VLOOKUP($B83,Reliability!$A$3:$I$170,9,FALSE) -> Medium | K83: =IF(OR(M83="x",L83="x"),"x",ROUND((5-GEOMEAN(((5-L83)/5*4+1),((5-M83)/5*4+1),((5-M83)/5*4+1)))/4*5,1)) -> 3.9 | L83: =VLOOKUP($B83,'Impact of the crisis'!$C$6:$N$170,12,FALSE) -> 4.6 | M83: =VLOOKUP($B83,'Impact of the crisis'!$C$6:$AB$170,26,FALSE) -> 3.5 | N83: =VLOOKUP($B83,'Conditions of people affected'!$C$6:$R$170,16,FALSE) -> 4.5 | O83: =VLOOKUP($B83,'Conditions of people affected'!$C$6:$R$170,9,FALSE) -> 5 | P83: =VLOOKUP($B83,'Conditions of people affected'!$C$6:$R$170,15,FALSE) -> 4 | Q83: =IF(OR(S83="x",R83="x"),R83,ROUND((5-GEOMEAN(((5-R83)/5*4+1),((5-S83)/5*4+1)))/4*5,1)) -> 2.7 | R83: =VLOOKUP($B83,'Complexity of the crisis'!$C$6:$AN$170,22,FALSE) -> 2.9 | S83: =VLOOKUP($B83,'Complexity of the crisis'!$C$6:$AN$170,38,FALSE) -> 2.5 | T83: =VLOOKUP(B83,Lists!$C$3:$E$163,3,FALSE) -> Asia | U83: =VLOOKUP(B83,'INFORM Severity - hidden'!$C$5:$V$170,20,FALSE) -> 44584
A84: {=IFERROR(INDEX(Lists!$B$2:$B$153,SMALL(IF(Lists!$I$2:$I$153="Individual",ROW(Lists!$B$2:$B$153)),ROW(80:80))-1,1),"")} -> Conflict in Palestine | B84: =VLOOKUP(A84,Lists!$B$2:$G$153,2,FALSE) -> PSE002 | C84: =VLOOKUP(B84,'INFORM Severity - hidden'!$C$5:$D$160,2,FALSE) -> Palestine | D84: =VLOOKUP(A84,Lists!$B$2:$G$153,3,FALSE) -> PSE | E84: =VLOOKUP(A84,Lists!$B$2:$G$153,5,FALSE) -> Conflict | F84: =IF(OR(N84="x",K84="x"),"x",ROUND((5-GEOMEAN(((5-K84)/5*4+1),((5-N84)/5*4+1),((5-N84)/5*4+1)))/4*3.5+Q84*0.3,1)) -> 3.9 | G84: =IF(F84="x","x",ROUNDUP(F84,0)) -> 4 | H84: =IF(N84="x","x",IF(K84="x","x",(IF(G84=5,"Very High",IF(G84=4,"High",IF(G84=3,"Medium",IF(G84=2,"Low","Very Low"))))))) -> High | I84: =INDEX(Trends!$D$3:$D$404,MATCH(B84,Trends!$C$3:$C$404,0)) -> Decreasing | J84: =VLOOKUP($B84,Reliability!$A$3:$I$170,9,FALSE) -> Very High | K84: =IF(OR(M84="x",L84="x"),"x",ROUND((5-GEOMEAN(((5-L84)/5*4+1),((5-M84)/5*4+1),((5-M84)/5*4+1)))/4*5,1)) -> 3.7 | L84: =VLOOKUP($B84,'Impact of the crisis'!$C$6:$N$170,12,FALSE) -> 3.4 | M84: =VLOOKUP($B84,'Impact of the crisis'!$C$6:$AB$170,26,FALSE) -> 3.9 | N84: =VLOOKUP($B84,'Conditions of people affected'!$C$6:$R$170,16,FALSE) -> 4 | O84: =VLOOKUP($B84,'Conditions of people affected'!$C$6:$R$170,9,FALSE) -> 4 | P84: =VLOOKUP($B84,'Conditions of people affected'!$C$6:$R$170,15,FALSE) -> 4 | Q84: =IF(OR(S84="x",R84="x"),R84,ROUND((5-GEOMEAN(((5-R84)/5*4+1),((5-S84)/5*4+1)))/4*5,1)) -> 3.8 | R84: =VLOOKUP($B84,'Complexity of the crisis'!$C$6:$AN$170,22,FALSE) -> 2.8 | S84: =VLOOKUP($B84,'Complexity of the crisis'!$C$6:$AN$170,38,FALSE) -> 4.5 | T84: =VLOOKUP(B84,Lists!$C$3:$E$163,3,FALSE) -> Middle east | U84: =VLOOKUP(B84,'INFORM Severity - hidden'!$C$5:$V$170,20,FALSE) -> 44580
A85: {=IFERROR(INDEX(Lists!$B$2:$B$153,SMALL(IF(Lists!$I$2:$I$153="Individual",ROW(Lists!$B$2:$B$153)),ROW(81:81))-1,1),"")} -> Regional Boko Haram Crisis | B85: =VLOOKUP(A85,Lists!$B$2:$G$153,2,FALSE) -> REG001 | C85: =VLOOKUP(B85,'INFORM Severity - hidden'!$C$5:$D$160,2,FALSE) -> Nigeria,Niger,Chad,Cameroon | D85: =VLOOKUP(A85,Lists!$B$2:$G$153,3,FALSE) -> NGA,NER,TCD,CMR | E85: =VLOOKUP(A85,Lists!$B$2:$G$153,5,FALSE) -> Regional crisis | F85: =IF(OR(N85="x",K85="x"),"x",ROUND((5-GEOMEAN(((5-K85)/5*4+1),((5-N85)/5*4+1),((5-N85)/5*4+1)))/4*3.5+Q85*0.3,1)) -> 4.3 | G85: =IF(F85="x","x",ROUNDUP(F85,0)) -> 5 | H85: =IF(N85="x","x",IF(K85="x","x",(IF(G85=5,"Very High",IF(G85=4,"High",IF(G85=3,"Medium",IF(G85=2,"Low","Very Low"))))))) -> Very High | I85: =INDEX(Trends!$D$3:$D$404,MATCH(B85,Trends!$C$3:$C$404,0)) -> Decreasing | J85: =VLOOKUP($B85,Reliability!$A$3:$I$170,9,FALSE) -> Medium | K85: =IF(OR(M85="x",L85="x"),"x",ROUND((5-GEOMEAN(((5-L85)/5*4+1),((5-M85)/5*4+1),((5-M85)/5*4+1)))/4*5,1)) -> 4 | L85: =VLOOKUP($B85,'Impact of the crisis'!$C$6:$N$170,12,FALSE) -> 2.3 | M85: =VLOOKUP($B85,'Impact of the crisis'!$C$6:$AB$170,26,FALSE) -> 4.5 | N85: =VLOOKUP($B85,'Conditions of people affected'!$C$6:$R$170,16,FALSE) -> 4.45 | O85: =VLOOKUP($B85,'Conditions of people affected'!$C$6:$R$170,9,FALSE) -> 4.9 | P85: =VLOOKUP($B85,'Conditions of people affected'!$C$6:$R$170,15,FALSE) -> 4 | Q85: =IF(OR(S85="x",R85="x"),R85,ROUND((5-GEOMEAN(((5-R85)/5*4+1),((5-S85)/5*4+1)))/4*5,1)) -> 4.4 | R85: =VLOOKUP($B85,'Complexity of the crisis'!$C$6:$AN$170,22,FALSE) -> 4.3 | S85: =VLOOKUP($B85,'Complexity of the crisis'!$C$6:$AN$170,38,FALSE) -> 4.5 | T85: =VLOOKUP(B85,Lists!$C$3:$E$163,3,FALSE) -> Africa,Africa,Africa,Africa | U85: =VLOOKUP(B85,'INFORM Severity - hidden'!$C$5:$V$170,20,FALSE) -> 44499
A86: {=IFERROR(INDEX(Lists!$B$2:$B$153,SMALL(IF(Lists!$I$2:$I$153="Individual",ROW(Lists!$B$2:$B$153)),ROW(82:82))-1,1),"")} -> Venezuela Regional Crisis | B86: =VLOOKUP(A86,Lists!$B$2:$G$153,2,FALSE) -> REG002 | C86: =VLOOKUP(B86,'INFORM Severity - hidden'!$C$5:$D$160,2,FALSE) -> Venezuela,Brazil,Colombia,Ecuador,Peru,Trinidad and Tobago | D86: =VLOOKUP(A86,Lists!$B$2:$G$153,3,FALSE) -> VEN,BRA,COL,ECU,PER,TTO | E86: =VLOOKUP(A86,Lists!$B$2:$G$153,5,FALSE) -> Regional crisis | F86: =IF(OR(N86="x",K86="x"),"x",ROUND((5-GEOMEAN(((5-K86)/5*4+1),((5-N86)/5*4+1),((5-N86)/5*4+1)))/4*3.5+Q86*0.3,1)) -> 4.1 | G86: =IF(F86="x","x",ROUNDUP(F86,0)) -> 5 | H86: =IF(N86="x","x",IF(K86="x","x",(IF(G86=5,"Very High",IF(G86=4,"High",IF(G86=3,"Medium",IF(G86=2,"Low","Very Low"))))))) -> Very High | I86: =INDEX(Trends!$D$3:$D$404,MATCH(B86,Trends!$C$3:$C$404,0)) -> Increasing | J86: =VLOOKUP($B86,Reliability!$A$3:$I$170,9,FALSE) -> Low | K86: =IF(OR(M86="x",L86="x"),"x",ROUND((5-GEOMEAN(((5-L86)/5*4+1),((5-M86)/5*4+1),((5-M86)/5*4+1)))/4*5,1)) -> 4.1 | L86: =VLOOKUP($B86,'Impact of the crisis'!$C$6:$N$170,12,FALSE) -> 2.9 | M86: =VLOOKUP($B86,'Impact of the crisis'!$C$6:$AB$170,26,FALSE) -> 4.5 | N86: =VLOOKUP($B86,'Conditions of people affected'!$C$6:$R$170,16,FALSE) -> 4 | O86: =VLOOKUP($B86,'Conditions of people affected'!$C$6:$R$170,9,FALSE) -> 5 | P86: =VLOOKUP($B86,'Conditions of people affected'!$C$6:$R$170,15,FALSE) -> 3 | Q86: =IF(OR(S86="x",R86="x"),R86,ROUND((5-GEOMEAN(((5-R86)/5*4+1),((5-S86)/5*4+1)))/4*5,1)) -> 4.1 | R86: =VLOOKUP($B86,'Complexity of the crisis'!$C$6:$AN$170,22,FALSE) -> 3.6 | S86: =VLOOKUP($B86,'Complexity of the crisis'!$C$6:$AN$170,38,FALSE) -> 4.5 | T86: =VLOOKUP(B86,Lists!$C$3:$E$163,3,FALSE) -> Americas,Americas,Americas,Americas,Americas,Americas | U86: =VLOOKUP(B86,'INFORM Severity - hidden'!$C$5:$V$170,20,FALSE) -> 44496
A87: {=IFERROR(INDEX(Lists!$B$2:$B$153,SMALL(IF(Lists!$I$2:$I$153="Individual",ROW(Lists!$B$2:$B$153)),ROW(83:83))-1,1),"")} -> Regional Kashmir conflict | B87: =VLOOKUP(A87,Lists!$B$2:$G$153,2,FALSE) -> REG003 | C87: =VLOOKUP(B87,'INFORM Severity - hidden'!$C$5:$D$160,2,FALSE) -> India,Pakistan | D87: =VLOOKUP(A87,Lists!$B$2:$G$153,3,FALSE) -> IND,PAK | E87: =VLOOKUP(A87,Lists!$B$2:$G$153,5,FALSE) -> Regional crisis | F87: =IF(OR(N87="x",K87="x"),"x",ROUND((5-GEOMEAN(((5-K87)/5*4+1),((5-N87)/5*4+1),((5-N87)/5*4+1)))/4*3.5+Q87*0.3,1)) -> x | G87: =IF(F87="x","x",ROUNDUP(F87,0)) -> x | H87: =IF(N87="x","x",IF(K87="x","x",(IF(G87=5,"Very High",IF(G87=4,"High",IF(G87=3,"Medium",IF(G87=2,"Low","Very Low"))))))) -> x | I87: =INDEX(Trends!$D$3:$D$404,MATCH(B87,Trends!$C$3:$C$404,0)) -> - | J87: =VLOOKUP($B87,Reliability!$A$3:$I$170,9,FALSE) -> Very Low | K87: =IF(OR(M87="x",L87="x"),"x",ROUND((5-GEOMEAN(((5-L87)/5*4+1),((5-M87)/5*4+1),((5-M87)/5*4+1)))/4*5,1)) -> 3.3 | L87: =VLOOKUP($B87,'Impact of the crisis'!$C$6:$N$170,12,FALSE) -> 2.1 | M87: =VLOOKUP($B87,'Impact of the crisis'!$C$6:$AB$170,26,FALSE) -> 3.7 | N87: =VLOOKUP($B87,'Conditions of people affected'!$C$6:$R$170,16,FALSE) -> x | O87: =VLOOKUP($B87,'Conditions of people affected'!$C$6:$R$170,9,FALSE) -> x | P87: =VLOOKUP($B87,'Conditions of people affected'!$C$6:$R$170,15,FALSE) -> x | Q87: =IF(OR(S87="x",R87="x"),R87,ROUND((5-GEOMEAN(((5-R87)/5*4+1),((5-S87)/5*4+1)))/4*5,1)) -> 3 | R87: =VLOOKUP($B87,'Complexity of the crisis'!$C$6:$AN$170,22,FALSE) -> 3.5 | S87: =VLOOKUP($B87,'Complexity of the crisis'!$C$6:$AN$170,38,FALSE) -> 2.5 | T87: =VLOOKUP(B87,Lists!$C$3:$E$163,3,FALSE) -> Asia,Asia | U87: =VLOOKUP(B87,'INFORM Severity - hidden'!$C$5:$V$170,20,FALSE) -> 44584
A88: {=IFERROR(INDEX(Lists!$B$2:$B$153,SMALL(IF(Lists!$I$2:$I$153="Individual",ROW(Lists!$B$2:$B$153)),ROW(84:84))-1,1),"")} -> Syrian Regional Crisis | B88: =VLOOKUP(A88,Lists!$B$2:$G$153,2,FALSE) -> REG004 | C88: =VLOOKUP(B88,'INFORM Severity - hidden'!$C$5:$D$160,2,FALSE) -> Syria,Turkey,Iraq,Egypt,Jordan,Lebanon | D88: =VLOOKUP(A88,Lists!$B$2:$G$153,3,FALSE) -> SYR,TUR,IRQ,EGY,JOR,LBN | E88: =VLOOKUP(A88,Lists!$B$2:$G$153,5,FALSE) -> Regional crisis | F88: =IF(OR(N88="x",K88="x"),"x",ROUND((5-GEOMEAN(((5-K88)/5*4+1),((5-N88)/5*4+1),((5-N88)/5*4+1)))/4*3.5+Q88*0.3,1)) -> 4.4 | G88: =IF(F88="x","x",ROUNDUP(F88,0)) -> 5 | H88: =IF(N88="x","x",IF(K88="x","x",(IF(G88=5,"Very High",IF(G88=4,"High",IF(G88=3,"Medium",IF(G88=2,"Low","Very Low"))))))) -> Very High | I88: =INDEX(Trends!$D$3:$D$404,MATCH(B88,Trends!$C$3:$C$404,0)) -> Decreasing | J88: =VLOOKUP($B88,Reliability!$A$3:$I$170,9,FALSE) -> High | K88: =IF(OR(M88="x",L88="x"),"x",ROUND((5-GEOMEAN(((5-L88)/5*4+1),((5-M88)/5*4+1),((5-M88)/5*4+1)))/4*5,1)) -> 3.9 | L88: =VLOOKUP($B88,'Impact of the crisis'!$C$6:$N$170,12,FALSE) -> 3.1 | M88: =VLOOKUP($B88,'Impact of the crisis'!$C$6:$AB$170,26,FALSE) -> 4.2 | N88: =VLOOKUP($B88,'Conditions of people affected'!$C$6:$R$170,16,FALSE) -> 4.5 | O88: =VLOOKUP($B88,'Conditions of people affected'!$C$6:$R$170,9,FALSE) -> 5 | P88: =VLOOKUP($B88,'Conditions of people affected'!$C$6:$R$170,15,FALSE) -> 4 | Q88: =IF(OR(S88="x",R88="x"),R88,ROUND((5-GEOMEAN(((5-R88)/5*4+1),((5-S88)/5*4+1)))/4*5,1)) -> 4.7 | R88: =VLOOKUP($B88,'Complexity of the crisis'!$C$6:$AN$170,22,FALSE) -> 4.3 | S88: =VLOOKUP($B88,'Complexity of the crisis'!$C$6:$AN$170,38,FALSE) -> 5 | T88: =VLOOKUP(B88,Lists!$C$3:$E$163,3,FALSE) -> Middle east,Middle east,Middle east,Africa,Middle east,Middle east | U88: =VLOOKUP(B88,'INFORM Severity - hidden'!$C$5:$V$170,20,FALSE) -> 44560
A89: {=IFERROR(INDEX(Lists!$B$2:$B$153,SMALL(IF(Lists!$I$2:$I$153="Individual",ROW(Lists!$B$2:$B$153)),ROW(85:85))-1,1),"")} -> Eastern Mediterranean Route | B89: =VLOOKUP(A89,Lists!$B$2:$G$153,2,FALSE) -> REG006 | C89: =VLOOKUP(B89,'INFORM Severity - hidden'!$C$5:$D$160,2,FALSE) -> Turkey,Greece | D89: =VLOOKUP(A89,Lists!$B$2:$G$153,3,FALSE) -> TUR,GRC | E89: =VLOOKUP(A89,Lists!$B$2:$G$153,5,FALSE) -> Regional crisis | F89: =IF(OR(N89="x",K89="x"),"x",ROUND((5-GEOMEAN(((5-K89)/5*4+1),((5-N89)/5*4+1),((5-N89)/5*4+1)))/4*3.5+Q89*0.3,1)) -> 3.3 | G89: =IF(F89="x","x",ROUNDUP(F89,0)) -> 4 | H89: =IF(N89="x","x",IF(K89="x","x",(IF(G89=5,"Very High",IF(G89=4,"High",IF(G89=3,"Medium",IF(G89=2,"Low","Very Low"))))))) -> High | I89: =INDEX(Trends!$D$3:$D$404,MATCH(B89,Trends!$C$3:$C$404,0)) -> Stable | J89: =VLOOKUP($B89,Reliability!$A$3:$I$170,9,FALSE) -> High | K89: =IF(OR(M89="x",L89="x"),"x",ROUND((5-GEOMEAN(((5-L89)/5*4+1),((5-M89)/5*4+1),((5-M89)/5*4+1)))/4*5,1)) -> 3.2 | L89: =VLOOKUP($B89,'Impact of the crisis'!$C$6:$N$170,12,FALSE) -> 3 | M89: =VLOOKUP($B89,'Impact of the crisis'!$C$6:$AB$170,26,FALSE) -> 3.3 | N89: =VLOOKUP($B89,'Conditions of people affected'!$C$6:$R$170,16,FALSE) -> 3.5 | O89: =VLOOKUP($B89,'Conditions of people affected'!$C$6:$R$170,9,FALSE) -> 4 | P89: =VLOOKUP($B89,'Conditions of people affected'!$C$6:$R$170,15,FALSE) -> 3 | Q89: =IF(OR(S89="x",R89="x"),R89,ROUND((5-GEOMEAN(((5-R89)/5*4+1),((5-S89)/5*4+1)))/4*5,1)) -> 3.2 | R89: =VLOOKUP($B89,'Complexity of the crisis'!$C$6:$AN$170,22,FALSE) -> 3.4 | S89: =VLOOKUP($B89,'Complexity of the crisis'!$C$6:$AN$170,38,FALSE) -> 3 | T89: =VLOOKUP(B89,Lists!$C$3:$E$163,3,FALSE) -> Middle east,Europe | U89: =VLOOKUP(B89,'INFORM Severity - hidden'!$C$5:$V$170,20,FALSE) -> 44560
A90: {=IFERROR(INDEX(Lists!$B$2:$B$153,SMALL(IF(Lists!$I$2:$I$153="Individual",ROW(Lists!$B$2:$B$153)),ROW(86:86))-1,1),"")} -> Central Mediterranean Route | B90: =VLOOKUP(A90,Lists!$B$2:$G$153,2,FALSE) -> REG007 | C90: =VLOOKUP(B90,'INFORM Severity - hidden'!$C$5:$D$160,2,FALSE) -> Algeria,Tunisia,Libya,Italy | D90: =VLOOKUP(A90,Lists!$B$2:$G$153,3,FALSE) -> DZA,TUN,LBY,ITA | E90: =VLOOKUP(A90,Lists!$B$2:$G$153,5,FALSE) -> Regional crisis | F90: =IF(OR(N90="x",K90="x"),"x",ROUND((5-GEOMEAN(((5-K90)/5*4+1),((5-N90)/5*4+1),((5-N90)/5*4+1)))/4*3.5+Q90*0.3,1)) -> x | G90: =IF(F90="x","x",ROUNDUP(F90,0)) -> x | H90: =IF(N90="x","x",IF(K90="x","x",(IF(G90=5,"Very High",IF(G90=4,"High",IF(G90=3,"Medium",IF(G90=2,"Low","Very Low"))))))) -> x | I90: =INDEX(Trends!$D$3:$D$404,MATCH(B90,Trends!$C$3:$C$404,0)) -> - | J90: =VLOOKUP($B90,Reliability!$A$3:$I$170,9,FALSE) -> Very Low | K90: =IF(OR(M90="x",L90="x"),"x",ROUND((5-GEOMEAN(((5-L90)/5*4+1),((5-M90)/5*4+1),((5-M90)/5*4+1)))/4*5,1)) -> x | L90: =VLOOKUP($B90,'Impact of the crisis'!$C$6:$N$170,12,FALSE) -> x | M90: =VLOOKUP($B90,'Impact of the crisis'!$C$6:$AB$170,26,FALSE) -> 4 | N90: =VLOOKUP($B90,'Conditions of people affected'!$C$6:$R$170,16,FALSE) -> x | O90: =VLOOKUP($B90,'Conditions of people affected'!$C$6:$R$170,9,FALSE) -> x | P90: =VLOOKUP($B90,'Conditions of people affected'!$C$6:$R$170,15,FALSE) -> x | Q90: =IF(OR(S90="x",R90="x"),R90,ROUND((5-GEOMEAN(((5-R90)/5*4+1),((5-S90)/5*4+1)))/4*5,1)) -> 2.8 | R90: =VLOOKUP($B90,'Complexity of the crisis'!$C$6:$AN$170,22,FALSE) -> 3.1 | S90: =VLOOKUP($B90,'Complexity of the crisis'!$C$6:$AN$170,38,FALSE) -> 2.5 | T90: =VLOOKUP(B90,Lists!$C$3:$E$163,3,FALSE) -> Africa,Africa,Africa,Europe | U90: =VLOOKUP(B90,'INFORM Severity - hidden'!$C$5:$V$170,20,FALSE) -> 44500
A91: {=IFERROR(INDEX(Lists!$B$2:$B$153,SMALL(IF(Lists!$I$2:$I$153="Individual",ROW(Lists!$B$2:$B$153)),ROW(87:87))-1,1),"")} -> Western Mediterranean Route | B91: =VLOOKUP(A91,Lists!$B$2:$G$153,2,FALSE) -> REG008 | C91: =VLOOKUP(B91,'INFORM Severity - hidden'!$C$5:$D$160,2,FALSE) -> Algeria,Morocco,Spain | D91: =VLOOKUP(A91,Lists!$B$2:$G$153,3,FALSE) -> DZA,MAR,ESP | E91: =VLOOKUP(A91,Lists!$B$2:$G$153,5,FALSE) -> Regional crisis | F91: =IF(OR(N91="x",K91="x"),"x",ROUND((5-GEOMEAN(((5-K91)/5*4+1),((5-N91)/5*4+1),((5-N91)/5*4+1)))/4*3.5+Q91*0.3,1)) -> x | G91: =IF(F91="x","x",ROUNDUP(F91,0)) -> x | H91: =IF(N91="x","x",IF(K91="x","x",(IF(G91=5,"Very High",IF(G91=4,"High",IF(G91=3,"Medium",IF(G91=2,"Low","Very Low"))))))) -> x | I91: =INDEX(Trends!$D$3:$D$404,MATCH(B91,Trends!$C$3:$C$404,0)) -> - | J91: =VLOOKUP($B91,Reliability!$A$3:$I$170,9,FALSE) -> Very Low | K91: =IF(OR(M91="x",L91="x"),"x",ROUND((5-GEOMEAN(((5-L91)/5*4+1),((5-M91)/5*4+1),((5-M91)/5*4+1)))/4*5,1)) -> x | L91: =VLOOKUP($B91,'Impact of the crisis'!$C$6:$N$170,12,FALSE) -> x | M91: =VLOOKUP($B91,'Impact of the crisis'!$C$6:$AB$170,26,FALSE) -> 3.2 | N91: =VLOOKUP($B91,'Conditions of people affected'!$C$6:$R$170,16,FALSE) -> x | O91: =VLOOKUP($B91,'Conditions of people affected'!$C$6:$R$170,9,FALSE) -> x | P91: =VLOOKUP($B91,'Conditions of people affected'!$C$6:$R$170,15,FALSE) -> x | Q91: =IF(OR(S91="x",R91="x"),R91,ROUND((5-GEOMEAN(((5-R91)/5*4+1),((5-S91)/5*4+1)))/4*5,1)) -> 2.8 | R91: =VLOOKUP($B91,'Complexity of the crisis'!$C$6:$AN$170,22,FALSE) -> 3.1 | S91: =VLOOKUP($B91,'Complexity of the crisis'!$C$6:$AN$170,38,FALSE) -> 2.5 | T91: =VLOOKUP(B91,Lists!$C$3:$E$163,3,FALSE) -> Africa,Africa,Europe | U91: =VLOOKUP(B91,'INFORM Severity - hidden'!$C$5:$V$170,20,FALSE) -> 44500
A92: {=IFERROR(INDEX(Lists!$B$2:$B$153,SMALL(IF(Lists!$I$2:$I$153="Individual",ROW(Lists!$B$2:$B$153)),ROW(88:88))-1,1),"")} -> Rohingya Regional Crisis | B92: =VLOOKUP(A92,Lists!$B$2:$G$153,2,FALSE) -> REG011 | C92: =VLOOKUP(B92,'INFORM Severity - hidden'!$C$5:$D$160,2,FALSE) -> Bangladesh,Myanmar | D92: =VLOOKUP(A92,Lists!$B$2:$G$153,3,FALSE) -> BGD,MMR | E92: =VLOOKUP(A92,Lists!$B$2:$G$153,5,FALSE) -> Regional crisis | F92: =IF(OR(N92="x",K92="x"),"x",ROUND((5-GEOMEAN(((5-K92)/5*4+1),((5-N92)/5*4+1),((5-N92)/5*4+1)))/4*3.5+Q92*0.3,1)) -> 3.9 | G92: =IF(F92="x","x",ROUNDUP(F92,0)) -> 4 | H92: =IF(N92="x","x",IF(K92="x","x",(IF(G92=5,"Very High",IF(G92=4,"High",IF(G92=3,"Medium",IF(G92=2,"Low","Very Low"))))))) -> High | I92: =INDEX(Trends!$D$3:$D$404,MATCH(B92,Trends!$C$3:$C$404,0)) -> Decreasing | J92: =VLOOKUP($B92,Reliability!$A$3:$I$170,9,FALSE) -> Very High | K92: =IF(OR(M92="x",L92="x"),"x",ROUND((5-GEOMEAN(((5-L92)/5*4+1),((5-M92)/5*4+1),((5-M92)/5*4+1)))/4*5,1)) -> 3 | L92: =VLOOKUP($B92,'Impact of the crisis'!$C$6:$N$170,12,FALSE) -> 1.4 | M92: =VLOOKUP($B92,'Impact of the crisis'!$C$6:$AB$170,26,FALSE) -> 3.6 | N92: =VLOOKUP($B92,'Conditions of people affected'!$C$6:$R$170,16,FALSE) -> 4.05 | O92: =VLOOKUP($B92,'Conditions of people affected'!$C$6:$R$170,9,FALSE) -> 4.1 | P92: =VLOOKUP($B92,'Conditions of people affected'!$C$6:$R$170,15,FALSE) -> 4 | Q92: =IF(OR(S92="x",R92="x"),R92,ROUND((5-GEOMEAN(((5-R92)/5*4+1),((5-S92)/5*4+1)))/4*5,1)) -> 4.3 | R92: =VLOOKUP($B92,'Complexity of the crisis'!$C$6:$AN$170,22,FALSE) -> 4 | S92: =VLOOKUP($B92,'Complexity of the crisis'!$C$6:$AN$170,38,FALSE) -> 4.5 | T92: =VLOOKUP(B92,Lists!$C$3:$E$163,3,FALSE) -> Asia,Asia | U92: =VLOOKUP(B92,'INFORM Severity - hidden'!$C$5:$V$170,20,FALSE) -> 44585
A93: {=IFERROR(INDEX(Lists!$B$2:$B$153,SMALL(IF(Lists!$I$2:$I$153="Individual",ROW(Lists!$B$2:$B$153)),ROW(89:89))-1,1),"")} -> Southern Africa Regional Food Security Crisis | B93: =VLOOKUP(A93,Lists!$B$2:$G$153,2,FALSE) -> REG012 | C93: =VLOOKUP(B93,'INFORM Severity - hidden'!$C$5:$D$160,2,FALSE) -> Lesotho,Madagascar,Malawi,Namibia,Eswatini,Zambia,Zimbabwe | D93: =VLOOKUP(A93,Lists!$B$2:$G$153,3,FALSE) -> LSO,MDG,MWI,NAM,SWZ,ZMB,ZWE | E93: =VLOOKUP(A93,Lists!$B$2:$G$153,5,FALSE) -> Regional crisis | F93: =IF(OR(N93="x",K93="x"),"x",ROUND((5-GEOMEAN(((5-K93)/5*4+1),((5-N93)/5*4+1),((5-N93)/5*4+1)))/4*3.5+Q93*0.3,1)) -> 3.6 | G93: =IF(F93="x","x",ROUNDUP(F93,0)) -> 4 | H93: =IF(N93="x","x",IF(K93="x","x",(IF(G93=5,"Very High",IF(G93=4,"High",IF(G93=3,"Medium",IF(G93=2,"Low","Very Low"))))))) -> High | I93: =INDEX(Trends!$D$3:$D$404,MATCH(B93,Trends!$C$3:$C$404,0)) -> Stable | J93: =VLOOKUP($B93,Reliability!$A$3:$I$170,9,FALSE) -> Very High | K93: =IF(OR(M93="x",L93="x"),"x",ROUND((5-GEOMEAN(((5-L93)/5*4+1),((5-M93)/5*4+1),((5-M93)/5*4+1)))/4*5,1)) -> 3.7 | L93: =VLOOKUP($B93,'Impact of the crisis'!$C$6:$N$170,12,FALSE) -> 4.6 | M93: =VLOOKUP($B93,'Impact of the crisis'!$C$6:$AB$170,26,FALSE) -> 3 | N93: =VLOOKUP($B93,'Conditions of people affected'!$C$6:$R$170,16,FALSE) -> 4 | O93: =VLOOKUP($B93,'Conditions of people affected'!$C$6:$R$170,9,FALSE) -> 5 | P93: =VLOOKUP($B93,'Conditions of people affected'!$C$6:$R$170,15,FALSE) -> 3 | Q93: =IF(OR(S93="x",R93="x"),R93,ROUND((5-GEOMEAN(((5-R93)/5*4+1),((5-S93)/5*4+1)))/4*5,1)) -> 2.9 | R93: =VLOOKUP($B93,'Complexity of the crisis'!$C$6:$AN$170,22,FALSE) -> 2.7 | S93: =VLOOKUP($B93,'Complexity of the crisis'!$C$6:$AN$170,38,FALSE) -> 3 | T93: =VLOOKUP(B93,Lists!$C$3:$E$163,3,FALSE) -> Africa,Africa,Africa,Africa,Africa,Africa,Africa | U93: =VLOOKUP(B93,'INFORM Severity - hidden'!$C$5:$V$170,20,FALSE) -> 44591
A94: {=IFERROR(INDEX(Lists!$B$2:$B$153,SMALL(IF(Lists!$I$2:$I$153="Individual",ROW(Lists!$B$2:$B$153)),ROW(90:90))-1,1),"")} -> Nagorno-Karabakh Conflict | B94: =VLOOKUP(A94,Lists!$B$2:$G$153,2,FALSE) -> REG013 | C94: =VLOOKUP(B94,'INFORM Severity - hidden'!$C$5:$D$160,2,FALSE) -> Armenia,Azerbaijan | D94: =VLOOKUP(A94,Lists!$B$2:$G$153,3,FALSE) -> ARM,AZE | E94: =VLOOKUP(A94,Lists!$B$2:$G$153,5,FALSE) -> Regional crisis | F94: =IF(OR(N94="x",K94="x"),"x",ROUND((5-GEOMEAN(((5-K94)/5*4+1),((5-N94)/5*4+1),((5-N94)/5*4+1)))/4*3.5+Q94*0.3,1)) -> x | G94: =IF(F94="x","x",ROUNDUP(F94,0)) -> x | H94: =IF(N94="x","x",IF(K94="x","x",(IF(G94=5,"Very High",IF(G94=4,"High",IF(G94=3,"Medium",IF(G94=2,"Low","Very Low"))))))) -> x | I94: =INDEX(Trends!$D$3:$D$404,MATCH(B94,Trends!$C$3:$C$404,0)) -> - | J94: =VLOOKUP($B94,Reliability!$A$3:$I$170,9,FALSE) -> Very Low | K94: =IF(OR(M94="x",L94="x"),"x",ROUND((5-GEOMEAN(((5-L94)/5*4+1),((5-M94)/5*4+1),((5-M94)/5*4+1)))/4*5,1)) -> 2.7 | L94: =VLOOKUP($B94,'Impact of the crisis'!$C$6:$N$170,12,FALSE) -> 2.6 | M94: =VLOOKUP($B94,'Impact of the crisis'!$C$6:$AB$170,26,FALSE) -> 2.7 | N94: =VLOOKUP($B94,'Conditions of people affected'!$C$6:$R$170,16,FALSE) -> x | O94: =VLOOKUP($B94,'Conditions of people affected'!$C$6:$R$170,9,FALSE) -> x | P94: =VLOOKUP($B94,'Conditions of people affected'!$C$6:$R$170,15,FALSE) -> x | Q94: =IF(OR(S94="x",R94="x"),R94,ROUND((5-GEOMEAN(((5-R94)/5*4+1),((5-S94)/5*4+1)))/4*5,1)) -> 3 | R94: =VLOOKUP($B94,'Complexity of the crisis'!$C$6:$AN$170,22,FALSE) -> 3.4 | S94: =VLOOKUP($B94,'Complexity of the crisis'!$C$6:$AN$170,38,FALSE) -> 2.5 | T94: =VLOOKUP(B94,Lists!$C$3:$E$163,3,FALSE) -> Middle east,Middle east | U94: =VLOOKUP(B94,'INFORM Severity - hidden'!$C$5:$V$170,20,FALSE) -> 44500
A95: {=IFERROR(INDEX(Lists!$B$2:$B$153,SMALL(IF(Lists!$I$2:$I$153="Individual",ROW(Lists!$B$2:$B$153)),ROW(91:91))-1,1),"")} -> Burundi and DRC refugees in Rwanda | B95: =VLOOKUP(A95,Lists!$B$2:$G$153,2,FALSE) -> RWA002 | C95: =VLOOKUP(B95,'INFORM Severity - hidden'!$C$5:$D$160,2,FALSE) -> Rwanda | D95: =VLOOKUP(A95,Lists!$B$2:$G$153,3,FALSE) -> RWA | E95: =VLOOKUP(A95,Lists!$B$2:$G$153,5,FALSE) -> International displacement | F95: =IF(OR(N95="x",K95="x"),"x",ROUND((5-GEOMEAN(((5-K95)/5*4+1),((5-N95)/5*4+1),((5-N95)/5*4+1)))/4*3.5+Q95*0.3,1)) -> 2.2 | G95: =IF(F95="x","x",ROUNDUP(F95,0)) -> 3 | H95: =IF(N95="x","x",IF(K95="x","x",(IF(G95=5,"Very High",IF(G95=4,"High",IF(G95=3,"Medium",IF(G95=2,"Low","Very Low"))))))) -> Medium | I95: =INDEX(Trends!$D$3:$D$404,MATCH(B95,Trends!$C$3:$C$404,0)) -> Stable | J95: =VLOOKUP($B95,Reliability!$A$3:$I$170,9,FALSE) -> Low | K95: =IF(OR(M95="x",L95="x"),"x",ROUND((5-GEOMEAN(((5-L95)/5*4+1),((5-M95)/5*4+1),((5-M95)/5*4+1)))/4*5,1)) -> 2.6 | L95: =VLOOKUP($B95,'Impact of the crisis'!$C$6:$N$170,12,FALSE) -> 2.1 | M95: =VLOOKUP($B95,'Impact of the crisis'!$C$6:$AB$170,26,FALSE) -> 2.8 | N95: =VLOOKUP($B95,'Conditions of people affected'!$C$6:$R$170,16,FALSE) -> 1.45 | O95: =VLOOKUP($B95,'Conditions of people affected'!$C$6:$R$170,9,FALSE) -> 1.9 | P95: =VLOOKUP($B95,'Conditions of people affected'!$C$6:$R$170,15,FALSE) -> 1 | Q95: =IF(OR(S95="x",R95="x"),R95,ROUND((5-GEOMEAN(((5-R95)/5*4+1),((5-S95)/5*4+1)))/4*5,1)) -> 3 | R95: =VLOOKUP($B95,'Complexity of the crisis'!$C$6:$AN$170,22,FALSE) -> 4 | S95: =VLOOKUP($B95,'Complexity of the crisis'!$C$6:$AN$170,38,FALSE) -> 1.5 | T95: =VLOOKUP(B95,Lists!$C$3:$E$163,3,FALSE) -> Africa | U95: =VLOOKUP(B95,'INFORM Severity - hidden'!$C$5:$V$170,20,FALSE) -> 44498
A96: {=IFERROR(INDEX(Lists!$B$2:$B$153,SMALL(IF(Lists!$I$2:$I$153="Individual",ROW(Lists!$B$2:$B$153)),ROW(92:92))-1,1),"")} -> Refugees in Sudan | B96: =VLOOKUP(A96,Lists!$B$2:$G$153,2,FALSE) -> SDN005 | C96: =VLOOKUP(B96,'INFORM Severity - hidden'!$C$5:$D$160,2,FALSE) -> Sudan | D96: =VLOOKUP(A96,Lists!$B$2:$G$153,3,FALSE) -> SDN | E96: =VLOOKUP(A96,Lists!$B$2:$G$153,5,FALSE) -> International displacement | F96: =IF(OR(N96="x",K96="x"),"x",ROUND((5-GEOMEAN(((5-K96)/5*4+1),((5-N96)/5*4+1),((5-N96)/5*4+1)))/4*3.5+Q96*0.3,1)) -> 3.4 | G96: =IF(F96="x","x",ROUNDUP(F96,0)) -> 4 | H96: =IF(N96="x","x",IF(K96="x","x",(IF(G96=5,"Very High",IF(G96=4,"High",IF(G96=3,"Medium",IF(G96=2,"Low","Very Low"))))))) -> High | I96: =INDEX(Trends!$D$3:$D$404,MATCH(B96,Trends!$C$3:$C$404,0)) -> Stable | J96: =VLOOKUP($B96,Reliability!$A$3:$I$170,9,FALSE) -> Very High | K96: =IF(OR(M96="x",L96="x"),"x",ROUND((5-GEOMEAN(((5-L96)/5*4+1),((5-M96)/5*4+1),((5-M96)/5*4+1)))/4*5,1)) -> 3.4 | L96: =VLOOKUP($B96,'Impact of the crisis'!$C$6:$N$170,12,FALSE) -> 2.1 | M96: =VLOOKUP($B96,'Impact of the crisis'!$C$6:$AB$170,26,FALSE) -> 3.9 | N96: =VLOOKUP($B96,'Conditions of people affected'!$C$6:$R$170,16,FALSE) -> 3.2 | O96: =VLOOKUP($B96,'Conditions of people affected'!$C$6:$R$170,9,FALSE) -> 3.4 | P96: =VLOOKUP($B96,'Conditions of people affected'!$C$6:$R$170,15,FALSE) -> 3 | Q96: =IF(OR(S96="x",R96="x"),R96,ROUND((5-GEOMEAN(((5-R96)/5*4+1),((5-S96)/5*4+1)))/4*5,1)) -> 3.7 | R96: =VLOOKUP($B96,'Complexity of the crisis'!$C$6:$AN$170,22,FALSE) -> 4.7 | S96: =VLOOKUP($B96,'Complexity of the crisis'!$C$6:$AN$170,38,FALSE) -> 2 | T96: =VLOOKUP(B96,Lists!$C$3:$E$163,3,FALSE) -> Africa | U96: =VLOOKUP(B96,'INFORM Severity - hidden'!$C$5:$V$170,20,FALSE) -> 44591
A97: {=IFERROR(INDEX(Lists!$B$2:$B$153,SMALL(IF(Lists!$I$2:$I$153="Individual",ROW(Lists!$B$2:$B$153)),ROW(93:93))-1,1),"")} -> Refugees from Ethiopia | B97: =VLOOKUP(A97,Lists!$B$2:$G$153,2,FALSE) -> SDN007 | C97: =VLOOKUP(B97,'INFORM Severity - hidden'!$C$5:$D$160,2,FALSE) -> Sudan | D97: =VLOOKUP(A97,Lists!$B$2:$G$153,3,FALSE) -> SDN | E97: =VLOOKUP(A97,Lists!$B$2:$G$153,5,FALSE) -> International displacement | F97: =IF(OR(N97="x",K97="x"),"x",ROUND((5-GEOMEAN(((5-K97)/5*4+1),((5-N97)/5*4+1),((5-N97)/5*4+1)))/4*3.5+Q97*0.3,1)) -> 2.6 | G97: =IF(F97="x","x",ROUNDUP(F97,0)) -> 3 | H97: =IF(N97="x","x",IF(K97="x","x",(IF(G97=5,"Very High",IF(G97=4,"High",IF(G97=3,"Medium",IF(G97=2,"Low","Very Low"))))))) -> Medium | I97: =INDEX(Trends!$D$3:$D$404,MATCH(B97,Trends!$C$3:$C$404,0)) -> Stable | J97: =VLOOKUP($B97,Reliability!$A$3:$I$170,9,FALSE) -> Very High | K97: =IF(OR(M97="x",L97="x"),"x",ROUND((5-GEOMEAN(((5-L97)/5*4+1),((5-M97)/5*4+1),((5-M97)/5*4+1)))/4*5,1)) -> 3 | L97: =VLOOKUP($B97,'Impact of the crisis'!$C$6:$N$170,12,FALSE) -> 2.4 | M97: =VLOOKUP($B97,'Impact of the crisis'!$C$6:$AB$170,26,FALSE) -> 3.3 | N97: =VLOOKUP($B97,'Conditions of people affected'!$C$6:$R$170,16,FALSE) -> 1.7 | O97: =VLOOKUP($B97,'Conditions of people affected'!$C$6:$R$170,9,FALSE) -> 1.4 | P97: =VLOOKUP($B97,'Conditions of people affected'!$C$6:$R$170,15,FALSE) -> 2 | Q97: =IF(OR(S97="x",R97="x"),R97,ROUND((5-GEOMEAN(((5-R97)/5*4+1),((5-S97)/5*4+1)))/4*5,1)) -> 3.7 | R97: =VLOOKUP($B97,'Complexity of the crisis'!$C$6:$AN$170,22,FALSE) -> 4.7 | S97: =VLOOKUP($B97,'Complexity of the crisis'!$C$6:$AN$170,38,FALSE) -> 2 | T97: =VLOOKUP(B97,Lists!$C$3:$E$163,3,FALSE) -> Africa | U97: =VLOOKUP(B97,'INFORM Severity - hidden'!$C$5:$V$170,20,FALSE) -> 44591
A98: {=IFERROR(INDEX(Lists!$B$2:$B$153,SMALL(IF(Lists!$I$2:$I$153="Individual",ROW(Lists!$B$2:$B$153)),ROW(94:94))-1,1),"")} -> Violence West-Darfur | B98: =VLOOKUP(A98,Lists!$B$2:$G$153,2,FALSE) -> SDN008 | C98: =VLOOKUP(B98,'INFORM Severity - hidden'!$C$5:$D$160,2,FALSE) -> Sudan | D98: =VLOOKUP(A98,Lists!$B$2:$G$153,3,FALSE) -> SDN | E98: =VLOOKUP(A98,Lists!$B$2:$G$153,5,FALSE) -> Other type of violence | F98: =IF(OR(N98="x",K98="x"),"x",ROUND((5-GEOMEAN(((5-K98)/5*4+1),((5-N98)/5*4+1),((5-N98)/5*4+1)))/4*3.5+Q98*0.3,1)) -> 3.7 | G98: =IF(F98="x","x",ROUNDUP(F98,0)) -> 4 | H98: =IF(N98="x","x",IF(K98="x","x",(IF(G98=5,"Very High",IF(G98=4,"High",IF(G98=3,"Medium",IF(G98=2,"Low","Very Low"))))))) -> High | I98: =INDEX(Trends!$D$3:$D$404,MATCH(B98,Trends!$C$3:$C$404,0)) -> Increasing | J98: =VLOOKUP($B98,Reliability!$A$3:$I$170,9,FALSE) -> Very High | K98: =IF(OR(M98="x",L98="x"),"x",ROUND((5-GEOMEAN(((5-L98)/5*4+1),((5-M98)/5*4+1),((5-M98)/5*4+1)))/4*5,1)) -> 3.5 | L98: =VLOOKUP($B98,'Impact of the crisis'!$C$6:$N$170,12,FALSE) -> 1.1 | M98: =VLOOKUP($B98,'Impact of the crisis'!$C$6:$AB$170,26,FALSE) -> 4.2 | N98: =VLOOKUP($B98,'Conditions of people affected'!$C$6:$R$170,16,FALSE) -> 3.65 | O98: =VLOOKUP($B98,'Conditions of people affected'!$C$6:$R$170,9,FALSE) -> 3.3 | P98: =VLOOKUP($B98,'Conditions of people affected'!$C$6:$R$170,15,FALSE) -> 4 | Q98: =IF(OR(S98="x",R98="x"),R98,ROUND((5-GEOMEAN(((5-R98)/5*4+1),((5-S98)/5*4+1)))/4*5,1)) -> 3.8 | R98: =VLOOKUP($B98,'Complexity of the crisis'!$C$6:$AN$170,22,FALSE) -> 4.7 | S98: =VLOOKUP($B98,'Complexity of the crisis'!$C$6:$AN$170,38,FALSE) -> 2.5 | T98: =VLOOKUP(B98,Lists!$C$3:$E$163,3,FALSE) -> Africa | U98: =VLOOKUP(B98,'INFORM Severity - hidden'!$C$5:$V$170,20,FALSE) -> 44591
A99: {=IFERROR(INDEX(Lists!$B$2:$B$153,SMALL(IF(Lists!$I$2:$I$153="Individual",ROW(Lists!$B$2:$B$153)),ROW(95:95))-1,1),"")} -> Drought in Senegal | B99: =VLOOKUP(A99,Lists!$B$2:$G$153,2,FALSE) -> SEN002 | C99: =VLOOKUP(B99,'INFORM Severity - hidden'!$C$5:$D$160,2,FALSE) -> Senegal | D99: =VLOOKUP(A99,Lists!$B$2:$G$153,3,FALSE) -> SEN | E99: =VLOOKUP(A99,Lists!$B$2:$G$153,5,FALSE) -> Drought | F99: =IF(OR(N99="x",K99="x"),"x",ROUND((5-GEOMEAN(((5-K99)/5*4+1),((5-N99)/5*4+1),((5-N99)/5*4+1)))/4*3.5+Q99*0.3,1)) -> 2.4 | G99: =IF(F99="x","x",ROUNDUP(F99,0)) -> 3 | H99: =IF(N99="x","x",IF(K99="x","x",(IF(G99=5,"Very High",IF(G99=4,"High",IF(G99=3,"Medium",IF(G99=2,"Low","Very Low"))))))) -> Medium | I99: =INDEX(Trends!$D$3:$D$404,MATCH(B99,Trends!$C$3:$C$404,0)) -> Stable | J99: =VLOOKUP($B99,Reliability!$A$3:$I$170,9,FALSE) -> Medium | K99: =IF(OR(M99="x",L99="x"),"x",ROUND((5-GEOMEAN(((5-L99)/5*4+1),((5-M99)/5*4+1),((5-M99)/5*4+1)))/4*5,1)) -> 2.7 | L99: =VLOOKUP($B99,'Impact of the crisis'!$C$6:$N$170,12,FALSE) -> 4.5 | M99: =VLOOKUP($B99,'Impact of the crisis'!$C$6:$AB$170,26,FALSE) -> 1.2 | N99: =VLOOKUP($B99,'Conditions of people affected'!$C$6:$R$170,16,FALSE) -> 2.4 | O99: =VLOOKUP($B99,'Conditions of people affected'!$C$6:$R$170,9,FALSE) -> 2.8 | P99: =VLOOKUP($B99,'Conditions of people affected'!$C$6:$R$170,15,FALSE) -> 2 | Q99: =IF(OR(S99="x",R99="x"),R99,ROUND((5-GEOMEAN(((5-R99)/5*4+1),((5-S99)/5*4+1)))/4*5,1)) -> 2.3 | R99: =VLOOKUP($B99,'Complexity of the crisis'!$C$6:$AN$170,22,FALSE) -> 2.1 | S99: =VLOOKUP($B99,'Complexity of the crisis'!$C$6:$AN$170,38,FALSE) -> 2.5 | T99: =VLOOKUP(B99,Lists!$C$3:$E$163,3,FALSE) -> Africa | U99: =VLOOKUP(B99,'INFORM Severity - hidden'!$C$5:$V$170,20,FALSE) -> 44496
A100: {=IFERROR(INDEX(Lists!$B$2:$B$153,SMALL(IF(Lists!$I$2:$I$153="Individual",ROW(Lists!$B$2:$B$153)),ROW(96:96))-1,1),"")} -> Complex crisis in El Salvador | B100: =VLOOKUP(A100,Lists!$B$2:$G$153,2,FALSE) -> SLV001 | C100: =VLOOKUP(B100,'INFORM Severity - hidden'!$C$5:$D$160,2,FALSE) -> El Salvador | D100: =VLOOKUP(A100,Lists!$B$2:$G$153,3,FALSE) -> SLV | E100: =VLOOKUP(A100,Lists!$B$2:$G$153,5,FALSE) -> Complex crisis | F100: =IF(OR(N100="x",K100="x"),"x",ROUND((5-GEOMEAN(((5-K100)/5*4+1),((5-N100)/5*4+1),((5-N100)/5*4+1)))/4*3.5+Q100*0.3,1)) -> 3.2 | G100: =IF(F100="x","x",ROUNDUP(F100,0)) -> 4 | H100: =IF(N100="x","x",IF(K100="x","x",(IF(G100=5,"Very High",IF(G100=4,"High",IF(G100=3,"Medium",IF(G100=2,"Low","Very Low"))))))) -> High | I100: =INDEX(Trends!$D$3:$D$404,MATCH(B100,Trends!$C$3:$C$404,0)) -> Increasing | J100: =VLOOKUP($B100,Reliability!$A$3:$I$170,9,FALSE) -> Very High | K100: =IF(OR(M100="x",L100="x"),"x",ROUND((5-GEOMEAN(((5-L100)/5*4+1),((5-M100)/5*4+1),((5-M100)/5*4+1)))/4*5,1)) -> 3.4 | L100: =VLOOKUP($B100,'Impact of the crisis'!$C$6:$N$170,12,FALSE) -> 3.8 | M100: =VLOOKUP($B100,'Impact of the crisis'!$C$6:$AB$170,26,FALSE) -> 3.1 | N100: =VLOOKUP($B100,'Conditions of people affected'!$C$6:$R$170,16,FALSE) -> 3.35 | O100: =VLOOKUP($B100,'Conditions of people affected'!$C$6:$R$170,9,FALSE) -> 3.7 | P100: =VLOOKUP($B100,'Conditions of people affected'!$C$6:$R$170,15,FALSE) -> 3 | Q100: =IF(OR(S100="x",R100="x"),R100,ROUND((5-GEOMEAN(((5-R100)/5*4+1),((5-S100)/5*4+1)))/4*5,1)) -> 2.8 | R100: =VLOOKUP($B100,'Complexity of the crisis'!$C$6:$AN$170,22,FALSE) -> 3 | S100: =VLOOKUP($B100,'Complexity of the crisis'!$C$6:$AN$170,38,FALSE) -> 2.5 | T100: =VLOOKUP(B100,Lists!$C$3:$E$163,3,FALSE) -> Americas | U100: =VLOOKUP(B100,'INFORM Severity - hidden'!$C$5:$V$170,20,FALSE) -> 44516
...

Sheet INFORM Severity - country
A1: ="INFORM Severity Index - all countries. Release: "&About!$A$5&"" -> INFORM Severity Index - all countries. Release: January 2022
A2: CRISIS | B2: CRISIS ID | C2: COUNTRY | D2: ISO3 | E2: TYPE OF CRISIS | F2: INFORM Severity Index | G2: INFORM Severity category | H2: INFORM Severity category | I2: Trend (last 3 months) | J2: Reliability | K2: Impact of the crisis | L2: Geographical | M2: Human | N2: Conditions of people affected | O2: People in need | P2: Concentration of conditions | Q2: Complexity of the crisis | R2: Society and safety | S2: Operating environment | T2: Regions | U2: Last updated
A3: Weights
A4: (a-z) | D4: (a-z) | F4: (1-5) | G4: (1-5) | H4: (Very Low-Very High) | I4: (Decreasing-Stable-Increasing) | J4: (Very Low-Very High) | K4: (1-5) | L4: (1-5) | M4: (1-5) | N4: (1-5) | O4: (1-5) | P4: (1-5) | Q4: (1-5) | R4: (1-5) | S4: (1-5)
A5: {=IFERROR(INDEX(Lists!$B$2:$B$153,SMALL(IF(Lists!$H$2:$H$153="Yes",ROW(Lists!$B$2:$B$153)),ROW(1:1))-1,1),"")} -> Complex crisis in Afghanistan | B5: =VLOOKUP(A5,Lists!$B$2:$G$153,2,FALSE) -> AFG001 | C5: =VLOOKUP(B5,'INFORM Severity - hidden'!$C$5:$D$160,2,FALSE) -> Afghanistan | D5: =VLOOKUP(A5,Lists!$B$2:$G$153,3,FALSE) -> AFG | E5: =VLOOKUP(A5,Lists!$B$2:$G$153,5,FALSE) -> Complex crisis | F5: =IF(OR(N5="x",K5="x"),"x",ROUND((5-GEOMEAN(((5-K5)/5*4+1),((5-N5)/5*4+1),((5-N5)/5*4+1)))/4*3.5+Q5*0.3,1)) -> 4.7 | G5: =IF(F5="x","x",ROUNDUP(F5,0)) -> 5 | H5: =IF(N5="x","x",IF(K5="x","x",(IF(G5=5,"Very High",IF(G5=4,"High",IF(G5=3,"Medium",IF(G5=2,"Low","Very Low"))))))) -> Very High | I5: =INDEX(Trends!$D$3:$D$404,MATCH(B5,Trends!$C$3:$C$404,0)) -> Stable | J5: =VLOOKUP($B5,Reliability!$A$3:$I$170,9,FALSE) -> High | K5: =IF(OR(M5="x",L5="x"),"x",ROUND((5-GEOMEAN(((5-L5)/5*4+1),((5-M5)/5*4+1),((5-M5)/5*4+1)))/4*5,1)) -> 4.8 | L5: =VLOOKUP($B5,'Impact of the crisis'!$C$6:$N$170,12,FALSE) -> 4.9 | M5: =VLOOKUP($B5,'Impact of the crisis'!$C$6:$AB$170,26,FALSE) -> 4.8 | N5: =VLOOKUP($B5,'Conditions of people affected'!$C$6:$R$170,16,FALSE) -> 4.5 | O5: =VLOOKUP($B5,'Conditions of people affected'!$C$6:$R$170,9,FALSE) -> 5 | P5: =VLOOKUP($B5,'Conditions of people affected'!$C$6:$R$170,15,FALSE) -> 4 | Q5: =IF(OR(S5="x",R5="x"),R5,ROUND((5-GEOMEAN(((5-R5)/5*4+1),((5-S5)/5*4+1)))/4*5,1)) -> 4.9 | R5: =VLOOKUP($B5,'Complexity of the crisis'!$C$6:$AN$170,22,FALSE) -> 4.8 | S5: =VLOOKUP($B5,'Complexity of the crisis'!$C$6:$AN$170,38,FALSE) -> 5 | T5: =VLOOKUP(B5,Lists!$C$3:$E$163,3,FALSE) -> Asia | U5: =VLOOKUP(B5,'INFORM Severity - hidden'!$C$5:$V$170,20,FALSE) -> 44571
A6: {=IFERROR(INDEX(Lists!$B$2:$B$153,SMALL(IF(Lists!$H$2:$H$153="Yes",ROW(Lists!$B$2:$B$153)),ROW(2:2))-1,1),"")} -> Drought in South-West Angola | B6: =VLOOKUP(A6,Lists!$B$2:$G$153,2,FALSE) -> AGO002 | C6: =VLOOKUP(B6,'INFORM Severity - hidden'!$C$5:$D$160,2,FALSE) -> Angola | D6: =VLOOKUP(A6,Lists!$B$2:$G$153,3,FALSE) -> AGO | E6: =VLOOKUP(A6,Lists!$B$2:$G$153,5,FALSE) -> Food Security | F6: =IF(OR(N6="x",K6="x"),"x",ROUND((5-GEOMEAN(((5-K6)/5*4+1),((5-N6)/5*4+1),((5-N6)/5*4+1)))/4*3.5+Q6*0.3,1)) -> 3.2 | G6: =IF(F6="x","x",ROUNDUP(F6,0)) -> 4 | H6: =IF(N6="x","x",IF(K6="x","x",(IF(G6=5,"Very High",IF(G6=4,"High",IF(G6=3,"Medium",IF(G6=2,"Low","Very Low"))))))) -> High | I6: =INDEX(Trends!$D$3:$D$404,MATCH(B6,Trends!$C$3:$C$404,0)) -> - | J6: =VLOOKUP($B6,Reliability!$A$3:$I$170,9,FALSE) -> Very High | K6: =IF(OR(M6="x",L6="x"),"x",ROUND((5-GEOMEAN(((5-L6)/5*4+1),((5-M6)/5*4+1),((5-M6)/5*4+1)))/4*5,1)) -> 2 | L6: =VLOOKUP($B6,'Impact of the crisis'!$C$6:$N$170,12,FALSE) -> 1.7 | M6: =VLOOKUP($B6,'Impact of the crisis'!$C$6:$AB$170,26,FALSE) -> 2.2 | N6: =VLOOKUP($B6,'Conditions of people affected'!$C$6:$R$170,16,FALSE) -> 3.8 | O6: =VLOOKUP($B6,'Conditions of people affected'!$C$6:$R$170,9,FALSE) -> 3.6 | P6: =VLOOKUP($B6,'Conditions of people affected'!$C$6:$R$170,15,FALSE) -> 4 | Q6: =IF(OR(S6="x",R6="x"),R6,ROUND((5-GEOMEAN(((5-R6)/5*4+1),((5-S6)/5*4+1)))/4*5,1)) -> 2.9 | R6: =VLOOKUP($B6,'Complexity of the crisis'!$C$6:$AN$170,22,FALSE) -> 3.6 | S6: =VLOOKUP($B6,'Complexity of the crisis'!$C$6:$AN$170,38,FALSE) -> 2 | T6: =VLOOKUP(B6,Lists!$C$3:$E$163,3,FALSE) -> Africa | U6: =VLOOKUP(B6,'INFORM Severity - hidden'!$C$5:$V$170,20,FALSE) -> 44550
